Workbook

Sheet Cuotas Estudiantes Pregrado
A2: MUESTRA POR SEMESTRE PREGRADO
A3: NOMBRE DEL PROGRAMA | B3: SEMESTRE 2 | C3: SEMESTRE 3 | D3: SEMESTRE 4 | E3: SEMESTRE 5 | F3: SEMESTRE 6 | G3: SEMESTRE 7 | H3: SEMESTRE 8 | I3: SEMESTRE 9 | J3: SEMESTRE 10 | K3: SEMESTRE 11 | L3: SEMESTRE 12 | M3: TOTAL POBLACIÓN | N3: MUESTRA | O3: ALCANCE | P3: ME (95%)
A4: Administración & Servicio | B4: 10 | C4: 9 | D4: 7 | E4: 9 | F4: 12 | G4: 12 | H4: 12 | M4: 84 | N4: =SUM(B4:L4) -> 71 | O4: =N4/M4 -> 0.8452381 | P4: =IFERROR((((1.96^2*0.5*0.5*($M4-N4))/(N4*($M4-1)))^0.5),"") -> 0.046028787
A5: Administración de Empresas | B5: 24 | C5: 24 | D5: 21 | E5: 22 | F5: 19 | G5: 23 | H5: 29 | M5: 253 | N5: =SUM(B5:L5) -> 162 | O5: =N5/M5 -> 0.64031621 | P5: =IFERROR((((1.96^2*0.5*0.5*($M5-N5))/(N5*($M5-1)))^0.5),"") -> 0.046268881
A6: Administración de Mercadeo y Logística Internacionales | B6: 34 | C6: 22 | D6: 37 | E6: 28 | F6: 29 | G6: 20 | H6: 25 | M6: 344 | N6: =SUM(B6:L6) -> 195 | O6: =N6/M6 -> 0.56686047 | P6: =IFERROR((((1.96^2*0.5*0.5*($M6-N6))/(N6*($M6-1)))^0.5),"") -> 0.046254591
A7: Administración de Negocios Internacionales | B7: 47 | C7: 36 | D7: 37 | E7: 34 | F7: 39 | G7: 28 | H7: 33 | M7: 580 | N7: =SUM(B7:L7) -> 254 | O7: =N7/M7 -> 0.43793103 | P7: =IFERROR((((1.96^2*0.5*0.5*($M7-N7))/(N7*($M7-1)))^0.5),"") -> 0.046140122
A8: Economía y Finanzas Internacionales | B8: 32 | C8: 26 | D8: 21 | E8: 13 | F8: 18 | G8: 11 | H8: 25 | M8: 215 | N8: =SUM(B8:L8) -> 146 | O8: =N8/M8 -> 0.67906977 | P8: =IFERROR((((1.96^2*0.5*0.5*($M8-N8))/(N8*($M8-1)))^0.5),"") -> 0.046053995
A9: Gastronomía | B9: 41 | C9: 16 | D9: 27 | E9: 22 | F9: 19 | G9: 15 | H9: 18 | M9: 240 | N9: =SUM(B9:L9) -> 158 | O9: =N9/M9 -> 0.65833333 | P9: =IFERROR((((1.96^2*0.5*0.5*($M9-N9))/(N9*($M9-1)))^0.5),"") -> 0.045667318
A10: Comunicación Corporativa | B10: 19 | C10: 25 | D10: 21 | E10: 19 | F10: 24 | G10: 13 | H10: 21 | M10: 206 | N10: =SUM(B10:L10) -> 142 | O10: =N10/M10 -> 0.68932039 | P10: =IFERROR((((1.96^2*0.5*0.5*($M10-N10))/(N10*($M10-1)))^0.5),"") -> 0.045950999
A11: Comunicación Audiovisual y Multimedios | B11: 39 | C11: 49 | D11: 37 | E11: 38 | F11: 30 | G11: 34 | H11: 32 | M11: 606 | N11: =SUM(B11:L11) -> 259 | O11: =N11/M11 -> 0.42739274 | P11: =IFERROR((((1.96^2*0.5*0.5*($M11-N11))/(N11*($M11-1)))^0.5),"") -> 0.046117233
A12: Comunicación Social y Periodismo | B12: 27 | C12: 23 | D12: 32 | E12: 24 | F12: 33 | G12: 30 | H12: 31 | M12: 360 | N12: =SUM(B12:L12) -> 200 | O12: =N12/M12 -> 0.55555556 | P12: =IFERROR((((1.96^2*0.5*0.5*($M12-N12))/(N12*($M12-1)))^0.5),"") -> 0.04626194
A13: Ciencias Políticas | B13: 11 | C13: 10 | D13: 6 | E13: 17 | F13: 8 | G13: 9 | H13: 10 | M13: 85 | N13: =SUM(B13:L13) -> 71 | O13: =N13/M13 -> 0.83529412 | P13: =IFERROR((((1.96^2*0.5*0.5*($M13-N13))/(N13*($M13-1)))^0.5),"") -> 0.047481155
A14: Derecho | B14: 34 | C14: 16 | D14: 21 | E14: 20 | F14: 23 | G14: 20 | H14: 30 | I14: 19 | M14: 306 | N14: =SUM(B14:L14) -> 183 | O14: =N14/M14 -> 0.59803922 | P14: =IFERROR((((1.96^2*0.5*0.5*($M14-N14))/(N14*($M14-1)))^0.5),"") -> 0.046004802
A15: Licenciatura en Educación Infantil | B15: 15 | C15: 5 | D15: 5 | E15: 9 | F15: 12 | G15: 6 | H15: 8 | I15: 1 | J15: 0 | M15: 70 | N15: =SUM(B15:L15) -> 61 | O15: =N15/M15 -> 0.87142857 | P15: =IFERROR((((1.96^2*0.5*0.5*($M15-N15))/(N15*($M15-1)))^0.5),"") -> 0.045316657
A16: Enfermería | B16: 24 | C16: 16 | D16: 21 | E16: 14 | F16: 10 | G16: 14 | H16: 15 | M16: 150 | N16: =SUM(B16:L16) -> 114 | O16: =N16/M16 -> 0.76 | P16: =IFERROR((((1.96^2*0.5*0.5*($M16-N16))/(N16*($M16-1)))^0.5),"") -> 0.045116122
A17: Fisioterapia | B17: 20 | C17: 22 | D17: 33 | E17: 21 | F17: 18 | G17: 25 | H17: 11 | M17: 224 | N17: =SUM(B17:L17) -> 150 | O17: =N17/M17 -> 0.66964286 | P17: =IFERROR((((1.96^2*0.5*0.5*($M17-N17))/(N17*($M17-1)))^0.5),"") -> 0.046093944
A18: Filosofía | B18: 4 | C18: 3 | D18: 7 | E18: 6 | F18: 5 | G18: 1 | H18: 3 | I18: 5 | M18: 34 | N18: =SUM(B18:L18) -> 34 | O18: =N18/M18 -> 1 | P18: =IFERROR((((1.96^2*0.5*0.5*($M18-N18))/(N18*($M18-1)))^0.5),"") -> 0
A19: Ingeniería Civil | B19: 14 | C19: 8 | D19: 8 | E19: 14 | F19: 20 | G19: 8 | H19: 19 | M19: 114 | N19: =SUM(B19:L19) -> 91 | O19: =N19/M19 -> 0.79824561 | P19: =IFERROR((((1.96^2*0.5*0.5*($M19-N19))/(N19*($M19-1)))^0.5),"") -> 0.046347902
A20: Ingeniería Industrial | B20: 30 | C20: 19 | D20: 30 | E20: 12 | F20: 40 | G20: 20 | H20: 23 | M20: 287 | N20: =SUM(B20:L20) -> 174 | O20: =N20/M20 -> 0.60627178 | P20: =IFERROR((((1.96^2*0.5*0.5*($M20-N20))/(N20*($M20-1)))^0.5),"") -> 0.046699008
A21: Ingeniería Informática | B21: 39 | C21: 28 | D21: 37 | E21: 35 | F21: 16 | G21: 12 | H21: 22 | M21: 322 | N21: =SUM(B21:L21) -> 189 | O21: =N21/M21 -> 0.58695652 | P21: =IFERROR((((1.96^2*0.5*0.5*($M21-N21))/(N21*($M21-1)))^0.5),"") -> 0.045884761
A22: Ingeniería Mecánica | B22: 23 | C22: 19 | D22: 13 | E22: 9 | F22: 22 | G22: 15 | H22: 25 | M22: 175 | N22: =SUM(B22:L22) -> 126 | O22: =N22/M22 -> 0.72 | P22: =IFERROR((((1.96^2*0.5*0.5*($M22-N22))/(N22*($M22-1)))^0.5),"") -> 0.046330205
A23: Ingeniería de Bioproducción / Producción Agroindustrial | B23: 6 | C23: 2 | D23: 2 | E23: 6 | F23: 3 | G23: 1 | H23: 9 | I23: 4 | M23: 47 | N23: =SUM(B23:L23) -> 33 | O23: =N23/M23 -> 0.70212766 | P23: =IFERROR((((1.96^2*0.5*0.5*($M23-N23))/(N23*($M23-1)))^0.5),"") -> 0.094113995
A24: Ingeniería Química | B24: 15 | C24: 17 | D24: 19 | E24: 24 | F24: 18 | G24: 24 | H24: 20 | M24: 197 | N24: =SUM(B24:L24) -> 137 | O24: =N24/M24 -> 0.69543147 | P24: =IFERROR((((1.96^2*0.5*0.5*($M24-N24))/(N24*($M24-1)))^0.5),"") -> 0.046324782
A25: Medicina | B25: 43 | C25: 26 | D25: 23 | E25: 37 | F25: 31 | G25: 30 | H25: 33 | I25: 30 | J25: 22 | K25: 31 | M25: 972 | N25: =SUM(B25:K25) -> 306 | O25: =N25/M25 -> 0.31481481 | P25: =IFERROR((((1.96^2*0.5*0.5*($M25-N25))/(N25*($M25-1)))^0.5),"") -> 0.046397316
A26: Psicología | B26: 33 | C26: 22 | D26: 31 | E26: 29 | F26: 19 | G26: 30 | H26: 31 | M26: 340 | N26: =SUM(B26:L26) -> 195 | O26: =N26/M26 -> 0.57352941 | P26: =IFERROR((((1.96^2*0.5*0.5*($M26-N26))/(N26*($M26-1)))^0.5),"") -> 0.045897911
A27: Ciencia de Datos | B27: 21 | C27: 1 | D27: 1 | E27: 2 | F27: 0 | G27: 0 | H27: 0 | M27: 26 | N27: =SUM(B27:L27) -> 25 | O27: =N27/M27 -> 0.96153846 | P27: =IFERROR((((1.96^2*0.5*0.5*($M27-N27))/(N27*($M27-1)))^0.5),"") -> 0.0392
A28: Licenciatura en Ciencias Naturales | B28: 0 | C28: 3 | D28: 1 | E28: 3 | F28: 4 | G28: 0 | H28: 11 | I28: 6 | M28: 27 | N28: =SUM(B28:L28) -> 28 | O28: =N28/M28 -> 1.037037 | P28: =IFERROR((((1.96^2*0.5*0.5*($M28-N28))/(N28*($M28-1)))^0.5),"")
M29: =SUM(M4:M28) -> 6264 | N29: =SUM(N4:N28) -> 3504
A31: NOMBRE DEL PROGRAMA | B31: SEMESTRE 2 | C31: SEMESTRE 3 | D31: SEMESTRE 4 | E31: SEMESTRE 5 | F31: SEMESTRE 6 | G31: SEMESTRE 7 | H31: SEMESTRE 8 | I31: SEMESTRE 9 | J31: SEMESTRE 10 | K31: SEMESTRE 11 | L31: SEMESTRE 12 | M31: TOTAL POBLACIÓN
A32: Administración & Servicio | B32: =VLOOKUP($A32,'BDD Esudiantes'!$E$3:$P$30,2,0) -> 9 | C32: =VLOOKUP($A32,'BDD Esudiantes'!$E$3:$P$30,3,0) -> 11 | D32: =VLOOKUP($A32,'BDD Esudiantes'!$E$3:$P$30,4,0) -> 3 | E32: =VLOOKUP($A32,'BDD Esudiantes'!$E$3:$P$30,5,0) -> 7 | F32: =VLOOKUP($A32,'BDD Esudiantes'!$E$3:$P$30,6,0) -> 12 | G32: =VLOOKUP($A32,'BDD Esudiantes'!$E$3:$P$30,7,0) -> 12 | H32: =VLOOKUP($A32,'BDD Esudiantes'!$E$3:$P$30,8,0) -> 12 | M32: 82 | N32: =SUM(B32:L32) -> 66 | O32: =VLOOKUP($A32,'BDD Esudiantes'!$E$3:$P$30,12,0) -> 66 | P32: =O32-N32 -> 0 | Q32: =VLOOKUP(A32,'Resumen Estudiantes y Profesore'!$B$3:$F$27,5,0) -> 66 | R32: =Q32-O32 -> 0
A33: Administración de Empresas | B33: =VLOOKUP($A33,'BDD Esudiantes'!$E$3:$P$30,2,0) -> 23 | C33: =VLOOKUP($A33,'BDD Esudiantes'!$E$3:$P$30,3,0) -> 12 | D33: =VLOOKUP($A33,'BDD Esudiantes'!$E$3:$P$30,4,0) -> 22 | E33: =VLOOKUP($A33,'BDD Esudiantes'!$E$3:$P$30,5,0) -> 18 | F33: =VLOOKUP($A33,'BDD Esudiantes'!$E$3:$P$30,6,0) -> 23 | G33: =VLOOKUP($A33,'BDD Esudiantes'!$E$3:$P$30,7,0) -> 19 | H33: =VLOOKUP($A33,'BDD Esudiantes'!$E$3:$P$30,8,0) -> 30 | M33: 253 | N33: =SUM(B33:L33) -> 147 | O33: =VLOOKUP($A33,'BDD Esudiantes'!$E$3:$P$30,12,0) -> 147 | P33: =O33-N33 -> 0 | Q33: =VLOOKUP(A33,'Resumen Estudiantes y Profesore'!$B$3:$F$27,5,0) -> 147 | R33: =Q33-O33 -> 0
A34: Administración de Mercadeo y Logística Internacionales | B34: =VLOOKUP($A34,'BDD Esudiantes'!$E$3:$P$30,2,0) -> 2 | C34: =VLOOKUP($A34,'BDD Esudiantes'!$E$3:$P$30,3,0) -> 29 | D34: =VLOOKUP($A34,'BDD Esudiantes'!$E$3:$P$30,4,0) -> 47 | E34: =VLOOKUP($A34,'BDD Esudiantes'!$E$3:$P$30,5,0) -> 35 | F34: =VLOOKUP($A34,'BDD Esudiantes'!$E$3:$P$30,6,0) -> 53 | G34: =VLOOKUP($A34,'BDD Esudiantes'!$E$3:$P$30,7,0) -> 29 | H34: =VLOOKUP($A34,'BDD Esudiantes'!$E$3:$P$30,8,0) -> 28 | M34: 356 | N34: =SUM(B34:L34) -> 223 | O34: =VLOOKUP($A34,'BDD Esudiantes'!$E$3:$P$30,12,0) -> 223 | P34: =O34-N34 -> 0 | Q34: =VLOOKUP(A34,'Resumen Estudiantes y Profesore'!$B$3:$F$27,5,0) -> 223 | R34: =Q34-O34 -> 0
A35: Administración de Negocios Internacionales | B35: =VLOOKUP($A35,'BDD Esudiantes'!$E$3:$P$30,2,0) -> 48 | C35: =VLOOKUP($A35,'BDD Esudiantes'!$E$3:$P$30,3,0) -> 50 | D35: =VLOOKUP($A35,'BDD Esudiantes'!$E$3:$P$30,4,0) -> 65 | E35: =VLOOKUP($A35,'BDD Esudiantes'!$E$3:$P$30,5,0) -> 48 | F35: =VLOOKUP($A35,'BDD Esudiantes'!$E$3:$P$30,6,0) -> 28 | G35: =VLOOKUP($A35,'BDD Esudiantes'!$E$3:$P$30,7,0) -> 29 | H35: =VLOOKUP($A35,'BDD Esudiantes'!$E$3:$P$30,8,0) -> 31 | M35: 582 | N35: =SUM(B35:L35) -> 299 | O35: =VLOOKUP($A35,'BDD Esudiantes'!$E$3:$P$30,12,0) -> 299 | P35: =O35-N35 -> 0 | Q35: =VLOOKUP(A35,'Resumen Estudiantes y Profesore'!$B$3:$F$27,5,0) -> 299 | R35: =Q35-O35 -> 0
A36: Economía y Finanzas Internacionales | B36: =VLOOKUP($A36,'BDD Esudiantes'!$E$3:$P$30,2,0) -> 27 | C36: =VLOOKUP($A36,'BDD Esudiantes'!$E$3:$P$30,3,0) -> 17 | D36: =VLOOKUP($A36,'BDD Esudiantes'!$E$3:$P$30,4,0) -> 34 | E36: =VLOOKUP($A36,'BDD Esudiantes'!$E$3:$P$30,5,0) -> 14 | F36: =VLOOKUP($A36,'BDD Esudiantes'!$E$3:$P$30,6,0) -> 23 | G36: =VLOOKUP($A36,'BDD Esudiantes'!$E$3:$P$30,7,0) -> 13 | H36: =VLOOKUP($A36,'BDD Esudiantes'!$E$3:$P$30,8,0) -> 13 | M36: 209 | N36: =SUM(B36:L36) -> 141 | O36: =VLOOKUP($A36,'BDD Esudiantes'!$E$3:$P$30,12,0) -> 141 | P36: =O36-N36 -> 0 | Q36: =VLOOKUP(A36,'Resumen Estudiantes y Profesore'!$B$3:$F$27,5,0) -> 141 | R36: =Q36-O36 -> 0
A37: Gastronomía | B37: =VLOOKUP($A37,'BDD Esudiantes'!$E$3:$P$30,2,0) -> 31 | C37: =VLOOKUP($A37,'BDD Esudiantes'!$E$3:$P$30,3,0) -> 17 | D37: =VLOOKUP($A37,'BDD Esudiantes'!$E$3:$P$30,4,0) -> 25 | E37: =VLOOKUP($A37,'BDD Esudiantes'!$E$3:$P$30,5,0) -> 16 | F37: =VLOOKUP($A37,'BDD Esudiantes'!$E$3:$P$30,6,0) -> 23 | G37: =VLOOKUP($A37,'BDD Esudiantes'!$E$3:$P$30,7,0) -> 12 | H37: =VLOOKUP($A37,'BDD Esudiantes'!$E$3:$P$30,8,0) -> 7 | M37: 234 | N37: =SUM(B37:L37) -> 131 | O37: =VLOOKUP($A37,'BDD Esudiantes'!$E$3:$P$30,12,0) -> 131 | P37: =O37-N37 -> 0 | Q37: =VLOOKUP(A37,'Resumen Estudiantes y Profesore'!$B$3:$F$27,5,0) -> 131 | R37: =Q37-O37 -> 0
A38: Comunicación Corporativa | B38: =VLOOKUP($A38,'BDD Esudiantes'!$E$3:$P$30,2,0) -> 12 | C38: =VLOOKUP($A38,'BDD Esudiantes'!$E$3:$P$30,3,0) -> 26 | D38: =VLOOKUP($A38,'BDD Esudiantes'!$E$3:$P$30,4,0) -> 7 | E38: =VLOOKUP($A38,'BDD Esudiantes'!$E$3:$P$30,5,0) -> 16 | F38: =VLOOKUP($A38,'BDD Esudiantes'!$E$3:$P$30,6,0) -> 22 | G38: =VLOOKUP($A38,'BDD Esudiantes'!$E$3:$P$30,7,0) -> 15 | H38: =VLOOKUP($A38,'BDD Esudiantes'!$E$3:$P$30,8,0) -> 14 | M38: 195 | N38: =SUM(B38:L38) -> 112 | O38: =VLOOKUP($A38,'BDD Esudiantes'!$E$3:$P$30,12,0) -> 112 | P38: =O38-N38 -> 0 | Q38: =VLOOKUP(A38,'Resumen Estudiantes y Profesore'!$B$3:$F$27,5,0) -> 112 | R38: =Q38-O38 -> 0
A39: Comunicación Audiovisual y Multimedios | B39: =VLOOKUP($A39,'BDD Esudiantes'!$E$3:$P$30,2,0) -> 56 | C39: =VLOOKUP($A39,'BDD Esudiantes'!$E$3:$P$30,3,0) -> 35 | D39: =VLOOKUP($A39,'BDD Esudiantes'!$E$3:$P$30,4,0) -> 69 | E39: =VLOOKUP($A39,'BDD Esudiantes'!$E$3:$P$30,5,0) -> 35 | F39: =VLOOKUP($A39,'BDD Esudiantes'!$E$3:$P$30,6,0) -> 21 | G39: =VLOOKUP($A39,'BDD Esudiantes'!$E$3:$P$30,7,0) -> 18 | H39: =VLOOKUP($A39,'BDD Esudiantes'!$E$3:$P$30,8,0) -> 33 | M39: 606 | N39: =SUM(B39:L39) -> 267 | O39: =VLOOKUP($A39,'BDD Esudiantes'!$E$3:$P$30,12,0) -> 267 | P39: =O39-N39 -> 0 | Q39: =VLOOKUP(A39,'Resumen Estudiantes y Profesore'!$B$3:$F$27,5,0) -> 267 | R39: =Q39-O39 -> 0
A40: Comunicación Social y Periodismo | B40: =VLOOKUP($A40,'BDD Esudiantes'!$E$3:$P$30,2,0) -> 30 | C40: =VLOOKUP($A40,'BDD Esudiantes'!$E$3:$P$30,3,0) -> 31 | D40: =VLOOKUP($A40,'BDD Esudiantes'!$E$3:$P$30,4,0) -> 45 | E40: =VLOOKUP($A40,'BDD Esudiantes'!$E$3:$P$30,5,0) -> 25 | F40: =VLOOKUP($A40,'BDD Esudiantes'!$E$3:$P$30,6,0) -> 34 | G40: =VLOOKUP($A40,'BDD Esudiantes'!$E$3:$P$30,7,0) -> 17 | H40: =VLOOKUP($A40,'BDD Esudiantes'!$E$3:$P$30,8,0) -> 14 | M40: 375 | N40: =SUM(B40:L40) -> 196 | O40: =VLOOKUP($A40,'BDD Esudiantes'!$E$3:$P$30,12,0) -> 196 | P40: =O40-N40 -> 0 | Q40: =VLOOKUP(A40,'Resumen Estudiantes y Profesore'!$B$3:$F$27,5,0) -> 196 | R40: =Q40-O40 -> 0
A41: Ciencias Políticas | B41: =VLOOKUP($A41,'BDD Esudiantes'!$E$3:$P$30,2,0) -> 7 | C41: =VLOOKUP($A41,'BDD Esudiantes'!$E$3:$P$30,3,0) -> 12 | D41: =VLOOKUP($A41,'BDD Esudiantes'!$E$3:$P$30,4,0) -> 11 | E41: =VLOOKUP($A41,'BDD Esudiantes'!$E$3:$P$30,5,0) -> 6 | F41: =VLOOKUP($A41,'BDD Esudiantes'!$E$3:$P$30,6,0) -> 13 | G41: =VLOOKUP($A41,'BDD Esudiantes'!$E$3:$P$30,7,0) -> 8 | H41: =VLOOKUP($A41,'BDD Esudiantes'!$E$3:$P$30,8,0) -> 11 | M41: 85 | N41: =SUM(B41:L41) -> 68 | O41: =VLOOKUP($A41,'BDD Esudiantes'!$E$3:$P$30,12,0) -> 68 | P41: =O41-N41 -> 0 | Q41: =VLOOKUP(A41,'Resumen Estudiantes y Profesore'!$B$3:$F$27,5,0) -> 68 | R41: =Q41-O41 -> 0
A42: Derecho | B42: =VLOOKUP($A42,'BDD Esudiantes'!$E$3:$P$30,2,0) -> 49 | C42: =VLOOKUP($A42,'BDD Esudiantes'!$E$3:$P$30,3,0) -> 14 | D42: =VLOOKUP($A42,'BDD Esudiantes'!$E$3:$P$30,4,0) -> 23 | E42: =VLOOKUP($A42,'BDD Esudiantes'!$E$3:$P$30,5,0) -> 16 | F42: =VLOOKUP($A42,'BDD Esudiantes'!$E$3:$P$30,6,0) -> 32 | G42: =VLOOKUP($A42,'BDD Esudiantes'!$E$3:$P$30,7,0) -> 21 | H42: =VLOOKUP($A42,'BDD Esudiantes'!$E$3:$P$30,8,0) -> 19 | I42: =VLOOKUP($A42,'BDD Esudiantes'!$E$3:$P$30,9,0) -> 16 | M42: 247 | N42: =SUM(B42:L42) -> 190 | O42: =VLOOKUP($A42,'BDD Esudiantes'!$E$3:$P$30,12,0) -> 190 | P42: =O42-N42 -> 0 | Q42: =VLOOKUP(A42,'Resumen Estudiantes y Profesore'!$B$3:$F$27,5,0) -> 190 | R42: =Q42-O42 -> 0
A43: Licenciatura en Educación Infantil | B43: =VLOOKUP($A43,'BDD Esudiantes'!$E$3:$P$30,2,0) -> 14 | C43: =VLOOKUP($A43,'BDD Esudiantes'!$E$3:$P$30,3,0) -> 5 | D43: =VLOOKUP($A43,'BDD Esudiantes'!$E$3:$P$30,4,0) -> 6 | E43: =VLOOKUP($A43,'BDD Esudiantes'!$E$3:$P$30,5,0) -> 9 | F43: =VLOOKUP($A43,'BDD Esudiantes'!$E$3:$P$30,6,0) -> 2 | G43: =VLOOKUP($A43,'BDD Esudiantes'!$E$3:$P$30,7,0) -> 4 | H43: =VLOOKUP($A43,'BDD Esudiantes'!$E$3:$P$30,8,0) -> 9 | I43: =VLOOKUP($A43,'BDD Esudiantes'!$E$3:$P$30,9,0) -> 2 | J43: =VLOOKUP($A43,'BDD Esudiantes'!$E$3:$P$30,10,0) -> 3 | M43: 54 | N43: =SUM(B43:L43) -> 54 | O43: =VLOOKUP($A43,'BDD Esudiantes'!$E$3:$P$30,12,0) -> 54 | P43: =O43-N43 -> 0 | Q43: =VLOOKUP(A43,'Resumen Estudiantes y Profesore'!$B$3:$F$27,5,0) -> 54 | R43: =Q43-O43 -> 0
A44: Enfermería | B44: =VLOOKUP($A44,'BDD Esudiantes'!$E$3:$P$30,2,0) -> 27 | C44: =VLOOKUP($A44,'BDD Esudiantes'!$E$3:$P$30,3,0) -> 19 | D44: =VLOOKUP($A44,'BDD Esudiantes'!$E$3:$P$30,4,0) -> 25 | E44: =VLOOKUP($A44,'BDD Esudiantes'!$E$3:$P$30,5,0) -> 14 | F44: =VLOOKUP($A44,'BDD Esudiantes'!$E$3:$P$30,6,0) -> 16 | G44: =VLOOKUP($A44,'BDD Esudiantes'!$E$3:$P$30,7,0) -> 12 | H44: =VLOOKUP($A44,'BDD Esudiantes'!$E$3:$P$30,8,0) -> 19 | M44: 132 | N44: =SUM(B44:L44) -> 132 | O44: =VLOOKUP($A44,'BDD Esudiantes'!$E$3:$P$30,12,0) -> 132 | P44: =O44-N44 -> 0 | Q44: =VLOOKUP(A44,'Resumen Estudiantes y Profesore'!$B$3:$F$27,5,0) -> 132 | R44: =Q44-O44 -> 0
A45: Fisioterapia | B45: =VLOOKUP($A45,'BDD Esudiantes'!$E$3:$P$30,2,0) -> 21 | C45: =VLOOKUP($A45,'BDD Esudiantes'!$E$3:$P$30,3,0) -> 1 | D45: =VLOOKUP($A45,'BDD Esudiantes'!$E$3:$P$30,4,0) -> 37 | E45: =VLOOKUP($A45,'BDD Esudiantes'!$E$3:$P$30,5,0) -> 43 | F45: =VLOOKUP($A45,'BDD Esudiantes'!$E$3:$P$30,6,0) -> 28 | G45: =VLOOKUP($A45,'BDD Esudiantes'!$E$3:$P$30,7,0) -> 19 | H45: =VLOOKUP($A45,'BDD Esudiantes'!$E$3:$P$30,8,0) -> 33 | M45: 224 | N45: =SUM(B45:L45) -> 182 | O45: =VLOOKUP($A45,'BDD Esudiantes'!$E$3:$P$30,12,0) -> 182 | P45: =O45-N45 -> 0 | Q45: =VLOOKUP(A45,'Resumen Estudiantes y Profesore'!$B$3:$F$27,5,0) -> 182 | R45: =Q45-O45 -> 0
A46: Filosofía | B46: =VLOOKUP($A46,'BDD Esudiantes'!$E$3:$P$30,2,0) -> 5 | C46: =VLOOKUP($A46,'BDD Esudiantes'!$E$3:$P$30,3,0) -> 1 | D46: =VLOOKUP($A46,'BDD Esudiantes'!$E$3:$P$30,4,0) -> 6 | E46: =VLOOKUP($A46,'BDD Esudiantes'!$E$3:$P$30,5,0) -> 5 | F46: =VLOOKUP($A46,'BDD Esudiantes'!$E$3:$P$30,6,0) -> 7 | G46: =VLOOKUP($A46,'BDD Esudiantes'!$E$3:$P$30,7,0) -> 1 | H46: =VLOOKUP($A46,'BDD Esudiantes'!$E$3:$P$30,8,0) -> 2 | I46: =VLOOKUP($A46,'BDD Esudiantes'!$E$3:$P$30,9,0) -> 4 | M46: 28 | N46: =SUM(B46:L46) -> 31 | O46: =VLOOKUP($A46,'BDD Esudiantes'!$E$3:$P$30,12,0) -> 31 | P46: =O46-N46 -> 0 | Q46: =VLOOKUP(A46,'Resumen Estudiantes y Profesore'!$B$3:$F$27,5,0) -> 31 | R46: =Q46-O46 -> 0
A47: Ingeniería Civil | B47: =VLOOKUP($A47,'BDD Esudiantes'!$E$3:$P$30,2,0) -> 17 | C47: =VLOOKUP($A47,'BDD Esudiantes'!$E$3:$P$30,3,0) -> 9 | D47: =VLOOKUP($A47,'BDD Esudiantes'!$E$3:$P$30,4,0) -> 12 | E47: =VLOOKUP($A47,'BDD Esudiantes'!$E$3:$P$30,5,0) -> 11 | F47: =VLOOKUP($A47,'BDD Esudiantes'!$E$3:$P$30,6,0) -> 21 | G47: =VLOOKUP($A47,'BDD Esudiantes'!$E$3:$P$30,7,0) -> 8 | H47: =VLOOKUP($A47,'BDD Esudiantes'!$E$3:$P$30,8,0) -> 23 | M47: 112 | N47: =SUM(B47:L47) -> 101 | O47: =VLOOKUP($A47,'BDD Esudiantes'!$E$3:$P$30,12,0) -> 101 | P47: =O47-N47 -> 0 | Q47: =VLOOKUP(A47,'Resumen Estudiantes y Profesore'!$B$3:$F$27,5,0) -> 101 | R47: =Q47-O47 -> 0
A48: Ingeniería de Producción Agroindustrial | B48: =VLOOKUP($A48,'BDD Esudiantes'!$E$3:$P$30,2,0) -> 2 | C48: =VLOOKUP($A48,'BDD Esudiantes'!$E$3:$P$30,3,0) -> 0 | D48: =VLOOKUP($A48,'BDD Esudiantes'!$E$3:$P$30,4,0) -> 0 | E48: =VLOOKUP($A48,'BDD Esudiantes'!$E$3:$P$30,5,0) -> 0 | F48: =VLOOKUP($A48,'BDD Esudiantes'!$E$3:$P$30,6,0) -> 0 | G48: =VLOOKUP($A48,'BDD Esudiantes'!$E$3:$P$30,7,0) -> 1 | H48: =VLOOKUP($A48,'BDD Esudiantes'!$E$3:$P$30,8,0) -> 10 | I48: =VLOOKUP($A48,'BDD Esudiantes'!$E$3:$P$30,9,0) -> 0 | M48: 22 | O48: =VLOOKUP($A48,'BDD Esudiantes'!$E$3:$P$30,12,0) -> 13 | R48: =Q48-O48 -> -13
A49: Ingeniería Industrial | B49: =VLOOKUP($A49,'BDD Esudiantes'!$E$3:$P$30,2,0) -> 34 | C49: =VLOOKUP($A49,'BDD Esudiantes'!$E$3:$P$30,3,0) -> 22 | D49: =VLOOKUP($A49,'BDD Esudiantes'!$E$3:$P$30,4,0) -> 28 | E49: =VLOOKUP($A49,'BDD Esudiantes'!$E$3:$P$30,5,0) -> 9 | F49: =VLOOKUP($A49,'BDD Esudiantes'!$E$3:$P$30,6,0) -> 49 | G49: =VLOOKUP($A49,'BDD Esudiantes'!$E$3:$P$30,7,0) -> 23 | H49: =VLOOKUP($A49,'BDD Esudiantes'!$E$3:$P$30,8,0) -> 20 | M49: 254 | N49: =SUM(B49:L49) -> 185 | O49: =VLOOKUP($A49,'BDD Esudiantes'!$E$3:$P$30,12,0) -> 185 | P49: =O49-N49 -> 0 | Q49: =VLOOKUP(A49,'Resumen Estudiantes y Profesore'!$B$3:$F$27,5,0) -> 185 | R49: =Q49-O49 -> 0
A50: Ingeniería Informática | B50: =VLOOKUP($A50,'BDD Esudiantes'!$E$3:$P$30,2,0) -> 26 | C50: =VLOOKUP($A50,'BDD Esudiantes'!$E$3:$P$30,3,0) -> 25 | D50: =VLOOKUP($A50,'BDD Esudiantes'!$E$3:$P$30,4,0) -> 31 | E50: =VLOOKUP($A50,'BDD Esudiantes'!$E$3:$P$30,5,0) -> 36 | F50: =VLOOKUP($A50,'BDD Esudiantes'!$E$3:$P$30,6,0) -> 38 | G50: =VLOOKUP($A50,'BDD Esudiantes'!$E$3:$P$30,7,0) -> 19 | H50: =VLOOKUP($A50,'BDD Esudiantes'!$E$3:$P$30,8,0) -> 34 | M50: 275 | N50: =SUM(B50:L50) -> 209 | O50: =VLOOKUP($A50,'BDD Esudiantes'!$E$3:$P$30,12,0) -> 209 | P50: =O50-N50 -> 0 | Q50: =VLOOKUP(A50,'Resumen Estudiantes y Profesore'!$B$3:$F$27,5,0) -> 209 | R50: =Q50-O50 -> 0
A51: Ingeniería Mecánica | B51: =VLOOKUP($A51,'BDD Esudiantes'!$E$3:$P$30,2,0) -> 19 | C51: =VLOOKUP($A51,'BDD Esudiantes'!$E$3:$P$30,3,0) -> 21 | D51: =VLOOKUP($A51,'BDD Esudiantes'!$E$3:$P$30,4,0) -> 20 | E51: =VLOOKUP($A51,'BDD Esudiantes'!$E$3:$P$30,5,0) -> 14 | F51: =VLOOKUP($A51,'BDD Esudiantes'!$E$3:$P$30,6,0) -> 26 | G51: =VLOOKUP($A51,'BDD Esudiantes'!$E$3:$P$30,7,0) -> 11 | H51: =VLOOKUP($A51,'BDD Esudiantes'!$E$3:$P$30,8,0) -> 25 | M51: 176 | N51: =SUM(B51:L51) -> 136 | O51: =VLOOKUP($A51,'BDD Esudiantes'!$E$3:$P$30,12,0) -> 136 | P51: =O51-N51 -> 0 | Q51: =VLOOKUP(A51,'Resumen Estudiantes y Profesore'!$B$3:$F$27,5,0) -> 136 | R51: =Q51-O51 -> 0
A52: Ingeniería de Bioproducción | B52: =VLOOKUP($A52,'BDD Esudiantes'!$E$3:$P$30,2,0) -> 5 | C52: =VLOOKUP($A52,'BDD Esudiantes'!$E$3:$P$30,3,0) -> 0 | D52: =VLOOKUP($A52,'BDD Esudiantes'!$E$3:$P$30,4,0) -> 3 | E52: =VLOOKUP($A52,'BDD Esudiantes'!$E$3:$P$30,5,0) -> 7 | F52: =VLOOKUP($A52,'BDD Esudiantes'!$E$3:$P$30,6,0) -> 2 | G52: =VLOOKUP($A52,'BDD Esudiantes'!$E$3:$P$30,7,0) -> 2 | H52: =VLOOKUP($A52,'BDD Esudiantes'!$E$3:$P$30,8,0) -> 3 | I52: =VLOOKUP($A52,'BDD Esudiantes'!$E$3:$P$30,9,0) -> 0 | M52: 24 | O52: =VLOOKUP($A52,'BDD Esudiantes'!$E$3:$P$30,12,0) -> 22 | R52: =Q52-O52 -> -22
A53: Ingeniería de Bioproducción / Producción Agroindustrial | B53: =B48+B52 -> 7 | C53: =C48+C52 -> 0 | D53: =D48+D52 -> 3 | E53: =E48+E52 -> 7 | F53: =F48+F52 -> 2 | G53: =G48+G52 -> 3 | H53: =H48+H52 -> 13 | I53: =I48+I52 -> 0 | N53: =SUM(B53:L53) -> 35 | O53: =O52+O48 -> 35 | P53: =O53-N53 -> 0 | Q53: =VLOOKUP(A53,'Resumen Estudiantes y Profesore'!$B$3:$F$27,5,0) -> 35 | R53: =Q53-O53 -> 0
A54: Ingeniería Química | B54: =VLOOKUP($A54,'BDD Esudiantes'!$E$3:$P$30,2,0) -> 24 | C54: =VLOOKUP($A54,'BDD Esudiantes'!$E$3:$P$30,3,0) -> 17 | D54: =VLOOKUP($A54,'BDD Esudiantes'!$E$3:$P$30,4,0) -> 19 | E54: =VLOOKUP($A54,'BDD Esudiantes'!$E$3:$P$30,5,0) -> 18 | F54: =VLOOKUP($A54,'BDD Esudiantes'!$E$3:$P$30,6,0) -> 17 | G54: =VLOOKUP($A54,'BDD Esudiantes'!$E$3:$P$30,7,0) -> 20 | H54: =VLOOKUP($A54,'BDD Esudiantes'!$E$3:$P$30,8,0) -> 24 | M54: 197 | N54: =SUM(B54:L54) -> 139 | O54: =VLOOKUP($A54,'BDD Esudiantes'!$E$3:$P$30,12,0) -> 139 | P54: =O54-N54 -> 0 | Q54: =VLOOKUP(A54,'Resumen Estudiantes y Profesore'!$B$3:$F$27,5,0) -> 139 | R54: =Q54-O54 -> 0
A55: Medicina | B55: =VLOOKUP($A55,'BDD Esudiantes'!$E$3:$P$30,2,0) -> 82 | C55: =VLOOKUP($A55,'BDD Esudiantes'!$E$3:$P$30,3,0) -> 69 | D55: =VLOOKUP($A55,'BDD Esudiantes'!$E$3:$P$30,4,0) -> 62 | E55: =VLOOKUP($A55,'BDD Esudiantes'!$E$3:$P$30,5,0) -> 108 | F55: =VLOOKUP($A55,'BDD Esudiantes'!$E$3:$P$30,6,0) -> 58 | G55: =VLOOKUP($A55,'BDD Esudiantes'!$E$3:$P$30,7,0) -> 54 | H55: =VLOOKUP($A55,'BDD Esudiantes'!$E$3:$P$30,8,0) -> 55 | I55: =VLOOKUP($A55,'BDD Esudiantes'!$E$3:$P$30,9,0) -> 54 | J55: =VLOOKUP($A55,'BDD Esudiantes'!$E$3:$P$30,10,0) -> 49 | K55: =VLOOKUP($A55,'BDD Esudiantes'!$E$3:$P$30,11,0) -> 88 | M55: 1046 | N55: =SUM(B55:L55) -> 679 | O55: =VLOOKUP($A55,'BDD Esudiantes'!$E$3:$P$30,12,0) -> 679 | P55: =O55-N55 -> 0 | Q55: =VLOOKUP(A55,'Resumen Estudiantes y Profesore'!$B$3:$F$27,5,0) -> 679 | R55: =Q55-O55 -> 0
A56: Psicología | B56: =VLOOKUP($A56,'BDD Esudiantes'!$E$3:$P$30,2,0) -> 49 | C56: =VLOOKUP($A56,'BDD Esudiantes'!$E$3:$P$30,3,0) -> 26 | D56: =VLOOKUP($A56,'BDD Esudiantes'!$E$3:$P$30,4,0) -> 37 | E56: =VLOOKUP($A56,'BDD Esudiantes'!$E$3:$P$30,5,0) -> 27 | F56: =VLOOKUP($A56,'BDD Esudiantes'!$E$3:$P$30,6,0) -> 18 | G56: =VLOOKUP($A56,'BDD Esudiantes'!$E$3:$P$30,7,0) -> 14 | H56: =VLOOKUP($A56,'BDD Esudiantes'!$E$3:$P$30,8,0) -> 32 | M56: 340 | N56: =SUM(B56:L56) -> 203 | O56: =VLOOKUP($A56,'BDD Esudiantes'!$E$3:$P$30,12,0) -> 203 | P56: =O56-N56 -> 0 | Q56: =VLOOKUP(A56,'Resumen Estudiantes y Profesore'!$B$3:$F$27,5,0) -> 205 | R56: =Q56-O56 -> 2
A57: Ciencia de Datos | B57: =VLOOKUP($A57,'BDD Esudiantes'!$E$3:$P$30,2,0) -> 19 | C57: =VLOOKUP($A57,'BDD Esudiantes'!$E$3:$P$30,3,0) -> 3 | D57: =VLOOKUP($A57,'BDD Esudiantes'!$E$3:$P$30,4,0) -> 0 | E57: =VLOOKUP($A57,'BDD Esudiantes'!$E$3:$P$30,5,0) -> 2 | F57: =VLOOKUP($A57,'BDD Esudiantes'!$E$3:$P$30,6,0) -> 0 | G57: =VLOOKUP($A57,'BDD Esudiantes'!$E$3:$P$30,7,0) -> 0 | H57: =VLOOKUP($A57,'BDD Esudiantes'!$E$3:$P$30,8,0) -> 0 | N57: =SUM(B57:L57) -> 24 | O57: =VLOOKUP($A57,'BDD Esudiantes'!$E$3:$P$30,12,0) -> 24 | P57: =O57-N57 -> 0 | Q57: =VLOOKUP(A57,'Resumen Estudiantes y Profesore'!$B$3:$F$27,5,0) -> 24 | R57: =Q57-O57 -> 0
A58: Licenciatura en Ciencias Naturales | B58: =VLOOKUP($A58,'BDD Esudiantes'!$E$3:$P$30,2,0) -> 0 | C58: =VLOOKUP($A58,'BDD Esudiantes'!$E$3:$P$30,3,0) -> 0 | D58: =VLOOKUP($A58,'BDD Esudiantes'!$E$3:$P$30,4,0) -> 2 | E58: =VLOOKUP($A58,'BDD Esudiantes'!$E$3:$P$30,5,0) -> 1 | F58: =VLOOKUP($A58,'BDD Esudiantes'!$E$3:$P$30,6,0) -> 1 | G58: =VLOOKUP($A58,'BDD Esudiantes'!$E$3:$P$30,7,0) -> 0 | H58: =VLOOKUP($A58,'BDD Esudiantes'!$E$3:$P$30,8,0) -> 5 | I58: =VLOOKUP($A58,'BDD Esudiantes'!$E$3:$P$30,9,0) -> 2 | N58: =SUM(B58:L58) -> 11 | O58: =VLOOKUP($A58,'BDD Esudiantes'!$E$3:$P$30,12,0) -> 11 | P58: =O58-N58 -> 0 | Q58: =VLOOKUP(A58,'Resumen Estudiantes y Profesore'!$B$3:$F$27,5,0) -> 11 | R58: =Q58-O58 -> 0
A59: LOGRADO
A60: NOMBRE DEL PROGRAMA | B60: SEMESTRE 2 | C60: SEMESTRE 3 | D60: SEMESTRE 4 | E60: SEMESTRE 5 | F60: SEMESTRE 6 | G60: SEMESTRE 7 | H60: SEMESTRE 8 | I60: SEMESTRE 9 | J60: SEMESTRE 10 | K60: SEMESTRE 11 | L60: SEMESTRE 12 | M60: TOTAL POBLACIÓN | N60: TOTAL EJECUCIÓN | O60: ALCANCE EJECUCIÓN | P60: ME Lograddo (95%)
A61: Administración & Servicio | B61: =IFERROR(B32,0) -> 9 | C61: =IFERROR(C32,0) -> 11 | D61: =IFERROR(D32,0) -> 3 | E61: =IFERROR(E32,0) -> 7 | F61: =IFERROR(F32,0) -> 12 | G61: =IFERROR(G32,0) -> 12 | H61: =IFERROR(H32,0) -> 12 | M61: 84 | N61: =SUM(B61:L61) -> 66 | O61: =N61/M61 -> 0.78571429 | P61: =IFERROR((((1.96^2*0.5*0.5*($M61-N61))/(N61*($M61-1)))^0.5),"") -> 0.056176065 | Q61: =VLOOKUP(A61,'Resumen Estudiantes y Profesore'!$B$3:$F$27,5,0) -> 66 | S61: Se solicita cerrar el programa | T61: =Q61-N61 -> 0
A62: Administración de Empresas | B62: =IFERROR(B33,0) -> 23 | C62: =IFERROR(C33,0) -> 12 | D62: =IFERROR(D33,0) -> 22 | E62: =IFERROR(E33,0) -> 18 | F62: =IFERROR(F33,0) -> 23 | G62: =IFERROR(G33,0) -> 19 | H62: =IFERROR(H33,0) -> 30 | M62: 253 | N62: =SUM(B62:L62) -> 147 | O62: =N62/M62 -> 0.58102767 | P62: =IFERROR((((1.96^2*0.5*0.5*($M62-N62))/(N62*($M62-1)))^0.5),"") -> 0.052422783 | Q62: =VLOOKUP(A62,'Resumen Estudiantes y Profesore'!$B$3:$F$27,5,0) -> 147 | S62: Verificar si los semestres en los que no se hcieron encuestas tienen estudiantes, si no hay estudiantes se puede cerrar. | T62: =Q62-N62 -> 0
A63: Administración de Mercadeo y Logística Internacionales | B63: =IFERROR(B34,0) -> 2 | C63: =IFERROR(C34,0) -> 29 | D63: =IFERROR(D34,0) -> 47 | E63: =IFERROR(E34,0) -> 35 | F63: =IFERROR(F34,0) -> 53 | G63: =IFERROR(G34,0) -> 29 | H63: =IFERROR(H34,0) -> 28 | M63: 344 | N63: =SUM(B63:L63) -> 223 | O63: =N63/M63 -> 0.64825581 | P63: =IFERROR((((1.96^2*0.5*0.5*($M63-N63))/(N63*($M63-1)))^0.5),"") -> 0.038977975 | Q63: =VLOOKUP(A63,'Resumen Estudiantes y Profesore'!$B$3:$F$27,5,0) -> 223 | S63: El ME es bajo pero no hay encuestas en todos los semestres | T63: =Q63-N63 -> 0
A64: Administración de Negocios Internacionales | B64: =IFERROR(B35,0) -> 48 | C64: =IFERROR(C35,0) -> 50 | D64: =IFERROR(D35,0) -> 65 | E64: =IFERROR(E35,0) -> 48 | F64: =IFERROR(F35,0) -> 28 | G64: =IFERROR(G35,0) -> 29 | H64: =IFERROR(H35,0) -> 31 | M64: 580 | N64: =SUM(B64:L64) -> 299 | O64: =N64/M64 -> 0.51551724 | P64: =IFERROR((((1.96^2*0.5*0.5*($M64-N64))/(N64*($M64-1)))^0.5),"") -> 0.039482474 | Q64: =VLOOKUP(A64,'Resumen Estudiantes y Profesore'!$B$3:$F$27,5,0) -> 299 | S64: Hay encuestas en todos los semestres pero el margen de error es superior al 6% | T64: =Q64-N64 -> 0
A65: Economía y Finanzas Internacionales | B65: =IFERROR(B36,0) -> 27 | C65: =IFERROR(C36,0) -> 17 | D65: =IFERROR(D36,0) -> 34 | E65: =IFERROR(E36,0) -> 14 | F65: =IFERROR(F36,0) -> 23 | G65: =IFERROR(G36,0) -> 13 | H65: =IFERROR(H36,0) -> 13 | M65: 215 | N65: =SUM(B65:L65) -> 141 | O65: =N65/M65 -> 0.65581395 | P65: =IFERROR((((1.96^2*0.5*0.5*($M65-N65))/(N65*($M65-1)))^0.5),"") -> 0.048531699 | Q65: =VLOOKUP(A65,'Resumen Estudiantes y Profesore'!$B$3:$F$27,5,0) -> 141 | S65: No hay encuestas en todos los semestres y el ME aun es alto | T65: =Q65-N65 -> 0
A66: Gastronomía | B66: =IFERROR(B37,0) -> 31 | C66: =IFERROR(C37,0) -> 17 | D66: =IFERROR(D37,0) -> 25 | E66: =IFERROR(E37,0) -> 16 | F66: =IFERROR(F37,0) -> 23 | G66: =IFERROR(G37,0) -> 12 | H66: =IFERROR(H37,0) -> 7 | M66: 240 | N66: =SUM(B66:L66) -> 131 | O66: =N66/M66 -> 0.54583333 | P66: =IFERROR((((1.96^2*0.5*0.5*($M66-N66))/(N66*($M66-1)))^0.5),"") -> 0.057823547 | Q66: =VLOOKUP(A66,'Resumen Estudiantes y Profesore'!$B$3:$F$27,5,0) -> 131 | T66: =Q66-N66 -> 0
A67: Comunicación Corporativa | B67: =IFERROR(B38,0) -> 12 | C67: =IFERROR(C38,0) -> 26 | D67: =IFERROR(D38,0) -> 7 | E67: =IFERROR(E38,0) -> 16 | F67: =IFERROR(F38,0) -> 22 | G67: =IFERROR(G38,0) -> 15 | H67: =IFERROR(H38,0) -> 14 | M67: 206 | N67: =SUM(B67:L67) -> 112 | O67: =N67/M67 -> 0.54368932 | P67: =IFERROR((((1.96^2*0.5*0.5*($M67-N67))/(N67*($M67-1)))^0.5),"") -> 0.062705273 | Q67: =VLOOKUP(A67,'Resumen Estudiantes y Profesore'!$B$3:$F$27,5,0) -> 112 | T67: =Q67-N67 -> 0
A68: Comunicación Audiovisual y Multimedios | B68: =IFERROR(B39,0) -> 56 | C68: =IFERROR(C39,0) -> 35 | D68: =IFERROR(D39,0) -> 69 | E68: =IFERROR(E39,0) -> 35 | F68: =IFERROR(F39,0) -> 21 | G68: =IFERROR(G39,0) -> 18 | H68: =IFERROR(H39,0) -> 33 | M68: 606 | N68: =SUM(B68:L68) -> 267 | O68: =N68/M68 -> 0.44059406 | P68: =IFERROR((((1.96^2*0.5*0.5*($M68-N68))/(N68*($M68-1)))^0.5),"") -> 0.044894445 | Q68: =VLOOKUP(A68,'Resumen Estudiantes y Profesore'!$B$3:$F$27,5,0) -> 267 | T68: =Q68-N68 -> 0
A69: Comunicación Social y Periodismo | B69: =IFERROR(B40,0) -> 30 | C69: =IFERROR(C40,0) -> 31 | D69: =IFERROR(D40,0) -> 45 | E69: =IFERROR(E40,0) -> 25 | F69: =IFERROR(F40,0) -> 34 | G69: =IFERROR(G40,0) -> 17 | H69: =IFERROR(H40,0) -> 14 | M69: 360 | N69: =SUM(B69:L69) -> 196 | O69: =N69/M69 -> 0.54444444 | P69: =IFERROR((((1.96^2*0.5*0.5*($M69-N69))/(N69*($M69-1)))^0.5),"") -> 0.047312156 | Q69: =VLOOKUP(A69,'Resumen Estudiantes y Profesore'!$B$3:$F$27,5,0) -> 196 | T69: =Q69-N69 -> 0
A70: Ciencias Políticas | B70: =IFERROR(B41,0) -> 7 | C70: =IFERROR(C41,0) -> 12 | D70: =IFERROR(D41,0) -> 11 | E70: =IFERROR(E41,0) -> 6 | F70: =IFERROR(F41,0) -> 13 | G70: =IFERROR(G41,0) -> 8 | H70: =IFERROR(H41,0) -> 11 | M70: 85 | N70: =SUM(B70:L70) -> 68 | O70: =N70/M70 -> 0.8 | P70: =IFERROR((((1.96^2*0.5*0.5*($M70-N70))/(N70*($M70-1)))^0.5),"") -> 0.053463383 | Q70: =VLOOKUP(A70,'Resumen Estudiantes y Profesore'!$B$3:$F$27,5,0) -> 68 | T70: =Q70-N70 -> 0
A71: Derecho | B71: =IFERROR(B42,0) -> 49 | C71: =IFERROR(C42,0) -> 14 | D71: =IFERROR(D42,0) -> 23 | E71: =IFERROR(E42,0) -> 16 | F71: =IFERROR(F42,0) -> 32 | G71: =IFERROR(G42,0) -> 21 | H71: =IFERROR(H42,0) -> 19 | I71: =IFERROR(I42,0) -> 16 | M71: 306 | N71: =SUM(B71:L71) -> 190 | O71: =N71/M71 -> 0.62091503 | P71: =IFERROR((((1.96^2*0.5*0.5*($M71-N71))/(N71*($M71-1)))^0.5),"") -> 0.043845836 | Q71: =VLOOKUP(A71,'Resumen Estudiantes y Profesore'!$B$3:$F$27,5,0) -> 190 | T71: =Q71-N71 -> 0
A72: Licenciatura en Educación Infantil | B72: =IFERROR(B43,0) -> 14 | C72: =IFERROR(C43,0) -> 5 | D72: =IFERROR(D43,0) -> 6 | E72: =IFERROR(E43,0) -> 9 | F72: =IFERROR(F43,0) -> 2 | G72: =IFERROR(G43,0) -> 4 | H72: =IFERROR(H43,0) -> 9 | I72: =IFERROR(I43,0) -> 2 | J72: =IFERROR(J43,0) -> 3 | M72: 70 | N72: =SUM(B72:L72) -> 54 | O72: =N72/M72 -> 0.77142857 | P72: =IFERROR((((1.96^2*0.5*0.5*($M72-N72))/(N72*($M72-1)))^0.5),"") -> 0.064219163 | Q72: =VLOOKUP(A72,'Resumen Estudiantes y Profesore'!$B$3:$F$27,5,0) -> 54 | T72: =Q72-N72 -> 0
A73: Enfermería | B73: =IFERROR(B44,0) -> 27 | C73: =IFERROR(C44,0) -> 19 | D73: =IFERROR(D44,0) -> 25 | E73: =IFERROR(E44,0) -> 14 | F73: =IFERROR(F44,0) -> 16 | G73: =IFERROR(G44,0) -> 12 | H73: =IFERROR(H44,0) -> 19 | M73: 150 | N73: =SUM(B73:L73) -> 132 | O73: =N73/M73 -> 0.88 | P73: =IFERROR((((1.96^2*0.5*0.5*($M73-N73))/(N73*($M73-1)))^0.5),"") -> 0.029647101 | Q73: =VLOOKUP(A73,'Resumen Estudiantes y Profesore'!$B$3:$F$27,5,0) -> 132 | T73: =Q73-N73 -> 0
A74: Fisioterapia | B74: =IFERROR(B45,0) -> 21 | C74: =IFERROR(C45,0) -> 1 | D74: =IFERROR(D45,0) -> 37 | E74: =IFERROR(E45,0) -> 43 | F74: =IFERROR(F45,0) -> 28 | G74: =IFERROR(G45,0) -> 19 | H74: =IFERROR(H45,0) -> 33 | M74: 224 | N74: =SUM(B74:L74) -> 182 | O74: =N74/M74 -> 0.8125 | P74: =IFERROR((((1.96^2*0.5*0.5*($M74-N74))/(N74*($M74-1)))^0.5),"") -> 0.031525544 | Q74: =VLOOKUP(A74,'Resumen Estudiantes y Profesore'!$B$3:$F$27,5,0) -> 182 | T74: =Q74-N74 -> 0
A75: Filosofía | B75: =IFERROR(B46,0) -> 5 | C75: =IFERROR(C46,0) -> 1 | D75: =IFERROR(D46,0) -> 6 | E75: =IFERROR(E46,0) -> 5 | F75: =IFERROR(F46,0) -> 7 | G75: =IFERROR(G46,0) -> 1 | H75: =IFERROR(H46,0) -> 2 | I75: =IFERROR(I46,0) -> 4 | M75: 34 | N75: =SUM(B75:L75) -> 31 | O75: =N75/M75 -> 0.91176471 | P75: =IFERROR((((1.96^2*0.5*0.5*($M75-N75))/(N75*($M75-1)))^0.5),"") -> 0.053069975 | Q75: =VLOOKUP(A75,'Resumen Estudiantes y Profesore'!$B$3:$F$27,5,0) -> 31 | T75: =Q75-N75 -> 0
A76: Ingeniería Civil | B76: =IFERROR(B47,0) -> 17 | C76: =IFERROR(C47,0) -> 9 | D76: =IFERROR(D47,0) -> 12 | E76: =IFERROR(E47,0) -> 11 | F76: =IFERROR(F47,0) -> 21 | G76: =IFERROR(G47,0) -> 8 | H76: =IFERROR(H47,0) -> 23 | M76: 114 | N76: =SUM(B76:L76) -> 101 | O76: =N76/M76 -> 0.88596491 | P76: =IFERROR((((1.96^2*0.5*0.5*($M76-N76))/(N76*($M76-1)))^0.5),"") -> 0.033074847 | Q76: =VLOOKUP(A76,'Resumen Estudiantes y Profesore'!$B$3:$F$27,5,0) -> 101 | T76: =Q76-N76 -> 0
A77: Ingeniería Industrial | B77: =IFERROR(B49,0) -> 34 | C77: =IFERROR(C49,0) -> 22 | D77: =IFERROR(D49,0) -> 28 | E77: =IFERROR(E49,0) -> 9 | F77: =IFERROR(F49,0) -> 49 | G77: =IFERROR(G49,0) -> 23 | H77: =IFERROR(H49,0) -> 20 | M77: 287 | N77: =SUM(B77:L77) -> 185 | O77: =N77/M77 -> 0.6445993 | P77: =IFERROR((((1.96^2*0.5*0.5*($M77-N77))/(N77*($M77-1)))^0.5),"") -> 0.043028606 | Q77: =VLOOKUP(A77,'Resumen Estudiantes y Profesore'!$B$3:$F$27,5,0) -> 185 | T77: =Q77-N77 -> 0
A78: Ingeniería Informática | B78: =IFERROR(B50,0) -> 26 | C78: =IFERROR(C50,0) -> 25 | D78: =IFERROR(D50,0) -> 31 | E78: =IFERROR(E50,0) -> 36 | F78: =IFERROR(F50,0) -> 38 | G78: =IFERROR(G50,0) -> 19 | H78: =IFERROR(H50,0) -> 34 | M78: 322 | N78: =SUM(B78:L78) -> 209 | O78: =N78/M78 -> 0.64906832 | P78: =IFERROR((((1.96^2*0.5*0.5*($M78-N78))/(N78*($M78-1)))^0.5),"") -> 0.040219775 | Q78: =VLOOKUP(A78,'Resumen Estudiantes y Profesore'!$B$3:$F$27,5,0) -> 209 | T78: =Q78-N78 -> 0
A79: Ingeniería Mecánica | B79: =IFERROR(B51,0) -> 19 | C79: =IFERROR(C51,0) -> 21 | D79: =IFERROR(D51,0) -> 20 | E79: =IFERROR(E51,0) -> 14 | F79: =IFERROR(F51,0) -> 26 | G79: =IFERROR(G51,0) -> 11 | H79: =IFERROR(H51,0) -> 25 | M79: 175 | N79: =SUM(B79:L79) -> 136 | O79: =N79/M79 -> 0.77714286 | P79: =IFERROR((((1.96^2*0.5*0.5*($M79-N79))/(N79*($M79-1)))^0.5),"") -> 0.039784536 | Q79: =VLOOKUP(A79,'Resumen Estudiantes y Profesore'!$B$3:$F$27,5,0) -> 136 | T79: =Q79-N79 -> 0
A80: Ingeniería de Bioproducción / Producción Agroindustrial | B80: =IFERROR(B53,0) -> 7 | C80: =IFERROR(C53,0) -> 0 | D80: =IFERROR(D53,0) -> 3 | E80: =IFERROR(E53,0) -> 7 | F80: =IFERROR(F53,0) -> 2 | G80: =IFERROR(G53,0) -> 3 | H80: =IFERROR(H53,0) -> 13 | I80: =IFERROR(I53,0) -> 0 | M80: 47 | N80: =SUM(B80:L80) -> 35 | O80: =N80/M80 -> 0.74468085 | P80: =IFERROR((((1.96^2*0.5*0.5*($M80-N80))/(N80*($M80-1)))^0.5),"") -> 0.084606506 | Q80: =VLOOKUP(A80,'Resumen Estudiantes y Profesore'!$B$3:$F$27,5,0) -> 35 | T80: =Q80-N80 -> 0
A81: Ingeniería Química | B81: =IFERROR(B54,0) -> 24 | C81: =IFERROR(C54,0) -> 17 | D81: =IFERROR(D54,0) -> 19 | E81: =IFERROR(E54,0) -> 18 | F81: =IFERROR(F54,0) -> 17 | G81: =IFERROR(G54,0) -> 20 | H81: =IFERROR(H54,0) -> 24 | M81: 197 | N81: =SUM(B81:L81) -> 139 | O81: =N81/M81 -> 0.70558376 | P81: =IFERROR((((1.96^2*0.5*0.5*($M81-N81))/(N81*($M81-1)))^0.5),"") -> 0.045217301 | Q81: =VLOOKUP(A81,'Resumen Estudiantes y Profesore'!$B$3:$F$27,5,0) -> 139 | T81: =Q81-N81 -> 0
A82: Medicina | B82: =IFERROR(B55,0) -> 82 | C82: =IFERROR(C55,0) -> 69 | D82: =IFERROR(D55,0) -> 62 | E82: =IFERROR(E55,0) -> 108 | F82: =IFERROR(F55,0) -> 58 | G82: =IFERROR(G55,0) -> 54 | H82: =IFERROR(H55,0) -> 55 | I82: =IFERROR(I55,0) -> 54 | ... K82: =IFERROR(K55,0) -> 88 | M82: 972 | N82: =SUM(B82:L82) -> 679 | O82: =N82/M82 -> 0.69855967 | P82: =IFERROR((((1.96^2*0.5*0.5*($M82-N82))/(N82*($M82-1)))^0.5),"") -> 0.02065929 | Q82: =VLOOKUP(A82,'Resumen Estudiantes y Profesore'!$B$3:$F$27,5,0) -> 679 | T82: =Q82-N82 -> 0
A83: Psicología | B83: =IFERROR(B56,0) -> 49 | C83: =IFERROR(C56,0) -> 26 | D83: =IFERROR(D56,0) -> 37 | E83: =IFERROR(E56,0) -> 27 | F83: =IFERROR(F56,0) -> 18 | G83: =IFERROR(G56,0) -> 14 | H83: =IFERROR(H56,0) -> 32 | M83: 340 | N83: =SUM(B83:L83) -> 203 | O83: =N83/M83 -> 0.59705882 | P83: =IFERROR((((1.96^2*0.5*0.5*($M83-N83))/(N83*($M83-1)))^0.5),"") -> 0.043725873 | Q83: =VLOOKUP(A83,'Resumen Estudiantes y Profesore'!$B$3:$F$27,5,0) -> 205 | T83: =Q83-N83 -> 2
A84: Ciencia de Datos | B84: =IFERROR(B57,0) -> 19 | C84: =IFERROR(C57,0) -> 3 | D84: =IFERROR(D57,0) -> 0 | E84: =IFERROR(E57,0) -> 2 | F84: =IFERROR(F57,0) -> 0 | G84: =IFERROR(G57,0) -> 0 | H84: =IFERROR(H57,0) -> 0 | M84: 26 | N84: =SUM(B84:L84) -> 24 | O84: =N84/M84 -> 0.92307692 | P84: =IFERROR((((1.96^2*0.5*0.5*($M84-N84))/(N84*($M84-1)))^0.5),"") -> 0.056580326 | Q84: =VLOOKUP(A84,'Resumen Estudiantes y Profesore'!$B$3:$F$27,5,0) -> 24 | T84: =Q84-N84 -> 0
A85: Licenciatura en Ciencias Naturales | B85: =IFERROR(B58,0) -> 0 | C85: =IFERROR(C58,0) -> 0 | D85: =IFERROR(D58,0) -> 2 | E85: =IFERROR(E58,0) -> 1 | F85: =IFERROR(F58,0) -> 1 | G85: =IFERROR(G58,0) -> 0 | H85: =IFERROR(H58,0) -> 5 | I85: =IFERROR(I58,0) -> 2 | M85: 27 | N85: =SUM(B85:L85) -> 11 | O85: =N85/M85 -> 0.40740741 | P85: =IFERROR((((1.96^2*0.5*0.5*($M85-N85))/(N85*($M85-1)))^0.5),"") -> 0.23179446 | Q85: =VLOOKUP(A85,'Resumen Estudiantes y Profesore'!$B$3:$F$27,5,0) -> 11 | T85: =Q85-N85 -> 0
L86: total | M86: =SUM(M61:M85) -> 6264 | N86: =SUM(N61:N85) -> 3961 | O86: =N86/M86 -> 0.63234355 | P86: =IFERROR((((1.96^2*0.5*0.5*($M86-N86))/(N86*($M86-1)))^0.5),"") -> 0.0094423353
A88: FALTANTES
A89: NOMBRE DEL PROGRAMA | B89: SEMESTRE 2 | C89: SEMESTRE 3 | D89: SEMESTRE 4 | E89: SEMESTRE 5 | F89: SEMESTRE 6 | G89: SEMESTRE 7 | H89: SEMESTRE 8 | I89: SEMESTRE 9 | J89: SEMESTRE 10 | K89: SEMESTRE 11 | L89: SEMESTRE 12 | M89: TOTAL POBLACIÓN | N89: TOTAL | O89: ALCANCE
A90: Administración & Servicio | B90: =B4-B61 -> 1 | C90: =C4-C61 -> -2 | D90: =D4-D61 -> 4 | E90: =E4-E61 -> 2 | F90: =F4-F61 -> 0 | G90: =G4-G61 -> 0 | H90: =H4-H61 -> 0 | M90: 84 | N90: =N4-N61 -> 5 | O90: =N90/M90 -> 0.05952381
A91: Administración de Empresas | B91: =B5-B62 -> 1 | C91: =C5-C62 -> 12 | D91: =D5-D62 -> -1 | E91: =E5-E62 -> 4 | F91: =F5-F62 -> -4 | G91: =G5-G62 -> 4 | H91: =H5-H62 -> -1 | M91: 253 | N91: =N5-N62 -> 15 | O91: =N91/M91 -> 0.059288538
A92: Administración de Mercadeo y Logística Internacionales | B92: =B6-B63 -> 32 | C92: =C6-C63 -> -7 | D92: =D6-D63 -> -10 | E92: =E6-E63 -> -7 | F92: =F6-F63 -> -24 | G92: =G6-G63 -> -9 | H92: =H6-H63 -> -3 | M92: 344 | N92: =N6-N63 -> -28 | O92: =N92/M92 -> -0.081395349
A93: Administración de Negocios Internacionales | B93: =B7-B64 -> -1 | C93: =C7-C64 -> -14 | D93: =D7-D64 -> -28 | E93: =E7-E64 -> -14 | F93: =F7-F64 -> 11 | G93: =G7-G64 -> -1 | H93: =H7-H64 -> 2 | M93: 580 | N93: =N7-N64 -> -45 | O93: =N93/M93 -> -0.077586207
A94: Economía y Finanzas Internacionales | B94: =B8-B65 -> 5 | C94: =C8-C65 -> 9 | D94: =D8-D65 -> -13 | E94: =E8-E65 -> -1 | F94: =F8-F65 -> -5 | G94: =G8-G65 -> -2 | H94: =H8-H65 -> 12 | M94: 215 | N94: =N8-N65 -> 5 | O94: =N94/M94 -> 0.023255814
A95: Gastronomía | B95: =B9-B66 -> 10 | C95: =C9-C66 -> -1 | D95: =D9-D66 -> 2 | E95: =E9-E66 -> 6 | F95: =F9-F66 -> -4 | G95: =G9-G66 -> 3 | H95: =H9-H66 -> 11 | M95: 240 | N95: =N9-N66 -> 27 | O95: =N95/M95 -> 0.1125
A96: Comunicación Corporativa | B96: =B10-B67 -> 7 | C96: =C10-C67 -> -1 | D96: =D10-D67 -> 14 | E96: =E10-E67 -> 3 | F96: =F10-F67 -> 2 | G96: =G10-G67 -> -2 | H96: =H10-H67 -> 7 | M96: 206 | N96: =N10-N67 -> 30 | O96: =N96/M96 -> 0.14563107
A97: Comunicación Audiovisual y Multimedios | B97: =B11-B68 -> -17 | C97: =C11-C68 -> 14 | D97: =D11-D68 -> -32 | E97: =E11-E68 -> 3 | F97: =F11-F68 -> 9 | G97: =G11-G68 -> 16 | H97: =H11-H68 -> -1 | M97: 606 | N97: =N11-N68 -> -8 | O97: =N97/M97 -> -0.01320132
A98: Comunicación Social y Periodismo | B98: =B12-B69 -> -3 | C98: =C12-C69 -> -8 | D98: =D12-D69 -> -13 | E98: =E12-E69 -> -1 | F98: =F12-F69 -> -1 | G98: =G12-G69 -> 13 | H98: =H12-H69 -> 17 | M98: 360 | N98: =N12-N69 -> 4 | O98: =N98/M98 -> 0.011111111
A99: Ciencias Políticas | B99: =B13-B70 -> 4 | C99: =C13-C70 -> -2 | D99: =D13-D70 -> -5 | E99: =E13-E70 -> 11 | F99: =F13-F70 -> -5 | G99: =G13-G70 -> 1 | H99: =H13-H70 -> -1 | M99: 85 | N99: =N13-N70 -> 3 | O99: =N99/M99 -> 0.035294118
A100: Derecho | B100: =B14-B71 -> -15 | C100: =C14-C71 -> 2 | D100: =D14-D71 -> -2 | E100: =E14-E71 -> 4 | F100: =F14-F71 -> -9 | G100: =G14-G71 -> -1 | H100: =H14-H71 -> 11 | I100: =I14-I71 -> 3 | M100: 306 | N100: =N14-N71 -> -7 | O100: =N100/M100 -> -0.022875817
A101: Licenciatura en Educación Infantil | B101: =B15-B72 -> 1 | C101: =C15-C72 -> 0 | D101: =D15-D72 -> -1 | E101: =E15-E72 -> 0 | F101: =F15-F72 -> 10 | G101: =G15-G72 -> 2 | H101: =H15-H72 -> -1 | I101: =I15-I72 -> -1 | J101: =J15-J72 -> -3 | M101: 70 | N101: =N15-N72 -> 7 | O101: =N101/M101 -> 0.1
A102: Enfermería | B102: =B16-B73 -> -3 | C102: =C16-C73 -> -3 | D102: =D16-D73 -> -4 | E102: =E16-E73 -> 0 | F102: =F16-F73 -> -6 | G102: =G16-G73 -> 2 | H102: =H16-H73 -> -4 | M102: 150 | N102: =N16-N73 -> -18 | O102: =N102/M102 -> -0.12
A103: Fisioterapia | B103: =B17-B74 -> -1 | C103: =C17-C74 -> 21 | D103: =D17-D74 -> -4 | E103: =E17-E74 -> -22 | F103: =F17-F74 -> -10 | G103: =G17-G74 -> 6 | H103: =H17-H74 -> -22 | M103: 224 | N103: =N17-N74 -> -32 | O103: =N103/M103 -> -0.14285714
...

Sheet BDD Esudiantes
A1: F3 | B1: Semestre | C1: Nombre de Programa | E1: Cuenta de Nombre de Programa | F1: Etiquetas de columna
A2: 39 | B2: 6 | C2: =VLOOKUP(A2,'Programas y Unidades'!$A:$B,2,0) -> Ingeniería Informática | E2: Etiquetas de fila | F2: 2 | G2: 3 | H2: 4 | I2: 5 | J2: 6 | K2: 7 | L2: 8 | M2: 9 | N2: 10 | O2: 11 | P2: Total general
A3: 39 | B3: 6 | C3: =VLOOKUP(A3,'Programas y Unidades'!$A:$B,2,0) -> Ingeniería Informática | E3: Administración & Servicio | F3: 9 | G3: 11 | H3: 3 | I3: 7 | J3: 12 | K3: 12 | L3: 12 | P3: 66
A4: 39 | B4: 7 | C4: =VLOOKUP(A4,'Programas y Unidades'!$A:$B,2,0) -> Ingeniería Informática | E4: Administración de Empresas | F4: 23 | G4: 12 | H4: 22 | I4: 18 | J4: 23 | K4: 19 | L4: 30 | P4: 147
A5: 39 | B5: 6 | C5: =VLOOKUP(A5,'Programas y Unidades'!$A:$B,2,0) -> Ingeniería Informática | E5: Administración de Mercadeo y Logística Internacionales | F5: 2 | G5: 29 | H5: 47 | I5: 35 | J5: 53 | K5: 29 | L5: 28 | P5: 223
A6: 39 | B6: 6 | C6: =VLOOKUP(A6,'Programas y Unidades'!$A:$B,2,0) -> Ingeniería Informática | E6: Administración de Negocios Internacionales | F6: 48 | G6: 50 | H6: 65 | I6: 48 | J6: 28 | K6: 29 | L6: 31 | P6: 299
A7: 39 | B7: 6 | C7: =VLOOKUP(A7,'Programas y Unidades'!$A:$B,2,0) -> Ingeniería Informática | E7: Comunicación Audiovisual y Multimedios | F7: 56 | G7: 35 | H7: 69 | I7: 35 | J7: 21 | K7: 18 | L7: 33 | P7: 267
A8: 39 | B8: 7 | C8: =VLOOKUP(A8,'Programas y Unidades'!$A:$B,2,0) -> Ingeniería Informática | E8: Comunicación Corporativa | F8: 12 | G8: 26 | H8: 7 | I8: 16 | J8: 22 | K8: 15 | L8: 14 | P8: 112
A9: 39 | B9: 5 | C9: =VLOOKUP(A9,'Programas y Unidades'!$A:$B,2,0) -> Ingeniería Informática | E9: Comunicación Social y Periodismo | F9: 30 | G9: 31 | H9: 45 | I9: 25 | J9: 34 | K9: 17 | L9: 14 | P9: 196
A10: 39 | B10: 5 | C10: =VLOOKUP(A10,'Programas y Unidades'!$A:$B,2,0) -> Ingeniería Informática | E10: Economía y Finanzas Internacionales | F10: 27 | G10: 17 | H10: 34 | I10: 14 | J10: 23 | K10: 13 | L10: 13 | P10: 141
A11: 39 | B11: 5 | C11: =VLOOKUP(A11,'Programas y Unidades'!$A:$B,2,0) -> Ingeniería Informática | E11: Fisioterapia | F11: 21 | G11: 1 | H11: 37 | I11: 43 | J11: 28 | K11: 19 | L11: 33 | P11: 182
A12: 39 | B12: 6 | C12: =VLOOKUP(A12,'Programas y Unidades'!$A:$B,2,0) -> Ingeniería Informática | E12: Gastronomía | F12: 31 | G12: 17 | H12: 25 | I12: 16 | J12: 23 | K12: 12 | L12: 7 | P12: 131
A13: 39 | B13: 7 | C13: =VLOOKUP(A13,'Programas y Unidades'!$A:$B,2,0) -> Ingeniería Informática | E13: Ingeniería Civil | F13: 17 | G13: 9 | H13: 12 | I13: 11 | J13: 21 | K13: 8 | L13: 23 | P13: 101
A14: 39 | B14: 7 | C14: =VLOOKUP(A14,'Programas y Unidades'!$A:$B,2,0) -> Ingeniería Informática | E14: Ingeniería Industrial | F14: 34 | G14: 22 | H14: 28 | I14: 9 | J14: 49 | K14: 23 | L14: 20 | P14: 185
... A17: 39 | B17: 6 | C17: =VLOOKUP(A17,'Programas y Unidades'!$A:$B,2,0) -> Ingeniería Informática | E17: Ingeniería Química | F17: 24 | G17: 17 | H17: 19 | I17: 18 | J17: 17 | K17: 20 | L17: 24 | P17: 139
A18: 39 | B18: 5 | C18: =VLOOKUP(A18,'Programas y Unidades'!$A:$B,2,0) -> Ingeniería Informática | E18: Licenciatura en Ciencias Naturales | H18: 2 | I18: 1 | J18: 1 | L18: 5 | M18: 2 | P18: 11
A19: 39 | B19: 7 | C19: =VLOOKUP(A19,'Programas y Unidades'!$A:$B,2,0) -> Ingeniería Informática | E19: Licenciatura en Educación Infantil | F19: 14 | G19: 5 | H19: 6 | I19: 9 | J19: 2 | K19: 4 | L19: 9 | M19: 2 | N19: 3 | P19: 54
A20: 39 | B20: 5 | C20: =VLOOKUP(A20,'Programas y Unidades'!$A:$B,2,0) -> Ingeniería Informática | E20: Psicología | F20: 49 | G20: 26 | H20: 37 | I20: 27 | J20: 18 | K20: 14 | L20: 32 | P20: 203
A21: 39 | B21: 6 | C21: =VLOOKUP(A21,'Programas y Unidades'!$A:$B,2,0) -> Ingeniería Informática | E21: Ciencia de Datos | F21: 19 | G21: 3 | I21: 2 | P21: 24
A22: 39 | B22: 6 | C22: =VLOOKUP(A22,'Programas y Unidades'!$A:$B,2,0) -> Ingeniería Informática | E22: Derecho | F22: 49 | G22: 14 | H22: 23 | I22: 16 | J22: 32 | K22: 21 | L22: 19 | M22: 16 | P22: 190
A23: 39 | B23: 5 | C23: =VLOOKUP(A23,'Programas y Unidades'!$A:$B,2,0) -> Ingeniería Informática | E23: Enfermería | F23: 27 | G23: 19 | H23: 25 | I23: 14 | J23: 16 | K23: 12 | L23: 19 | P23: 132
A24: 39 | B24: 6 | C24: =VLOOKUP(A24,'Programas y Unidades'!$A:$B,2,0) -> Ingeniería Informática | E24: Ingeniería de Producción Agroindustrial | F24: 2 | K24: 1 | L24: 10 | P24: 13
A25: 39 | B25: 5 | C25: =VLOOKUP(A25,'Programas y Unidades'!$A:$B,2,0) -> Ingeniería Informática | E25: Ingeniería de Bioproducción | F25: 5 | H25: 3 | I25: 7 | J25: 2 | K25: 2 | L25: 3 | P25: 22
A26: 39 | B26: 6 | C26: =VLOOKUP(A26,'Programas y Unidades'!$A:$B,2,0) -> Ingeniería Informática | E26: Ciencias Políticas | F26: 7 | G26: 12 | H26: 11 | I26: 6 | J26: 13 | K26: 8 | L26: 11 | P26: 68
A27: 39 | B27: 5 | C27: =VLOOKUP(A27,'Programas y Unidades'!$A:$B,2,0) -> Ingeniería Informática | E27: Filosofía | F27: 5 | G27: 1 | H27: 6 | I27: 5 | J27: 7 | K27: 1 | L27: 2 | M27: 4 | P27: 31
A28: 39 | B28: 5 | C28: =VLOOKUP(A28,'Programas y Unidades'!$A:$B,2,0) -> Ingeniería Informática | E28: Medicina | F28: 82 | G28: 69 | H28: 62 | I28: 108 | J28: 58 | K28: 54 | L28: 55 | M28: 54 | N28: 49 | O28: 88 | P28: 679
A29: 39 | B29: 6 | C29: =VLOOKUP(A29,'Programas y Unidades'!$A:$B,2,0) -> Ingeniería Informática | E29: Total general | F29: 638 | G29: 472 | H29: 639 | I29: 540 | J29: 567 | K29: 381 | L29: 506 | M29: 78 | N29: 52 | O29: 88 | P29: 3961
A30: 39 | B30: 5 | C30: =VLOOKUP(A30,'Programas y Unidades'!$A:$B,2,0) -> Ingeniería Informática
A31: 39 | B31: 8 | C31: =VLOOKUP(A31,'Programas y Unidades'!$A:$B,2,0) -> Ingeniería Informática
A32: 148 | B32: 2 | C32: =VLOOKUP(A32,'Programas y Unidades'!$A:$B,2,0) -> Ciencia de Datos
A33: 39 | B33: 7 | C33: =VLOOKUP(A33,'Programas y Unidades'!$A:$B,2,0) -> Ingeniería Informática
A34: 40 | B34: 5 | C34: =VLOOKUP(A34,'Programas y Unidades'!$A:$B,2,0) -> Ingeniería Mecánica
A35: 39 | B35: 6 | C35: =VLOOKUP(A35,'Programas y Unidades'!$A:$B,2,0) -> Ingeniería Informática
A36: 148 | B36: 3 | C36: =VLOOKUP(A36,'Programas y Unidades'!$A:$B,2,0) -> Ciencia de Datos
A37: 148 | B37: 2 | C37: =VLOOKUP(A37,'Programas y Unidades'!$A:$B,2,0) -> Ciencia de Datos
A38: 148 | B38: 5 | C38: =VLOOKUP(A38,'Programas y Unidades'!$A:$B,2,0) -> Ciencia de Datos
A39: 148 | B39: 5 | C39: =VLOOKUP(A39,'Programas y Unidades'!$A:$B,2,0) -> Ciencia de Datos
A40: 32 | B40: 8 | C40: =VLOOKUP(A40,'Programas y Unidades'!$A:$B,2,0) -> Licenciatura en Educación Infantil
A41: 32 | B41: 8 | C41: =VLOOKUP(A41,'Programas y Unidades'!$A:$B,2,0) -> Licenciatura en Educación Infantil
... A5724: 86 | B5724: 4 | C5724: =VLOOKUP(A5724,'Programas y Unidades'!$A:$B,2,0) -> Maestría en Didáctica Del Inglés Para el Aprendizaje Autodirigido - Virtual

Sheet Resumen Estudiantes y Profesore
D1: ESTUDIANTES | L1: PROFESOR PLANTA | T1: PROFESOR CATEDRA
A2: COD | B2: PROGRAMA | C2: UNIDAD | D2: Universo | E2: Muestra (ME 5 % NC 95%) | F2: Realizado | G2: Faltantes | H2: Alcance Vs Población | I2: ME (NC 95%) | J2: ME (NC 90%) | K2: Tipo de medición | L2: Universo | M2: Muestra (ME 5 % NC 95%) | N2: Realizado | O2: Faltantes | P2: Alcance Vs Población | Q2: ME (NC 95%) | R2: ME (NC 90%) | S2: Tipo de medición | T2: Universo | U2: Muestra (ME 5 % NC 95%) | V2: Realizado | W2: Faltantes | X2: Alcance Vs Población | Y2: ME (NC 95%) | Z2: ME (NC 90%) | AA2: Tipo de medición
A3: 20 | B3: Administración & Servicio | C3: ESCUELA INTERNACIONAL DE CIENCIAS ECONÓMICAS Y ADMINISTRATIVAS | D3: =VLOOKUP(B3,'Cuotas Estudiantes Pregrado'!$A$4:$N$28,13,0) -> 84 | E3: =VLOOKUP(B3,'Cuotas Estudiantes Pregrado'!$A$4:$N$28,14,0) -> 71 | F3: =VLOOKUP(B3,'BDD Estudiantes Posgrado'!$A$1:$D$200,4,0) -> 66 | G3: =VLOOKUP(B3,'Cuotas Estudiantes Pregrado'!$A$117:$M$142,13,0) -> 7 | H3: =F3/D3 -> 0.78571429 | I3: =IFERROR((((1.96^2*0.5*0.5*($D3-F3))/(F3*($D3-1)))^0.5),"") -> 0.056176065 | J3: =IFERROR((((1.65^2*0.5*0.5*($D3-F3))/(F3*($D3-1)))^0.5),"") -> 0.047291075 | K3: Encuesta | L3: ='BDD Prof. Planta'!$H$10 -> 40 | M3: 40 | N3: ='BDD Prof. Planta'!$D$10 -> 40 | O3: =M3-N3 -> 0 | P3: =N3/L3 -> 1 | Q3: =IFERROR((((1.96^2*0.5*0.5*($L3-N3))/(N3*($L3-1)))^0.5),"") -> 0 | R3: =IFERROR((((1.65^2*0.5*0.5*($L3-N3))/(N3*($L3-1)))^0.5),"") -> 0 | S3: Encuesta | T3: ='BDD Prof. Catedra'!$H$10 -> 112 | U3: 92 | V3: ='BDD Prof. Catedra'!$D$10 -> 90 | W3: =U3-V3 -> 2 | X3: =V3/T3 -> 0.80357143 | Y3: =IFERROR((((1.96^2*0.5*0.5*($T3-V3))/(V3*($T3-1)))^0.5),"") -> 0.045989075 | Z3: =IFERROR((((1.65^2*0.5*0.5*($T3-V3))/(V3*($T3-1)))^0.5),"") -> 0.038715293 | AA3: Encuesta
A4: 21 | B4: Administración de Empresas | C4: ESCUELA INTERNACIONAL DE CIENCIAS ECONÓMICAS Y ADMINISTRATIVAS | D4: =VLOOKUP(B4,'Cuotas Estudiantes Pregrado'!$A$4:$N$28,13,0) -> 253 | E4: =VLOOKUP(B4,'Cuotas Estudiantes Pregrado'!$A$4:$N$28,14,0) -> 162 | F4: =VLOOKUP(B4,'BDD Estudiantes Posgrado'!$A$1:$D$200,4,0) -> 147 | G4: =VLOOKUP(B4,'Cuotas Estudiantes Pregrado'!$A$117:$M$142,13,0) -> 21 | H4: =F4/D4 -> 0.58102767 | I4: =IFERROR((((1.96^2*0.5*0.5*($D4-F4))/(F4*($D4-1)))^0.5),"") -> 0.052422783 | J4: =IFERROR((((1.65^2*0.5*0.5*($D4-F4))/(F4*($D4-1)))^0.5),"") -> 0.044131424 | K4: Encuesta | L4: ='BDD Prof. Planta'!$H$10 -> 40 | M4: 40 | N4: ='BDD Prof. Planta'!$D$10 -> 40 | O4: =M4-N4 -> 0 | P4: =N4/L4 -> 1 | Q4: =IFERROR((((1.96^2*0.5*0.5*($L4-N4))/(N4*($L4-1)))^0.5),"") -> 0 | R4: =IFERROR((((1.65^2*0.5*0.5*($L4-N4))/(N4*($L4-1)))^0.5),"") -> 0 | S4: Encuesta | T4: ='BDD Prof. Catedra'!$H$10 -> 112 | U4: 92 | V4: ='BDD Prof. Catedra'!$D$10 -> 90 | W4: =U4-V4 -> 2 | X4: =V4/T4 -> 0.80357143 | Y4: =IFERROR((((1.96^2*0.5*0.5*($T4-V4))/(V4*($T4-1)))^0.5),"") -> 0.045989075 | Z4: =IFERROR((((1.65^2*0.5*0.5*($T4-V4))/(V4*($T4-1)))^0.5),"") -> 0.038715293 | AA4: Encuesta | AD4: Encuestas (ME <= 7,0% a NC 90%)
A5: 22 | B5: Administración de Mercadeo y Logística Internacionales | C5: ESCUELA INTERNACIONAL DE CIENCIAS ECONÓMICAS Y ADMINISTRATIVAS | D5: =VLOOKUP(B5,'Cuotas Estudiantes Pregrado'!$A$4:$N$28,13,0) -> 344 | E5: =VLOOKUP(B5,'Cuotas Estudiantes Pregrado'!$A$4:$N$28,14,0) -> 195 | F5: =VLOOKUP(B5,'BDD Estudiantes Posgrado'!$A$1:$D$200,4,0) -> 223 | G5: =VLOOKUP(B5,'Cuotas Estudiantes Pregrado'!$A$117:$M$142,13,0) -> 32 | H5: =F5/D5 -> 0.64825581 | I5: =IFERROR((((1.96^2*0.5*0.5*($D5-F5))/(F5*($D5-1)))^0.5),"") -> 0.038977975 | J5: =IFERROR((((1.65^2*0.5*0.5*($D5-F5))/(F5*($D5-1)))^0.5),"") -> 0.032813091 | K5: Encuesta | L5: ='BDD Prof. Planta'!$H$10 -> 40 | M5: 40 | N5: ='BDD Prof. Planta'!$D$10 -> 40 | O5: =M5-N5 -> 0 | P5: =N5/L5 -> 1 | Q5: =IFERROR((((1.96^2*0.5*0.5*($L5-N5))/(N5*($L5-1)))^0.5),"") -> 0 | R5: =IFERROR((((1.65^2*0.5*0.5*($L5-N5))/(N5*($L5-1)))^0.5),"") -> 0 | S5: Encuesta | T5: ='BDD Prof. Catedra'!$H$10 -> 112 | U5: 92 | V5: ='BDD Prof. Catedra'!$D$10 -> 90 | W5: =U5-V5 -> 2 | X5: =V5/T5 -> 0.80357143 | Y5: =IFERROR((((1.96^2*0.5*0.5*($T5-V5))/(V5*($T5-1)))^0.5),"") -> 0.045989075 | Z5: =IFERROR((((1.65^2*0.5*0.5*($T5-V5))/(V5*($T5-1)))^0.5),"") -> 0.038715293 | AA5: Encuesta | AD5: Encuestas (ME > 7,0% a NC 90% y Alcance >= 80%)
A6: 23 | B6: Administración de Negocios Internacionales | C6: ESCUELA INTERNACIONAL DE CIENCIAS ECONÓMICAS Y ADMINISTRATIVAS | D6: =VLOOKUP(B6,'Cuotas Estudiantes Pregrado'!$A$4:$N$28,13,0) -> 580 | E6: =VLOOKUP(B6,'Cuotas Estudiantes Pregrado'!$A$4:$N$28,14,0) -> 254 | F6: =VLOOKUP(B6,'BDD Estudiantes Posgrado'!$A$1:$D$200,4,0) -> 299 | G6: =VLOOKUP(B6,'Cuotas Estudiantes Pregrado'!$A$117:$M$142,13,0) -> 13 | H6: =F6/D6 -> 0.51551724 | I6: =IFERROR((((1.96^2*0.5*0.5*($D6-F6))/(F6*($D6-1)))^0.5),"") -> 0.039482474 | J6: =IFERROR((((1.65^2*0.5*0.5*($D6-F6))/(F6*($D6-1)))^0.5),"") -> 0.033237797 | K6: Encuesta | L6: ='BDD Prof. Planta'!$H$10 -> 40 | M6: 40 | N6: ='BDD Prof. Planta'!$D$10 -> 40 | O6: =M6-N6 -> 0 | P6: =N6/L6 -> 1 | Q6: =IFERROR((((1.96^2*0.5*0.5*($L6-N6))/(N6*($L6-1)))^0.5),"") -> 0 | R6: =IFERROR((((1.65^2*0.5*0.5*($L6-N6))/(N6*($L6-1)))^0.5),"") -> 0 | S6: Encuesta | T6: ='BDD Prof. Catedra'!$H$10 -> 112 | U6: 92 | V6: ='BDD Prof. Catedra'!$D$10 -> 90 | W6: =U6-V6 -> 2 | X6: =V6/T6 -> 0.80357143 | Y6: =IFERROR((((1.96^2*0.5*0.5*($T6-V6))/(V6*($T6-1)))^0.5),"") -> 0.045989075 | Z6: =IFERROR((((1.65^2*0.5*0.5*($T6-V6))/(V6*($T6-1)))^0.5),"") -> 0.038715293 | AA6: Encuesta | AD6: Sondeo (ME > 7,0% a NC 90% y Alcance < 80%)
A7: 24 | B7: Economía y Finanzas Internacionales | C7: ESCUELA INTERNACIONAL DE CIENCIAS ECONÓMICAS Y ADMINISTRATIVAS | D7: =VLOOKUP(B7,'Cuotas Estudiantes Pregrado'!$A$4:$N$28,13,0) -> 215 | E7: =VLOOKUP(B7,'Cuotas Estudiantes Pregrado'!$A$4:$N$28,14,0) -> 146 | F7: =VLOOKUP(B7,'BDD Estudiantes Posgrado'!$A$1:$D$200,4,0) -> 141 | G7: =VLOOKUP(B7,'Cuotas Estudiantes Pregrado'!$A$117:$M$142,13,0) -> 26 | H7: =F7/D7 -> 0.65581395 | I7: =IFERROR((((1.96^2*0.5*0.5*($D7-F7))/(F7*($D7-1)))^0.5),"") -> 0.048531699 | J7: =IFERROR((((1.65^2*0.5*0.5*($D7-F7))/(F7*($D7-1)))^0.5),"") -> 0.040855767 | K7: Encuesta | L7: ='BDD Prof. Planta'!$H$10 -> 40 | M7: 40 | N7: ='BDD Prof. Planta'!$D$10 -> 40 | O7: =M7-N7 -> 0 | P7: =N7/L7 -> 1 | Q7: =IFERROR((((1.96^2*0.5*0.5*($L7-N7))/(N7*($L7-1)))^0.5),"") -> 0 | R7: =IFERROR((((1.65^2*0.5*0.5*($L7-N7))/(N7*($L7-1)))^0.5),"") -> 0 | S7: Encuesta | T7: ='BDD Prof. Catedra'!$H$10 -> 112 | U7: 92 | V7: ='BDD Prof. Catedra'!$D$10 -> 90 | W7: =U7-V7 -> 2 | X7: =V7/T7 -> 0.80357143 | Y7: =IFERROR((((1.96^2*0.5*0.5*($T7-V7))/(V7*($T7-1)))^0.5),"") -> 0.045989075 | Z7: =IFERROR((((1.65^2*0.5*0.5*($T7-V7))/(V7*($T7-1)))^0.5),"") -> 0.038715293 | AA7: Encuesta | AD7: Sin información / Sin respuestas
A8: 25 | B8: Gastronomía | C8: ESCUELA INTERNACIONAL DE CIENCIAS ECONÓMICAS Y ADMINISTRATIVAS | D8: =VLOOKUP(B8,'Cuotas Estudiantes Pregrado'!$A$4:$N$28,13,0) -> 240 | E8: =VLOOKUP(B8,'Cuotas Estudiantes Pregrado'!$A$4:$N$28,14,0) -> 158 | F8: =VLOOKUP(B8,'BDD Estudiantes Posgrado'!$A$1:$D$200,4,0) -> 131 | G8: =VLOOKUP(B8,'Cuotas Estudiantes Pregrado'!$A$117:$M$142,13,0) -> 32 | H8: =F8/D8 -> 0.54583333 | I8: =IFERROR((((1.96^2*0.5*0.5*($D8-F8))/(F8*($D8-1)))^0.5),"") -> 0.057823547 | J8: =IFERROR((((1.65^2*0.5*0.5*($D8-F8))/(F8*($D8-1)))^0.5),"") -> 0.048677986 | K8: Encuesta | L8: ='BDD Prof. Planta'!$H$10 -> 40 | M8: 40 | N8: ='BDD Prof. Planta'!$D$10 -> 40 | O8: =M8-N8 -> 0 | P8: =N8/L8 -> 1 | Q8: =IFERROR((((1.96^2*0.5*0.5*($L8-N8))/(N8*($L8-1)))^0.5),"") -> 0 | R8: =IFERROR((((1.65^2*0.5*0.5*($L8-N8))/(N8*($L8-1)))^0.5),"") -> 0 | S8: Encuesta | T8: ='BDD Prof. Catedra'!$H$10 -> 112 | U8: 92 | V8: ='BDD Prof. Catedra'!$D$10 -> 90 | W8: =U8-V8 -> 2 | X8: =V8/T8 -> 0.80357143 | Y8: =IFERROR((((1.96^2*0.5*0.5*($T8-V8))/(V8*($T8-1)))^0.5),"") -> 0.045989075 | Z8: =IFERROR((((1.65^2*0.5*0.5*($T8-V8))/(V8*($T8-1)))^0.5),"") -> 0.038715293 | AA8: Encuesta
A9: 26 | B9: Comunicación Corporativa | C9: FACULTAD DE COMUNICACIÓN | D9: =VLOOKUP(B9,'Cuotas Estudiantes Pregrado'!$A$4:$N$28,13,0) -> 206 | E9: =VLOOKUP(B9,'Cuotas Estudiantes Pregrado'!$A$4:$N$28,14,0) -> 142 | F9: =VLOOKUP(B9,'BDD Estudiantes Posgrado'!$A$1:$D$200,4,0) -> 112 | G9: =VLOOKUP(B9,'Cuotas Estudiantes Pregrado'!$A$117:$M$142,13,0) -> 33 | H9: =F9/D9 -> 0.54368932 | I9: =IFERROR((((1.96^2*0.5*0.5*($D9-F9))/(F9*($D9-1)))^0.5),"") -> 0.062705273 | J9: =IFERROR((((1.65^2*0.5*0.5*($D9-F9))/(F9*($D9-1)))^0.5),"") -> 0.052787602 | K9: Encuesta | L9: =VLOOKUP($B9,'BDD Prof. Planta'!$A$1:$H$140,7,0) -> 15 | M9: 14 | N9: =VLOOKUP($B9,'BDD Prof. Planta'!$A$1:$L$140,12,0) -> 14 | O9: =M9-N9 -> 0 | P9: =N9/L9 -> 0.93333333 | Q9: =IFERROR((((1.96^2*0.5*0.5*($L9-N9))/(N9*($L9-1)))^0.5),"") -> 0.07 | R9: =IFERROR((((1.65^2*0.5*0.5*($L9-N9))/(N9*($L9-1)))^0.5),"") -> 0.058928571 | S9: Encuesta | T9: =VLOOKUP($B9,'BDD Prof. Catedra'!$A:$H,7,0) -> 23 | U9: 23 | V9: =VLOOKUP($B9,'BDD Prof. Catedra'!$A:$J,10,0) -> 21 | W9: =U9-V9 -> 2 | X9: =V9/T9 -> 0.91304348 | Y9: =IFERROR((((1.96^2*0.5*0.5*($T9-V9))/(V9*($T9-1)))^0.5),"") -> 0.064479266 | Z9: =IFERROR((((1.65^2*0.5*0.5*($T9-V9))/(V9*($T9-1)))^0.5),"") -> 0.054281015 | AA9: Encuesta
A10: 27 | B10: Comunicación Audiovisual y Multimedios | C10: FACULTAD DE COMUNICACIÓN | D10: =VLOOKUP(B10,'Cuotas Estudiantes Pregrado'!$A$4:$N$28,13,0) -> 606 | E10: =VLOOKUP(B10,'Cuotas Estudiantes Pregrado'!$A$4:$N$28,14,0) -> 259 | F10: =VLOOKUP(B10,'BDD Estudiantes Posgrado'!$A$1:$D$200,4,0) -> 267 | G10: =VLOOKUP(B10,'Cuotas Estudiantes Pregrado'!$A$117:$M$142,13,0) -> 42 | H10: =F10/D10 -> 0.44059406 | I10: =IFERROR((((1.96^2*0.5*0.5*($D10-F10))/(F10*($D10-1)))^0.5),"") -> 0.044894445 | J10: =IFERROR((((1.65^2*0.5*0.5*($D10-F10))/(F10*($D10-1)))^0.5),"") -> 0.037793793 | K10: Encuesta | L10: =VLOOKUP($B10,'BDD Prof. Planta'!$A$1:$H$140,7,0) -> 16 | M10: 16 | N10: =VLOOKUP($B10,'BDD Prof. Planta'!$A$1:$L$140,12,0) -> 16 | O10: =M10-N10 -> 0 | P10: =N10/L10 -> 1 | Q10: =IFERROR((((1.96^2*0.5*0.5*($L10-N10))/(N10*($L10-1)))^0.5),"") -> 0 | R10: =IFERROR((((1.65^2*0.5*0.5*($L10-N10))/(N10*($L10-1)))^0.5),"") -> 0 | S10: Encuesta | T10: =VLOOKUP($B10,'BDD Prof. Catedra'!$A:$H,7,0) -> 41 | U10: 40 | V10: =VLOOKUP($B10,'BDD Prof. Catedra'!$A:$J,10,0) -> 36 | W10: =U10-V10 -> 4 | X10: =V10/T10 -> 0.87804878 | Y10: =IFERROR((((1.96^2*0.5*0.5*($T10-V10))/(V10*($T10-1)))^0.5),"") -> 0.057747054 | Z10: =IFERROR((((1.65^2*0.5*0.5*($T10-V10))/(V10*($T10-1)))^0.5),"") -> 0.048613591 | AA10: Encuesta
A11: 28 | B11: Comunicación Social y Periodismo | C11: FACULTAD DE COMUNICACIÓN | D11: =VLOOKUP(B11,'Cuotas Estudiantes Pregrado'!$A$4:$N$28,13,0) -> 360 | E11: =VLOOKUP(B11,'Cuotas Estudiantes Pregrado'!$A$4:$N$28,14,0) -> 200 | F11: =VLOOKUP(B11,'BDD Estudiantes Posgrado'!$A$1:$D$200,4,0) -> 196 | G11: =VLOOKUP(B11,'Cuotas Estudiantes Pregrado'!$A$117:$M$142,13,0) -> 30 | H11: =F11/D11 -> 0.54444444 | I11: =IFERROR((((1.96^2*0.5*0.5*($D11-F11))/(F11*($D11-1)))^0.5),"") -> 0.047312156 | J11: =IFERROR((((1.65^2*0.5*0.5*($D11-F11))/(F11*($D11-1)))^0.5),"") -> 0.039829111 | K11: Encuesta | L11: =VLOOKUP($B11,'BDD Prof. Planta'!$A$1:$H$140,7,0) -> 14 | M11: 14 | N11: =VLOOKUP($B11,'BDD Prof. Planta'!$A$1:$L$140,12,0) -> 14 | O11: =M11-N11 -> 0 | P11: =N11/L11 -> 1 | Q11: =IFERROR((((1.96^2*0.5*0.5*($L11-N11))/(N11*($L11-1)))^0.5),"") -> 0 | R11: =IFERROR((((1.65^2*0.5*0.5*($L11-N11))/(N11*($L11-1)))^0.5),"") -> 0 | S11: Encuesta | T11: =VLOOKUP($B11,'BDD Prof. Catedra'!$A:$H,7,0) -> 35 | U11: 34 | V11: =VLOOKUP($B11,'BDD Prof. Catedra'!$A:$J,10,0) -> 28 | W11: =U11-V11 -> 6 | X11: =V11/T11 -> 0.8 | Y11: =IFERROR((((1.96^2*0.5*0.5*($T11-V11))/(V11*($T11-1)))^0.5),"") -> 0.084034307 | Z11: =IFERROR((((1.65^2*0.5*0.5*($T11-V11))/(V11*($T11-1)))^0.5),"") -> 0.070743166 | AA11: Encuesta
A12: 29 | B12: Ciencias Políticas | C12: FACULTAD DE DERECHO Y CIENCIAS POLÍTICAS | D12: =VLOOKUP(B12,'Cuotas Estudiantes Pregrado'!$A$4:$N$28,13,0) -> 85 | E12: =VLOOKUP(B12,'Cuotas Estudiantes Pregrado'!$A$4:$N$28,14,0) -> 71 | F12: =VLOOKUP(B12,'BDD Estudiantes Posgrado'!$A$1:$D$200,4,0) -> 68 | G12: =VLOOKUP(B12,'Cuotas Estudiantes Pregrado'!$A$117:$M$142,13,0) -> 16 | H12: =F12/D12 -> 0.8 | I12: =IFERROR((((1.96^2*0.5*0.5*($D12-F12))/(F12*($D12-1)))^0.5),"") -> 0.053463383 | J12: =IFERROR((((1.65^2*0.5*0.5*($D12-F12))/(F12*($D12-1)))^0.5),"") -> 0.04500744 | K12: Encuesta | L12: =VLOOKUP($B12,'BDD Prof. Planta'!$A$1:$H$140,7,0) -> 8 | M12: 8 | N12: =VLOOKUP($B12,'BDD Prof. Planta'!$A$1:$L$140,12,0) -> 8 | O12: =M12-N12 -> 0 | P12: =N12/L12 -> 1 | Q12: =IFERROR((((1.96^2*0.5*0.5*($L12-N12))/(N12*($L12-1)))^0.5),"") -> 0 | R12: =IFERROR((((1.65^2*0.5*0.5*($L12-N12))/(N12*($L12-1)))^0.5),"") -> 0 | S12: Encuesta | T12: =VLOOKUP($B12,'BDD Prof. Catedra'!$A:$H,7,0) -> 8 | U12: 8 | V12: =VLOOKUP($B12,'BDD Prof. Catedra'!$A:$J,10,0) -> 8 | W12: =U12-V12 -> 0 | X12: =V12/T12 -> 1 | Y12: =IFERROR((((1.96^2*0.5*0.5*($T12-V12))/(V12*($T12-1)))^0.5),"") -> 0 | Z12: =IFERROR((((1.65^2*0.5*0.5*($T12-V12))/(V12*($T12-1)))^0.5),"") -> 0 | AA12: Encuesta
A13: 30 | B13: Derecho | C13: FACULTAD DE DERECHO Y CIENCIAS POLÍTICAS | D13: =VLOOKUP(B13,'Cuotas Estudiantes Pregrado'!$A$4:$N$28,13,0) -> 306 | E13: =VLOOKUP(B13,'Cuotas Estudiantes Pregrado'!$A$4:$N$28,14,0) -> 183 | F13: =VLOOKUP(B13,'BDD Estudiantes Posgrado'!$A$1:$D$200,4,0) -> 190 | G13: =VLOOKUP(B13,'Cuotas Estudiantes Pregrado'!$A$117:$M$142,13,0) -> 20 | H13: =F13/D13 -> 0.62091503 | I13: =IFERROR((((1.96^2*0.5*0.5*($D13-F13))/(F13*($D13-1)))^0.5),"") -> 0.043845836 | J13: =IFERROR((((1.65^2*0.5*0.5*($D13-F13))/(F13*($D13-1)))^0.5),"") -> 0.036911035 | K13: Encuesta | L13: =VLOOKUP($B13,'BDD Prof. Planta'!$A$1:$H$140,7,0) -> 26 | M13: 26 | N13: =VLOOKUP($B13,'BDD Prof. Planta'!$A$1:$L$140,12,0) -> 26 | O13: =M13-N13 -> 0 | P13: =N13/L13 -> 1 | Q13: =IFERROR((((1.96^2*0.5*0.5*($L13-N13))/(N13*($L13-1)))^0.5),"") -> 0 | R13: =IFERROR((((1.65^2*0.5*0.5*($L13-N13))/(N13*($L13-1)))^0.5),"") -> 0 | S13: Encuesta | T13: =VLOOKUP($B13,'BDD Prof. Catedra'!$A:$H,7,0) -> 24 | U13: 24 | V13: =VLOOKUP($B13,'BDD Prof. Catedra'!$A:$J,10,0) -> 24 | W13: =U13-V13 -> 0 | X13: =V13/T13 -> 1 | Y13: =IFERROR((((1.96^2*0.5*0.5*($T13-V13))/(V13*($T13-1)))^0.5),"") -> 0 | Z13: =IFERROR((((1.65^2*0.5*0.5*($T13-V13))/(V13*($T13-1)))^0.5),"") -> 0 | AA13: Encuesta
A14: 31 | B14: Licenciatura en Ciencias Naturales | C14: FACULTAD DE EDUCACIÓN | D14: =VLOOKUP(B14,'Cuotas Estudiantes Pregrado'!$A$4:$N$28,13,0) -> 27 | E14: 26 | F14: =VLOOKUP(B14,'BDD Estudiantes Posgrado'!$A$1:$D$200,4,0) -> 11 | G14: =VLOOKUP(B14,'Cuotas Estudiantes Pregrado'!$A$117:$M$142,13,0) -> 18 | H14: =F14/D14 -> 0.40740741 | I14: =IFERROR((((1.96^2*0.5*0.5*($D14-F14))/(F14*($D14-1)))^0.5),"") -> 0.23179446 | J14: =IFERROR((((1.65^2*0.5*0.5*($D14-F14))/(F14*($D14-1)))^0.5),"") -> 0.19513309 | K14: Sondeo | L14: =VLOOKUP($B14,'BDD Prof. Planta'!$A$1:$H$140,7,0) -> 8 | M14: 8 | N14: =VLOOKUP($B14,'BDD Prof. Planta'!$A$1:$L$140,12,0) -> 7 | O14: =M14-N14 -> 1 | P14: =N14/L14 -> 0.875 | Q14: =IFERROR((((1.96^2*0.5*0.5*($L14-N14))/(N14*($L14-1)))^0.5),"") -> 0.14 | R14: =IFERROR((((1.65^2*0.5*0.5*($L14-N14))/(N14*($L14-1)))^0.5),"") -> 0.11785714 | S14: Encuesta | T14: =VLOOKUP($B14,'BDD Prof. Catedra'!$A:$H,7,0) -> 12 | U14: 11 | V14: =VLOOKUP($B14,'BDD Prof. Catedra'!$A:$J,10,0) -> 10 | W14: =U14-V14 -> 1 | X14: =V14/T14 -> 0.83333333 | Y14: =IFERROR((((1.96^2*0.5*0.5*($T14-V14))/(V14*($T14-1)))^0.5),"") -> 0.13214317 | Z14: =IFERROR((((1.65^2*0.5*0.5*($T14-V14))/(V14*($T14-1)))^0.5),"") -> 0.11124298 | AA14: Encuesta
A15: 32 | B15: Licenciatura en Educación Infantil | C15: FACULTAD DE EDUCACIÓN | D15: =VLOOKUP(B15,'Cuotas Estudiantes Pregrado'!$A$4:$N$28,13,0) -> 70 | E15: =VLOOKUP(B15,'Cuotas Estudiantes Pregrado'!$A$4:$N$28,14,0) -> 61 | F15: =VLOOKUP(B15,'BDD Estudiantes Posgrado'!$A$1:$D$200,4,0) -> 54 | G15: =VLOOKUP(B15,'Cuotas Estudiantes Pregrado'!$A$117:$M$142,13,0) -> 13 | H15: =F15/D15 -> 0.77142857 | I15: =IFERROR((((1.96^2*0.5*0.5*($D15-F15))/(F15*($D15-1)))^0.5),"") -> 0.064219163 | J15: =IFERROR((((1.65^2*0.5*0.5*($D15-F15))/(F15*($D15-1)))^0.5),"") -> 0.054062051 | K15: Encuesta | L15: =VLOOKUP($B15,'BDD Prof. Planta'!$A$1:$H$140,7,0) -> 9 | M15: 9 | N15: =VLOOKUP($B15,'BDD Prof. Planta'!$A$1:$L$140,12,0) -> 8 | O15: =M15-N15 -> 1 | P15: =N15/L15 -> 0.88888889 | Q15: =IFERROR((((1.96^2*0.5*0.5*($L15-N15))/(N15*($L15-1)))^0.5),"") -> 0.1225 | R15: =IFERROR((((1.65^2*0.5*0.5*($L15-N15))/(N15*($L15-1)))^0.5),"") -> 0.103125 | S15: Encuesta | T15: =VLOOKUP($B15,'BDD Prof. Catedra'!$A:$H,7,0) -> 15 | U15: 14 | V15: =VLOOKUP($B15,'BDD Prof. Catedra'!$A:$J,10,0) -> 13 | W15: =U15-V15 -> 1 | X15: =V15/T15 -> 0.86666667 | Y15: =IFERROR((((1.96^2*0.5*0.5*($T15-V15))/(V15*($T15-1)))^0.5),"") -> 0.10273191 | Z15: =IFERROR((((1.65^2*0.5*0.5*($T15-V15))/(V15*($T15-1)))^0.5),"") -> 0.086483499 | AA15: Encuesta
A16: 33 | B16: Enfermería | C16: FACULTAD DE ENFERMERÍA Y REHABILITACIÓN | D16: =VLOOKUP(B16,'Cuotas Estudiantes Pregrado'!$A$4:$N$28,13,0) -> 150 | E16: =VLOOKUP(B16,'Cuotas Estudiantes Pregrado'!$A$4:$N$28,14,0) -> 114 | F16: =VLOOKUP(B16,'BDD Estudiantes Posgrado'!$A$1:$D$200,4,0) -> 132 | G16: =VLOOKUP(B16,'Cuotas Estudiantes Pregrado'!$A$117:$M$142,13,0) -> 2 | H16: =F16/D16 -> 0.88 | I16: =IFERROR((((1.96^2*0.5*0.5*($D16-F16))/(F16*($D16-1)))^0.5),"") -> 0.029647101 | J16: =IFERROR((((1.65^2*0.5*0.5*($D16-F16))/(F16*($D16-1)))^0.5),"") -> 0.024958018 | K16: Encuesta | L16: =VLOOKUP($B16,'BDD Prof. Planta'!$A$1:$H$140,7,0) -> 14 | M16: 14 | N16: =VLOOKUP($B16,'BDD Prof. Planta'!$A$1:$L$140,12,0) -> 14 | O16: =M16-N16 -> 0 | P16: =N16/L16 -> 1 | Q16: =IFERROR((((1.96^2*0.5*0.5*($L16-N16))/(N16*($L16-1)))^0.5),"") -> 0 | R16: =IFERROR((((1.65^2*0.5*0.5*($L16-N16))/(N16*($L16-1)))^0.5),"") -> 0 | S16: Encuesta | T16: =VLOOKUP($B16,'BDD Prof. Catedra'!$A:$H,7,0) -> 6 | U16: 6 | V16: =VLOOKUP($B16,'BDD Prof. Catedra'!$A:$J,10,0) -> 5 | W16: =U16-V16 -> 1 | X16: =V16/T16 -> 0.83333333 | Y16: =IFERROR((((1.96^2*0.5*0.5*($T16-V16))/(V16*($T16-1)))^0.5),"") -> 0.196 | Z16: =IFERROR((((1.65^2*0.5*0.5*($T16-V16))/(V16*($T16-1)))^0.5),"") -> 0.165 | AA16: Encuesta
A17: 34 | B17: Fisioterapia | C17: FACULTAD DE ENFERMERÍA Y REHABILITACIÓN | D17: =VLOOKUP(B17,'Cuotas Estudiantes Pregrado'!$A$4:$N$28,13,0) -> 224 | E17: =VLOOKUP(B17,'Cuotas Estudiantes Pregrado'!$A$4:$N$28,14,0) -> 150 | F17: =VLOOKUP(B17,'BDD Estudiantes Posgrado'!$A$1:$D$200,4,0) -> 182 | G17: =VLOOKUP(B17,'Cuotas Estudiantes Pregrado'!$A$117:$M$142,13,0) -> 27 | H17: =F17/D17 -> 0.8125 | I17: =IFERROR((((1.96^2*0.5*0.5*($D17-F17))/(F17*($D17-1)))^0.5),"") -> 0.031525544 | J17: =IFERROR((((1.65^2*0.5*0.5*($D17-F17))/(F17*($D17-1)))^0.5),"") -> 0.026539361 | K17: Encuesta | L17: =VLOOKUP($B17,'BDD Prof. Planta'!$A$1:$H$140,7,0) -> 23 | M17: 23 | N17: =VLOOKUP($B17,'BDD Prof. Planta'!$A$1:$L$140,12,0) -> 23 | O17: =M17-N17 -> 0 | P17: =N17/L17 -> 1 | Q17: =IFERROR((((1.96^2*0.5*0.5*($L17-N17))/(N17*($L17-1)))^0.5),"") -> 0 | R17: =IFERROR((((1.65^2*0.5*0.5*($L17-N17))/(N17*($L17-1)))^0.5),"") -> 0 | S17: Encuesta | T17: =VLOOKUP($B17,'BDD Prof. Catedra'!$A:$H,7,0) -> 3 | U17: 3 | V17: =VLOOKUP($B17,'BDD Prof. Catedra'!$A:$J,10,0) -> 3 | W17: =U17-V17 -> 0 | X17: =V17/T17 -> 1 | Y17: =IFERROR((((1.96^2*0.5*0.5*($T17-V17))/(V17*($T17-1)))^0.5),"") -> 0 | Z17: =IFERROR((((1.65^2*0.5*0.5*($T17-V17))/(V17*($T17-1)))^0.5),"") -> 0 | AA17: Encuesta
A18: 35 | B18: Filosofía | C18: FACULTAD DE FILOSOFÍA Y CIENCIAS HUMANAS | D18: =VLOOKUP(B18,'Cuotas Estudiantes Pregrado'!$A$4:$N$28,13,0) -> 34 | E18: =VLOOKUP(B18,'Cuotas Estudiantes Pregrado'!$A$4:$N$28,14,0) -> 34 | F18: =VLOOKUP(B18,'BDD Estudiantes Posgrado'!$A$1:$D$200,4,0) -> 31 | G18: =VLOOKUP(B18,'Cuotas Estudiantes Pregrado'!$A$117:$M$142,13,0) -> 6 | H18: =F18/D18 -> 0.91176471 | I18: =IFERROR((((1.96^2*0.5*0.5*($D18-F18))/(F18*($D18-1)))^0.5),"") -> 0.053069975 | J18: =IFERROR((((1.65^2*0.5*0.5*($D18-F18))/(F18*($D18-1)))^0.5),"") -> 0.044676255 | K18: Encuesta | L18: =VLOOKUP($B18,'BDD Prof. Planta'!$A$1:$H$140,7,0) -> 5 | M18: 5 | N18: =VLOOKUP($B18,'BDD Prof. Planta'!$A$1:$L$140,12,0) -> 5 | O18: =M18-N18 -> 0 | P18: =N18/L18 -> 1 | Q18: =IFERROR((((1.96^2*0.5*0.5*($L18-N18))/(N18*($L18-1)))^0.5),"") -> 0 | R18: =IFERROR((((1.65^2*0.5*0.5*($L18-N18))/(N18*($L18-1)))^0.5),"") -> 0 | S18: Encuesta | T18: =VLOOKUP($B18,'BDD Prof. Catedra'!$A:$H,7,0) -> 5 | U18: 5 | V18: =VLOOKUP($B18,'BDD Prof. Catedra'!$A:$J,10,0) -> 5 | W18: =U18-V18 -> 0 | X18: =V18/T18 -> 1 | Y18: =IFERROR((((1.96^2*0.5*0.5*($T18-V18))/(V18*($T18-1)))^0.5),"") -> 0 | Z18: =IFERROR((((1.65^2*0.5*0.5*($T18-V18))/(V18*($T18-1)))^0.5),"") -> 0 | AA18: Encuesta
A19: 36 | B19: Ingeniería Civil | C19: FACULTAD DE INGENIERÍA | D19: =VLOOKUP(B19,'Cuotas Estudiantes Pregrado'!$A$4:$N$28,13,0) -> 114 | E19: =VLOOKUP(B19,'Cuotas Estudiantes Pregrado'!$A$4:$N$28,14,0) -> 91 | F19: =VLOOKUP(B19,'BDD Estudiantes Posgrado'!$A$1:$D$200,4,0) -> 101 | G19: =VLOOKUP(B19,'Cuotas Estudiantes Pregrado'!$A$117:$M$142,13,0) -> 3 | H19: =F19/D19 -> 0.88596491 | I19: =IFERROR((((1.96^2*0.5*0.5*($D19-F19))/(F19*($D19-1)))^0.5),"") -> 0.033074847 | J19: =IFERROR((((1.65^2*0.5*0.5*($D19-F19))/(F19*($D19-1)))^0.5),"") -> 0.027843621 | K19: Encuesta | L19: =VLOOKUP($B19,'BDD Prof. Planta'!$A$1:$H$140,7,0) -> 5 | M19: 5 | N19: =VLOOKUP($B19,'BDD Prof. Planta'!$A$1:$L$140,12,0) -> 5 | O19: =M19-N19 -> 0 | P19: =N19/L19 -> 1 | Q19: =IFERROR((((1.96^2*0.5*0.5*($L19-N19))/(N19*($L19-1)))^0.5),"") -> 0 | R19: =IFERROR((((1.65^2*0.5*0.5*($L19-N19))/(N19*($L19-1)))^0.5),"") -> 0 | S19: Encuesta | T19: =VLOOKUP($B19,'BDD Prof. Catedra'!$A:$H,7,0) -> 13 | U19: 13 | V19: =VLOOKUP($B19,'BDD Prof. Catedra'!$A:$J,10,0) -> 13 | W19: =U19-V19 -> 0 | X19: =V19/T19 -> 1 | Y19: =IFERROR((((1.96^2*0.5*0.5*($T19-V19))/(V19*($T19-1)))^0.5),"") -> 0 | Z19: =IFERROR((((1.65^2*0.5*0.5*($T19-V19))/(V19*($T19-1)))^0.5),"") -> 0 | AA19: Encuesta
A20: 37 | B20: Ingeniería de Bioproducción / Producción Agroindustrial | C20: FACULTAD DE INGENIERÍA | D20: =VLOOKUP(B20,'Cuotas Estudiantes Pregrado'!$A$4:$N$28,13,0) -> 47 | E20: 35 | F20: =VLOOKUP(B20,'BDD Estudiantes Posgrado'!$A$1:$D$200,4,0) -> 35 | G20: =VLOOKUP(B20,'Cuotas Estudiantes Pregrado'!$A$117:$M$142,13,0) -> 7 | H20: =F20/D20 -> 0.74468085 | I20: =IFERROR((((1.96^2*0.5*0.5*($D20-F20))/(F20*($D20-1)))^0.5),"") -> 0.084606506 | J20: =IFERROR((((1.65^2*0.5*0.5*($D20-F20))/(F20*($D20-1)))^0.5),"") -> 0.071224865 | K20: Encuesta | L20: =VLOOKUP($B20,'BDD Prof. Planta'!$A$1:$H$140,7,0) -> 11 | M20: 10 | N20: =VLOOKUP($B20,'BDD Prof. Planta'!$A$1:$L$140,12,0) -> 9 | O20: =M20-N20 -> 1 | P20: =N20/L20 -> 0.81818182 | Q20: =IFERROR((((1.96^2*0.5*0.5*($L20-N20))/(N20*($L20-1)))^0.5),"") -> 0.14608977 | R20: =IFERROR((((1.65^2*0.5*0.5*($L20-N20))/(N20*($L20-1)))^0.5),"") -> 0.12298374 | S20: Encuesta | T20: =VLOOKUP($B20,'BDD Prof. Catedra'!$A:$H,7,0) -> 4 | U20: 4 | V20: =VLOOKUP($B20,'BDD Prof. Catedra'!$A:$J,10,0) -> 3 | W20: =U20-V20 -> 1 | X20: =V20/T20 -> 0.75 | Y20: =IFERROR((((1.96^2*0.5*0.5*($T20-V20))/(V20*($T20-1)))^0.5),"") -> 0.32666667 | Z20: =IFERROR((((1.65^2*0.5*0.5*($T20-V20))/(V20*($T20-1)))^0.5),"") -> 0.275 | AA20: Sondeo
A21: 38 | B21: Ingeniería Industrial | C21: FACULTAD DE INGENIERÍA | D21: =VLOOKUP(B21,'Cuotas Estudiantes Pregrado'!$A$4:$N$28,13,0) -> 287 | E21: =VLOOKUP(B21,'Cuotas Estudiantes Pregrado'!$A$4:$N$28,14,0) -> 174 | F21: =VLOOKUP(B21,'BDD Estudiantes Posgrado'!$A$1:$D$200,4,0) -> 185 | G21: =VLOOKUP(B21,'Cuotas Estudiantes Pregrado'!$A$117:$M$142,13,0) -> 8 | H21: =F21/D21 -> 0.6445993 | I21: =IFERROR((((1.96^2*0.5*0.5*($D21-F21))/(F21*($D21-1)))^0.5),"") -> 0.043028606 | J21: =IFERROR((((1.65^2*0.5*0.5*($D21-F21))/(F21*($D21-1)))^0.5),"") -> 0.036223062 | K21: Encuesta | L21: =VLOOKUP($B21,'BDD Prof. Planta'!$A$1:$H$140,7,0) -> 21 | M21: 20 | N21: =VLOOKUP($B21,'BDD Prof. Planta'!$A$1:$L$140,12,0) -> 19 | O21: =M21-N21 -> 1 | P21: =N21/L21 -> 0.9047619 | Q21: =IFERROR((((1.96^2*0.5*0.5*($L21-N21))/(N21*($L21-1)))^0.5),"") -> 0.071096673 | R21: =IFERROR((((1.65^2*0.5*0.5*($L21-N21))/(N21*($L21-1)))^0.5),"") -> 0.059851791 | S21: Encuesta | T21: =VLOOKUP($B21,'BDD Prof. Catedra'!$A:$H,7,0) -> 21 | U21: 21 | V21: =VLOOKUP($B21,'BDD Prof. Catedra'!$A:$J,10,0) -> 15 | W21: =U21-V21 -> 6 | X21: =V21/T21 -> 0.71428571 | Y21: =IFERROR((((1.96^2*0.5*0.5*($T21-V21))/(V21*($T21-1)))^0.5),"") -> 0.13859293 | Z21: =IFERROR((((1.65^2*0.5*0.5*($T21-V21))/(V21*($T21-1)))^0.5),"") -> 0.11667262 | AA21: Sondeo
A22: 39 | B22: Ingeniería Informática | C22: FACULTAD DE INGENIERÍA | D22: =VLOOKUP(B22,'Cuotas Estudiantes Pregrado'!$A$4:$N$28,13,0) -> 322 | E22: =VLOOKUP(B22,'Cuotas Estudiantes Pregrado'!$A$4:$N$28,14,0) -> 189 | F22: =VLOOKUP(B22,'BDD Estudiantes Posgrado'!$A$1:$D$200,4,0) -> 209 | G22: =VLOOKUP(B22,'Cuotas Estudiantes Pregrado'!$A$117:$M$142,13,0) -> 22 | H22: =F22/D22 -> 0.64906832 | I22: =IFERROR((((1.96^2*0.5*0.5*($D22-F22))/(F22*($D22-1)))^0.5),"") -> 0.040219775 | J22: =IFERROR((((1.65^2*0.5*0.5*($D22-F22))/(F22*($D22-1)))^0.5),"") -> 0.033858484 | K22: Encuesta | L22: =VLOOKUP($B22,'BDD Prof. Planta'!$A$1:$H$140,7,0) -> 7 | M22: 7 | N22: =VLOOKUP($B22,'BDD Prof. Planta'!$A$1:$L$140,12,0) -> 7 | O22: =M22-N22 -> 0 | P22: =N22/L22 -> 1 | Q22: =IFERROR((((1.96^2*0.5*0.5*($L22-N22))/(N22*($L22-1)))^0.5),"") -> 0 | R22: =IFERROR((((1.65^2*0.5*0.5*($L22-N22))/(N22*($L22-1)))^0.5),"") -> 0 | S22: Encuesta | T22: =VLOOKUP($B22,'BDD Prof. Catedra'!$A:$H,7,0) -> 34 | U22: 33 | V22: =VLOOKUP($B22,'BDD Prof. Catedra'!$A:$J,10,0) -> 19 | W22: =U22-V22 -> 14 | X22: =V22/T22 -> 0.55882353 | Y22: =IFERROR((((1.96^2*0.5*0.5*($T22-V22))/(V22*($T22-1)))^0.5),"") -> 0.15157862 | Z22: =IFERROR((((1.65^2*0.5*0.5*($T22-V22))/(V22*($T22-1)))^0.5),"") -> 0.12760445 | AA22: Sondeo
A23: 40 | B23: Ingeniería Mecánica | C23: FACULTAD DE INGENIERÍA | D23: =VLOOKUP(B23,'Cuotas Estudiantes Pregrado'!$A$4:$N$28,13,0) -> 175 | E23: =VLOOKUP(B23,'Cuotas Estudiantes Pregrado'!$A$4:$N$28,14,0) -> 126 | F23: =VLOOKUP(B23,'BDD Estudiantes Posgrado'!$A$1:$D$200,4,0) -> 136 | G23: =VLOOKUP(B23,'Cuotas Estudiantes Pregrado'!$A$117:$M$142,13,0) -> 8 | H23: =F23/D23 -> 0.77714286 | I23: =IFERROR((((1.96^2*0.5*0.5*($D23-F23))/(F23*($D23-1)))^0.5),"") -> 0.039784536 | J23: =IFERROR((((1.65^2*0.5*0.5*($D23-F23))/(F23*($D23-1)))^0.5),"") -> 0.033492084 | K23: Encuesta | L23: =VLOOKUP($B23,'BDD Prof. Planta'!$A$1:$H$140,7,0) -> 6 | M23: 6 | N23: =VLOOKUP($B23,'BDD Prof. Planta'!$A$1:$L$140,12,0) -> 6 | O23: =M23-N23 -> 0 | P23: =N23/L23 -> 1 | Q23: =IFERROR((((1.96^2*0.5*0.5*($L23-N23))/(N23*($L23-1)))^0.5),"") -> 0 | R23: =IFERROR((((1.65^2*0.5*0.5*($L23-N23))/(N23*($L23-1)))^0.5),"") -> 0 | S23: Encuesta | T23: =VLOOKUP($B23,'BDD Prof. Catedra'!$A:$H,7,0) -> 12 | U23: 12 | V23: =VLOOKUP($B23,'BDD Prof. Catedra'!$A:$J,10,0) -> 9 | W23: =U23-V23 -> 3 | X23: =V23/T23 -> 0.75 | Y23: =IFERROR((((1.96^2*0.5*0.5*($T23-V23))/(V23*($T23-1)))^0.5),"") -> 0.1705961 | Z23: =IFERROR((((1.65^2*0.5*0.5*($T23-V23))/(V23*($T23-1)))^0.5),"") -> 0.14361407 | AA23: Sondeo
A24: 41 | B24: Ingeniería Química | C24: FACULTAD DE INGENIERÍA | D24: =VLOOKUP(B24,'Cuotas Estudiantes Pregrado'!$A$4:$N$28,13,0) -> 197 | E24: =VLOOKUP(B24,'Cuotas Estudiantes Pregrado'!$A$4:$N$28,14,0) -> 137 | F24: =VLOOKUP(B24,'BDD Estudiantes Posgrado'!$A$1:$D$200,4,0) -> 139 | G24: =VLOOKUP(B24,'Cuotas Estudiantes Pregrado'!$A$117:$M$142,13,0) -> 11 | H24: =F24/D24 -> 0.70558376 | I24: =IFERROR((((1.96^2*0.5*0.5*($D24-F24))/(F24*($D24-1)))^0.5),"") -> 0.045217301 | J24: =IFERROR((((1.65^2*0.5*0.5*($D24-F24))/(F24*($D24-1)))^0.5),"") -> 0.038065585 | K24: Encuesta | L24: =VLOOKUP($B24,'BDD Prof. Planta'!$A$1:$H$140,7,0) -> 13 | M24: 13 | N24: =VLOOKUP($B24,'BDD Prof. Planta'!$A$1:$L$140,12,0) -> 12 | O24: =M24-N24 -> 1 | P24: =N24/L24 -> 0.92307692 | Q24: =IFERROR((((1.96^2*0.5*0.5*($L24-N24))/(N24*($L24-1)))^0.5),"") -> 0.081666667 | R24: =IFERROR((((1.65^2*0.5*0.5*($L24-N24))/(N24*($L24-1)))^0.5),"") -> 0.06875 | S24: Encuesta | T24: =VLOOKUP($B24,'BDD Prof. Catedra'!$A:$H,7,0) -> 27 | U24: 27 | V24: =VLOOKUP($B24,'BDD Prof. Catedra'!$A:$J,10,0) -> 18 | W24: =U24-V24 -> 9 | X24: =V24/T24 -> 0.66666667 | Y24: =IFERROR((((1.96^2*0.5*0.5*($T24-V24))/(V24*($T24-1)))^0.5),"") -> 0.13590155 | Z24: =IFERROR((((1.65^2*0.5*0.5*($T24-V24))/(V24*($T24-1)))^0.5),"") -> 0.11440692 | AA24: Sondeo
A25: 42 | B25: Medicina | C25: FACULTAD DE MEDICINA | D25: =VLOOKUP(B25,'Cuotas Estudiantes Pregrado'!$A$4:$N$28,13,0) -> 972 | E25: =VLOOKUP(B25,'Cuotas Estudiantes Pregrado'!$A$4:$N$28,14,0) -> 306 | F25: =VLOOKUP(B25,'BDD Estudiantes Posgrado'!$A$1:$D$200,4,0) -> 679 | G25: =VLOOKUP(B25,'Cuotas Estudiantes Pregrado'!$A$117:$M$142,13,0) -> 0 | H25: =F25/D25 -> 0.69855967 | I25: =IFERROR((((1.96^2*0.5*0.5*($D25-F25))/(F25*($D25-1)))^0.5),"") -> 0.02065929 | J25: =IFERROR((((1.65^2*0.5*0.5*($D25-F25))/(F25*($D25-1)))^0.5),"") -> 0.017391749 | K25: Encuesta | L25: =VLOOKUP($B25,'BDD Prof. Planta'!$A$1:$H$140,7,0) -> 53 | M25: 50 | N25: =VLOOKUP($B25,'BDD Prof. Planta'!$A$1:$L$140,12,0) -> 48 | O25: =M25-N25 -> 2 | P25: =N25/L25 -> 0.90566038 | Q25: =IFERROR((((1.96^2*0.5*0.5*($L25-N25))/(N25*($L25-1)))^0.5),"") -> 0.043862036 | R25: =IFERROR((((1.65^2*0.5*0.5*($L25-N25))/(N25*($L25-1)))^0.5),"") -> 0.036924673 | S25: Encuesta | T25: =VLOOKUP($B25,'BDD Prof. Catedra'!$A:$H,7,0) -> 70 | U25: 61 | V25: =VLOOKUP($B25,'BDD Prof. Catedra'!$A:$J,10,0) -> 45 | W25: =U25-V25 -> 16 | X25: =V25/T25 -> 0.64285714 | Y25: =IFERROR((((1.96^2*0.5*0.5*($T25-V25))/(V25*($T25-1)))^0.5),"") -> 0.087935711 | Z25: =IFERROR((((1.65^2*0.5*0.5*($T25-V25))/(V25*($T25-1)))^0.5),"") -> 0.074027512 | AA25: Sondeo
A26: 43 | B26: Psicología | C26: FACULTAD DE PSICOLOGÍA | D26: =VLOOKUP(B26,'Cuotas Estudiantes Pregrado'!$A$4:$N$28,13,0) -> 340 | E26: =VLOOKUP(B26,'Cuotas Estudiantes Pregrado'!$A$4:$N$28,14,0) -> 195 | F26: =VLOOKUP(B26,'BDD Estudiantes Posgrado'!$A$1:$D$200,4,0) -> 205 | G26: =VLOOKUP(B26,'Cuotas Estudiantes Pregrado'!$A$117:$M$142,13,0) -> 19 | H26: =F26/D26 -> 0.60294118 | I26: =IFERROR((((1.96^2*0.5*0.5*($D26-F26))/(F26*($D26-1)))^0.5),"") -> 0.04319328 | J26: =IFERROR((((1.65^2*0.5*0.5*($D26-F26))/(F26*($D26-1)))^0.5),"") -> 0.036361689 | K26: Encuesta | L26: =VLOOKUP($B26,'BDD Prof. Planta'!$A$1:$H$140,7,0) -> 17 | M26: 16 | N26: =VLOOKUP($B26,'BDD Prof. Planta'!$A$1:$L$140,12,0) -> 16 | O26: =M26-N26 -> 0 | P26: =N26/L26 -> 0.94117647 | Q26: =IFERROR((((1.96^2*0.5*0.5*($L26-N26))/(N26*($L26-1)))^0.5),"") -> 0.06125 | R26: =IFERROR((((1.65^2*0.5*0.5*($L26-N26))/(N26*($L26-1)))^0.5),"") -> 0.0515625 | S26: Encuesta | T26: =VLOOKUP($B26,'BDD Prof. Catedra'!$A:$H,7,0) -> 14 | U26: 14 | V26: =VLOOKUP($B26,'BDD Prof. Catedra'!$A:$J,10,0) -> 13 | W26: =U26-V26 -> 1 | X26: =V26/T26 -> 0.92857143 | Y26: =IFERROR((((1.96^2*0.5*0.5*($T26-V26))/(V26*($T26-1)))^0.5),"") -> 0.075384615 | Z26: =IFERROR((((1.65^2*0.5*0.5*($T26-V26))/(V26*($T26-1)))^0.5),"") -> 0.063461538 | AA26: Encuesta
A27: 200 | B27: Ciencia de Datos | C27: FACULTAD DE INGENIERÍA | D27: =VLOOKUP(B27,'Cuotas Estudiantes Pregrado'!$A$4:$N$28,13,0) -> 26 | E27: =VLOOKUP(B27,'Cuotas Estudiantes Pregrado'!$A$4:$N$28,14,0) -> 25 | F27: =VLOOKUP(B27,'BDD Estudiantes Posgrado'!$A$1:$D$200,4,0) -> 24 | G27: =VLOOKUP(B27,'Cuotas Estudiantes Pregrado'!$A$117:$M$142,13,0) -> 3 | H27: =F27/D27 -> 0.92307692 | I27: =IFERROR((((1.96^2*0.5*0.5*($D27-F27))/(F27*($D27-1)))^0.5),"") -> 0.056580326 | J27: =IFERROR((((1.65^2*0.5*0.5*($D27-F27))/(F27*($D27-1)))^0.5),"") -> 0.047631397 | K27: Encuesta | L27: =VLOOKUP($B27,'BDD Prof. Planta'!$A$1:$H$140,7,0) -> 1 | M27: 1 | N27: =VLOOKUP($B27,'BDD Prof. Planta'!$A$1:$L$140,12,0) -> 1 | O27: =M27-N27 -> 0 | P27: =N27/L27 -> 1 | Q27: 0 | R27: =IFERROR((((1.65^2*0.5*0.5*($L27-N27))/(N27*($L27-1)))^0.5),0) -> 0 | S27: Encuesta | T27: =VLOOKUP($B27,'BDD Prof. Catedra'!$A:$H,7,0) -> 4 | U27: 4 | V27: =VLOOKUP($B27,'BDD Prof. Catedra'!$A:$J,10,0) -> 4 | W27: =U27-V27 -> 0 | X27: =V27/T27 -> 1 | Y27: =IFERROR((((1.96^2*0.5*0.5*($T27-V27))/(V27*($T27-1)))^0.5),"") -> 0 | Z27: =IFERROR((((1.65^2*0.5*0.5*($T27-V27))/(V27*($T27-1)))^0.5),"") -> 0 | AA27: Encuesta
A28: 210 | B28: Centro Internacional de Lenguas y Culturas Extranjeras | C28: CENTRO INTERNACIONAL DE LENGUAS Y CULTURAS EXTRANJERAS | I28: =IFERROR((((1.96^2*0.5*0.5*($D28-F28))/(F28*($D28-1)))^0.5),"") | J28: =IFERROR((((1.65^2*0.5*0.5*($D28-F28))/(F28*($D28-1)))^0.5),"") | L28: =VLOOKUP($B28,'BDD Prof. Planta'!$A$1:$H$140,7,0) -> 22 | M28: 21 | N28: =VLOOKUP($B28,'BDD Prof. Planta'!$A$1:$L$140,12,0) -> 20 | O28: =M28-N28 -> 1 | P28: =N28/L28 -> 0.90909091 | Q28: =IFERROR((((1.96^2*0.5*0.5*($L28-N28))/(N28*($L28-1)))^0.5),"") -> 0.067626425 | R28: =IFERROR((((1.65^2*0.5*0.5*($L28-N28))/(N28*($L28-1)))^0.5),"") -> 0.056930409 | S28: Encuesta | T28: =VLOOKUP($B28,'BDD Prof. Catedra'!$A:$H,7,0) -> 25 | U28: 24 | V28: =VLOOKUP($B28,'BDD Prof. Catedra'!$A:$J,10,0) -> 22 | W28: =U28-V28 -> 2 | X28: =V28/T28 -> 0.88 | Y28: =IFERROR((((1.96^2*0.5*0.5*($T28-V28))/(V28*($T28-1)))^0.5),"") -> 0.073870279 | Z28: =IFERROR((((1.65^2*0.5*0.5*($T28-V28))/(V28*($T28-1)))^0.5),"") -> 0.062186715 | AA28: Encuesta
A29: 211 | B29: Core Curriculum Persona y Cultura | C29: CORE CURRICULUM PERSONA Y CULTURA | I29: =IFERROR((((1.96^2*0.5*0.5*($D29-F29))/(F29*($D29-1)))^0.5),"") | J29: =IFERROR((((1.65^2*0.5*0.5*($D29-F29))/(F29*($D29-1)))^0.5),"") | L29: =VLOOKUP($B29,'BDD Prof. Planta'!$A$1:$H$140,7,0) -> 11 | M29: 11 | N29: =VLOOKUP($B29,'BDD Prof. Planta'!$A$1:$L$140,12,0) -> 11 | O29: =M29-N29 -> 0 | P29: =N29/L29 -> 1 | Q29: =IFERROR((((1.96^2*0.5*0.5*($L29-N29))/(N29*($L29-1)))^0.5),"") -> 0 | R29: =IFERROR((((1.65^2*0.5*0.5*($L29-N29))/(N29*($L29-1)))^0.5),"") -> 0 | S29: Encuesta | T29: =VLOOKUP($B29,'BDD Prof. Catedra'!$A:$H,7,0) -> 10 | U29: 10 | V29: =VLOOKUP($B29,'BDD Prof. Catedra'!$A:$J,10,0) -> 8 | W29: =U29-V29 -> 2 | X29: =V29/T29 -> 0.8 | Y29: =IFERROR((((1.96^2*0.5*0.5*($T29-V29))/(V29*($T29-1)))^0.5),"") -> 0.16333333 | Z29: =IFERROR((((1.65^2*0.5*0.5*($T29-V29))/(V29*($T29-1)))^0.5),"") -> 0.1375 | AA29: Encuesta
A30: 212 | B30: Centro de Tecnología para la Academia | C30: CENTRO DE TECNOLOGÍA PARA LA ACADEMIA | J30: =IFERROR((((1.65^2*0.5*0.5*($D30-F30))/(F30*($D30-1)))^0.5),"") | L30: =VLOOKUP($B30,'BDD Prof. Planta'!$A$1:$H$140,7,0) -> 3 | M30: 3 | N30: =VLOOKUP($B30,'BDD Prof. Planta'!$A$1:$L$140,12,0) -> 2 | O30: =M30-N30 -> 1 | P30: =N30/L30 -> 0.66666667 | Q30: =IFERROR((((1.96^2*0.5*0.5*($L30-N30))/(N30*($L30-1)))^0.5),"") -> 0.49 | R30: =IFERROR((((1.65^2*0.5*0.5*($L30-N30))/(N30*($L30-1)))^0.5),"") -> 0.4125 | S30: Sondeo | T30: =VLOOKUP($B30,'BDD Prof. Catedra'!$A:$H,7,0) -> 5 | U30: 5 | V30: =VLOOKUP($B30,'BDD Prof. Catedra'!$A:$J,10,0) -> 5 | W30: =U30-V30 -> 0 | X30: =V30/T30 -> 1 | Y30: =IFERROR((((1.96^2*0.5*0.5*($T30-V30))/(V30*($T30-1)))^0.5),"") -> 0 | Z30: =IFERROR((((1.65^2*0.5*0.5*($T30-V30))/(V30*($T30-1)))^0.5),"") -> 0 | AA30: Encuesta
A31: 44 | B31: DOCTORADO EN ADMINISTRACIÓN DE ORGANIZACIONES | C31: ESCUELA INTERNACIONAL DE CIENCIAS ECONÓMICAS Y ADMINISTRATIVAS | D31: 10 | E31: 10 | F31: =VLOOKUP(B31,'BDD Estudiantes Posgrado'!$A$1:$D$200,4,0) -> 9 | G31: =E31-F31 -> 1 | H31: =F31/D31 -> 0.9 | I31: =IFERROR((((1.96^2*0.5*0.5*($D31-F31))/(F31*($D31-1)))^0.5),"") -> 0.10888889 | J31: =IFERROR((((1.65^2*0.5*0.5*($D31-F31))/(F31*($D31-1)))^0.5),"") -> 0.091666667 | K31: Encuesta | L31: =VLOOKUP($B31,'BDD Prof. Planta'!$B$29:$G$162,6,0) -> 8 | M31: 8 | N31: =VLOOKUP($B31,'BDD Prof. Planta'!$B$29:$L$162,11,0) -> 8 | O31: =M31-N31 -> 0 | P31: =N31/L31 -> 1 | Q31: =IFERROR((((1.96^2*0.5*0.5*($L31-N31))/(N31*($L31-1)))^0.5),"") -> 0 | R31: =IFERROR((((1.65^2*0.5*0.5*($L31-N31))/(N31*($L31-1)))^0.5),"") -> 0 | S31: Encuesta | Y31: =IFERROR((((1.96^2*0.5*0.5*($T31-V31))/(V31*($T31-1)))^0.5),"") | Z31: =IFERROR((((1.65^2*0.5*0.5*($T31-V31))/(V31*($T31-1)))^0.5),"")
A32: 70 | B32: DOCTORADO EN BIOCIENCIAS | C32: FACULTAD DE INGENIERÍA | D32: 22 | E32: 21 | F32: =VLOOKUP(B32,'BDD Estudiantes Posgrado'!$A$1:$D$200,4,0) -> 7 | G32: =E32-F32 -> 14 | H32: =F32/D32 -> 0.31818182 | I32: =IFERROR((((1.96^2*0.5*0.5*($D32-F32))/(F32*($D32-1)))^0.5),"") -> 0.31304952 | J32: =IFERROR((((1.65^2*0.5*0.5*($D32-F32))/(F32*($D32-1)))^0.5),"") -> 0.26353658 | K32: Sondeo | L32: =VLOOKUP($B32,'BDD Prof. Planta'!$B$29:$G$162,6,0) -> 10 | M32: 10 | N32: =VLOOKUP($B32,'BDD Prof. Planta'!$B$29:$L$162,11,0) -> 6 | O32: =M32-N32 -> 4 | P32: =N32/L32 -> 0.6 | Q32: =IFERROR((((1.96^2*0.5*0.5*($L32-N32))/(N32*($L32-1)))^0.5),"") -> 0.26672222 | R32: =IFERROR((((1.65^2*0.5*0.5*($L32-N32))/(N32*($L32-1)))^0.5),"") -> 0.22453656 | S32: Sondeo | T32: =VLOOKUP($B32,'BDD Prof. Catedra'!B:G,6,0) -> 1 | U32: 1 | V32: =VLOOKUP($B32,'BDD Prof. Catedra'!$B:$J,9,0) -> 1 | W32: =U32-V32 -> 0 | X32: =V32/T32 -> 1 | Y32: 0 | Z32: =IFERROR((((1.65^2*0.5*0.5*($T32-V32))/(V32*($T32-1)))^0.5),0) -> 0 | AA32: Encuesta
A33: 50 | B33: DOCTORADO EN COMUNICACIÓN | C33: FACULTAD DE COMUNICACIÓN | D33: 11 | E33: 11 | F33: =VLOOKUP(B33,'BDD Estudiantes Posgrado'!$A$1:$D$200,4,0) -> 6 | G33: =E33-F33 -> 5 | H33: =F33/D33 -> 0.54545455 | I33: =IFERROR((((1.96^2*0.5*0.5*($D33-F33))/(F33*($D33-1)))^0.5),"") -> 0.28290163 | J33: =IFERROR((((1.65^2*0.5*0.5*($D33-F33))/(F33*($D33-1)))^0.5),"") -> 0.23815699 | K33: Sondeo | L33: =VLOOKUP($B33,'BDD Prof. Planta'!$B$29:$G$162,6,0) -> 5 | M33: 5 | N33: =VLOOKUP($B33,'BDD Prof. Planta'!$B$29:$L$162,11,0) -> 4 | O33: =M33-N33 -> 1 | P33: =N33/L33 -> 0.8 | Q33: =IFERROR((((1.96^2*0.5*0.5*($L33-N33))/(N33*($L33-1)))^0.5),"") -> 0.245 | R33: =IFERROR((((1.65^2*0.5*0.5*($L33-N33))/(N33*($L33-1)))^0.5),"") -> 0.20625 | S33: Encuesta | Y33: =IFERROR((((1.96^2*0.5*0.5*($T33-V33))/(V33*($T33-1)))^0.5),"") | Z33: =IFERROR((((1.65^2*0.5*0.5*($T33-V33))/(V33*($T33-1)))^0.5),"")
A34: 53 | B34: DOCTORADO EN DERECHO | C34: FACULTAD DE DERECHO Y CIENCIAS POLÍTICAS | D34: 10 | E34: 9 | F34: =VLOOKUP(B34,'BDD Estudiantes Posgrado'!$A$1:$D$200,4,0) -> 3 | G34: =E34-F34 -> 6 | H34: =F34/D34 -> 0.3 | I34: =IFERROR((((1.96^2*0.5*0.5*($D34-F34))/(F34*($D34-1)))^0.5),"") -> 0.49899158 | J34: =IFERROR((((1.65^2*0.5*0.5*($D34-F34))/(F34*($D34-1)))^0.5),"") -> 0.42006944 | K34: Sondeo | L34: =VLOOKUP($B34,'BDD Prof. Planta'!$B$29:$G$162,6,0) -> 3 | M34: 3 | N34: =VLOOKUP($B34,'BDD Prof. Planta'!$B$29:$L$162,11,0) -> 3 | O34: =M34-N34 -> 0 | P34: =N34/L34 -> 1 | Q34: =IFERROR((((1.96^2*0.5*0.5*($L34-N34))/(N34*($L34-1)))^0.5),"") -> 0 | R34: =IFERROR((((1.65^2*0.5*0.5*($L34-N34))/(N34*($L34-1)))^0.5),"") -> 0 | S34: Encuesta | T34: =VLOOKUP($B34,'BDD Prof. Catedra'!B:G,6,0) -> 1 | U34: 1 | V34: =VLOOKUP($B34,'BDD Prof. Catedra'!$B:$J,9,0) -> 0 | W34: =U34-V34 -> 1 | X34: =V34/T34 -> 0 | Y34: =IFERROR((((1.96^2*0.5*0.5*($T34-V34))/(V34*($T34-1)))^0.5),"") | Z34: =IFERROR((((1.65^2*0.5*0.5*($T34-V34))/(V34*($T34-1)))^0.5),"")
A35: 58 | B35: DOCTORADO EN EDUCACIÓN | C35: FACULTAD DE EDUCACIÓN | D35: 46 | E35: 41 | F35: =VLOOKUP(B35,'BDD Estudiantes Posgrado'!$A$1:$D$200,4,0) -> 36 | G35: =E35-F35 -> 5 | H35: =F35/D35 -> 0.7826087 | I35: =IFERROR((((1.96^2*0.5*0.5*($D35-F35))/(F35*($D35-1)))^0.5),"") -> 0.076996072 | J35: =IFERROR((((1.65^2*0.5*0.5*($D35-F35))/(F35*($D35-1)))^0.5),"") -> 0.064818122 | K35: Encuesta | L35: =VLOOKUP($B35,'BDD Prof. Planta'!$B$29:$G$162,6,0) -> 6 | M35: 6 | N35: =VLOOKUP($B35,'BDD Prof. Planta'!$B$29:$L$162,11,0) -> 5 | O35: =M35-N35 -> 1 | P35: =N35/L35 -> 0.83333333 | Q35: =IFERROR((((1.96^2*0.5*0.5*($L35-N35))/(N35*($L35-1)))^0.5),"") -> 0.196 | R35: =IFERROR((((1.65^2*0.5*0.5*($L35-N35))/(N35*($L35-1)))^0.5),"") -> 0.165 | S35: Encuesta | Y35: =IFERROR((((1.96^2*0.5*0.5*($T35-V35))/(V35*($T35-1)))^0.5),"") | Z35: =IFERROR((((1.65^2*0.5*0.5*($T35-V35))/(V35*($T35-1)))^0.5),"")
A36: 66 | B36: DOCTORADO EN ENFERMERÍA | C36: FACULTAD DE ENFERMERÍA Y REHABILITACIÓN | D36: 14 | E36: 14 | F36: =VLOOKUP(B36,'BDD Estudiantes Posgrado'!$A$1:$D$200,4,0) -> 12 | G36: =E36-F36 -> 2 | H36: =F36/D36 -> 0.85714286 | I36: =IFERROR((((1.96^2*0.5*0.5*($D36-F36))/(F36*($D36-1)))^0.5),"") -> 0.11096315 | J36: =IFERROR((((1.65^2*0.5*0.5*($D36-F36))/(F36*($D36-1)))^0.5),"") -> 0.093412855 | K36: Encuesta | L36: =VLOOKUP($B36,'BDD Prof. Planta'!$B$29:$G$162,6,0) -> 4 | M36: 4 | N36: =VLOOKUP($B36,'BDD Prof. Planta'!$B$29:$L$162,11,0) -> 4 | O36: =M36-N36 -> 0 | P36: =N36/L36 -> 1 | Q36: =IFERROR((((1.96^2*0.5*0.5*($L36-N36))/(N36*($L36-1)))^0.5),"") -> 0 | R36: =IFERROR((((1.65^2*0.5*0.5*($L36-N36))/(N36*($L36-1)))^0.5),"") -> 0 | S36: Encuesta | T36: =VLOOKUP($B36,'BDD Prof. Catedra'!B:G,6,0) -> 2 | U36: 2 | V36: =VLOOKUP($B36,'BDD Prof. Catedra'!$B:$J,9,0) -> 2 | W36: =U36-V36 -> 0 | X36: =V36/T36 -> 1 | Y36: =IFERROR((((1.96^2*0.5*0.5*($T36-V36))/(V36*($T36-1)))^0.5),"") -> 0 | Z36: =IFERROR((((1.65^2*0.5*0.5*($T36-V36))/(V36*($T36-1)))^0.5),"") -> 0 | AA36: Encuesta
A37: 72 | B37: DOCTORADO EN INGENIERÍA | C37: FACULTAD DE INGENIERÍA | D37: 14 | E37: 14 | F37: =VLOOKUP(B37,'BDD Estudiantes Posgrado'!$A$1:$D$200,4,0) -> 7 | G37: =E37-F37 -> 7 | H37: =F37/D37 -> 0.5 | I37: =IFERROR((((1.96^2*0.5*0.5*($D37-F37))/(F37*($D37-1)))^0.5),"") -> 0.2718031 | J37: =IFERROR((((1.65^2*0.5*0.5*($D37-F37))/(F37*($D37-1)))^0.5),"") -> 0.22881383 | K37: Sondeo | L37: =VLOOKUP($B37,'BDD Prof. Planta'!$B$29:$G$162,6,0) -> 5 | M37: 5 | N37: =VLOOKUP($B37,'BDD Prof. Planta'!$B$29:$L$162,11,0) -> 5 | O37: =M37-N37 -> 0 | P37: =N37/L37 -> 1 | Q37: =IFERROR((((1.96^2*0.5*0.5*($L37-N37))/(N37*($L37-1)))^0.5),"") -> 0 | R37: =IFERROR((((1.65^2*0.5*0.5*($L37-N37))/(N37*($L37-1)))^0.5),"") -> 0 | S37: Encuesta | Y37: =IFERROR((((1.96^2*0.5*0.5*($T37-V37))/(V37*($T37-1)))^0.5),"") | Z37: =IFERROR((((1.65^2*0.5*0.5*($T37-V37))/(V37*($T37-1)))^0.5),"")
A38: 59 | B38: DOCTORADO EN INNOVACIÓN EDUCATIVA CON USO DE TIC | C38: FACULTAD DE EDUCACIÓN | D38: 32 | E38: 30 | F38: =VLOOKUP(B38,'BDD Estudiantes Posgrado'!$A$1:$D$200,4,0) -> 25 | G38: =E38-F38 -> 5 | H38: =F38/D38 -> 0.78125 | I38: =IFERROR((((1.96^2*0.5*0.5*($D38-F38))/(F38*($D38-1)))^0.5),"") -> 0.093137429 | J38: =IFERROR((((1.65^2*0.5*0.5*($D38-F38))/(F38*($D38-1)))^0.5),"") -> 0.078406509 | K38: Sondeo | L38: =VLOOKUP($B38,'BDD Prof. Planta'!$B$29:$G$162,6,0) -> 4 | M38: 4 | N38: =VLOOKUP($B38,'BDD Prof. Planta'!$B$29:$L$162,11,0) -> 4 | O38: =M38-N38 -> 0 | P38: =N38/L38 -> 1 | Q38: =IFERROR((((1.96^2*0.5*0.5*($L38-N38))/(N38*($L38-1)))^0.5),"") -> 0 | R38: =IFERROR((((1.65^2*0.5*0.5*($L38-N38))/(N38*($L38-1)))^0.5),"") -> 0 | S38: Encuesta | T38: =VLOOKUP($B38,'BDD Prof. Catedra'!B:G,6,0) -> 2 | U38: 2 | V38: =VLOOKUP($B38,'BDD Prof. Catedra'!$B:$J,9,0) -> 2 | W38: =U38-V38 -> 0 | X38: =V38/T38 -> 1 | Y38: =IFERROR((((1.96^2*0.5*0.5*($T38-V38))/(V38*($T38-1)))^0.5),"") -> 0 | Z38: =IFERROR((((1.65^2*0.5*0.5*($T38-V38))/(V38*($T38-1)))^0.5),"") -> 0 | AA38: Encuesta
A39: 201 | B39: DOCTORADO EN PSICOLOGÍA | C39: FACULTAD DE PSICOLOGÍA | D39: 13 | E39: 13 | F39: =VLOOKUP(B39,'BDD Estudiantes Posgrado'!$A$1:$D$200,4,0) -> 11 | G39: =E39-F39 -> 2 | H39: =F39/D39 -> 0.84615385 | I39: =IFERROR((((1.96^2*0.5*0.5*($D39-F39))/(F39*($D39-1)))^0.5),"") -> 0.12062966 | J39: =IFERROR((((1.65^2*0.5*0.5*($D39-F39))/(F39*($D39-1)))^0.5),"") -> 0.10155048 | K39: Encuesta | L39: =VLOOKUP($B39,'BDD Prof. Planta'!$B$29:$G$201,6,0) -> 10 | M39: 10 | N39: =VLOOKUP($B39,'BDD Prof. Planta'!$B$29:$L$201,11,0) -> 5 | O39: =M39-N39 -> 5 | P39: =N39/L39 -> 0.5 | Q39: =IFERROR((((1.96^2*0.5*0.5*($L39-N39))/(N39*($L39-1)))^0.5),"") -> 0.32666667 | R39: =IFERROR((((1.65^2*0.5*0.5*($L39-N39))/(N39*($L39-1)))^0.5),"") -> 0.275 | S39: Sondeo | T39: =VLOOKUP($B39,'BDD Prof. Catedra'!B:G,6,0) -> 4 | U39: 4 | V39: =VLOOKUP($B39,'BDD Prof. Catedra'!$B:$J,9,0) -> 1 | W39: =U39-V39 -> 3 | X39: =V39/T39 -> 0.25 | Y39: =IFERROR((((1.96^2*0.5*0.5*($T39-V39))/(V39*($T39-1)))^0.5),"") -> 0.98 | Z39: =IFERROR((((1.65^2*0.5*0.5*($T39-V39))/(V39*($T39-1)))^0.5),"") -> 0.825 | AA39: Sondeo
A40: 71 | B40: DOCTORADO EN LOGÍSTICA Y GESTIÓN DE CADENA DE SUMINISTRO | C40: FACULTAD DE INGENIERÍA | D40: 14 | E40: 14 | F40: =VLOOKUP(B40,'BDD Estudiantes Posgrado'!$A$1:$D$200,4,0) -> 13 | G40: =E40-F40 -> 1 | H40: =F40/D40 -> 0.92857143 | I40: =IFERROR((((1.96^2*0.5*0.5*($D40-F40))/(F40*($D40-1)))^0.5),"") -> 0.075384615 | J40: =IFERROR((((1.65^2*0.5*0.5*($D40-F40))/(F40*($D40-1)))^0.5),"") -> 0.063461538 | K40: Encuesta | L40: =VLOOKUP($B40,'BDD Prof. Planta'!$B$29:$G$162,6,0) -> 2 | M40: 2 | N40: =VLOOKUP($B40,'BDD Prof. Planta'!$B$29:$L$162,11,0) -> 2 | O40: =M40-N40 -> 0 | P40: =N40/L40 -> 1 | Q40: =IFERROR((((1.96^2*0.5*0.5*($L40-N40))/(N40*($L40-1)))^0.5),"") -> 0 | R40: =IFERROR((((1.65^2*0.5*0.5*($L40-N40))/(N40*($L40-1)))^0.5),"") -> 0 | S40: Encuesta | Y40: =IFERROR((((1.96^2*0.5*0.5*($T40-V40))/(V40*($T40-1)))^0.5),"") | Z40: =IFERROR((((1.65^2*0.5*0.5*($T40-V40))/(V40*($T40-1)))^0.5),"")
A41: 1 | B41: ESPECIALIZACIÓN EN ANESTESIOLOGÍA Y MEDICINA PERIOPERATORIA | C41: FACULTAD DE MEDICINA | D41: 18 | E41: 17 | F41: =VLOOKUP(B41,'BDD Estudiantes Posgrado'!$A$1:$D$200,4,0) -> 7 | G41: =E41-F41 -> 10 | H41: =F41/D41 -> 0.38888889 | I41: =IFERROR((((1.96^2*0.5*0.5*($D41-F41))/(F41*($D41-1)))^0.5),"") -> 0.29795381 | J41: =IFERROR((((1.65^2*0.5*0.5*($D41-F41))/(F41*($D41-1)))^0.5),"") -> 0.25082846 | K41: Sondeo | L41: =VLOOKUP($B41,'BDD Prof. Planta'!$B$29:$G$162,6,0) -> 1 | M41: 1 | N41: =VLOOKUP($B41,'BDD Prof. Planta'!$B$29:$L$162,11,0) -> 1 | O41: =M41-N41 -> 0 | P41: =N41/L41 -> 1 | Q41: 0 | R41: =IFERROR((((1.65^2*0.5*0.5*($L41-N41))/(N41*($L41-1)))^0.5),0) -> 0 | S41: Encuesta | Y41: =IFERROR((((1.96^2*0.5*0.5*($T41-V41))/(V41*($T41-1)))^0.5),"") | Z41: =IFERROR((((1.65^2*0.5*0.5*($T41-V41))/(V41*($T41-1)))^0.5),"")
A42: 2 | B42: ESPECIALIZACIÓN EN CIRUGÍA GENERAL | C42: FACULTAD DE MEDICINA | D42: 24 | E42: 23 | F42: =VLOOKUP(B42,'BDD Estudiantes Posgrado'!$A$1:$D$200,4,0) -> 23 | G42: =E42-F42 -> 0 | H42: =F42/D42 -> 0.95833333 | I42: =IFERROR((((1.96^2*0.5*0.5*($D42-F42))/(F42*($D42-1)))^0.5),"") -> 0.042608696 | J42: =IFERROR((((1.65^2*0.5*0.5*($D42-F42))/(F42*($D42-1)))^0.5),"") -> 0.035869565 | K42: Encuesta | L42: =VLOOKUP($B42,'BDD Prof. Planta'!$B$29:$G$162,6,0) -> 3 | M42: 3 | N42: =VLOOKUP($B42,'BDD Prof. Planta'!$B$29:$L$162,11,0) -> 3 | O42: =M42-N42 -> 0 | P42: =N42/L42 -> 1 | Q42: =IFERROR((((1.96^2*0.5*0.5*($L42-N42))/(N42*($L42-1)))^0.5),"") -> 0 | R42: =IFERROR((((1.65^2*0.5*0.5*($L42-N42))/(N42*($L42-1)))^0.5),"") -> 0 | S42: Encuesta | T42: =VLOOKUP($B42,'BDD Prof. Catedra'!B:G,6,0) -> 3 | U42: 3 | V42: =VLOOKUP($B42,'BDD Prof. Catedra'!$B:$J,9,0) -> 2 | W42: =U42-V42 -> 1 | X42: =V42/T42 -> 0.66666667 | Y42: =IFERROR((((1.96^2*0.5*0.5*($T42-V42))/(V42*($T42-1)))^0.5),"") -> 0.49 | Z42: =IFERROR((((1.65^2*0.5*0.5*($T42-V42))/(V42*($T42-1)))^0.5),"") -> 0.4125 | AA42: Sondeo
A43: 3 | B43: ESPECIALIZACIÓN EN CUIDADO INTENSIVO PEDIÁTRICO | C43: FACULTAD DE MEDICINA | D43: 5 | E43: 5 | F43: =VLOOKUP(B43,'BDD Estudiantes Posgrado'!$A$1:$D$200,4,0) -> 4 | G43: =E43-F43 -> 1 | H43: =F43/D43 -> 0.8 | I43: =IFERROR((((1.96^2*0.5*0.5*($D43-F43))/(F43*($D43-1)))^0.5),"") -> 0.245 | J43: =IFERROR((((1.65^2*0.5*0.5*($D43-F43))/(F43*($D43-1)))^0.5),"") -> 0.20625 | K43: Encuesta | L43: =VLOOKUP($B43,'BDD Prof. Planta'!$B$29:$G$162,6,0) -> 1 | M43: 1 | N43: =VLOOKUP($B43,'BDD Prof. Planta'!$B$29:$L$162,11,0) -> 1 | O43: =M43-N43 -> 0 | P43: =N43/L43 -> 1 | Q43: 0 | R43: =IFERROR((((1.65^2*0.5*0.5*($L43-N43))/(N43*($L43-1)))^0.5),0) -> 0 | S43: Encuesta | T43: =VLOOKUP($B43,'BDD Prof. Catedra'!B:G,6,0) -> 1 | U43: 1 | V43: =VLOOKUP($B43,'BDD Prof. Catedra'!$B:$J,9,0) -> 1 | W43: =U43-V43 -> 0 | X43: =V43/T43 -> 1 | Y43: 0 | Z43: =IFERROR((((1.65^2*0.5*0.5*($T43-V43))/(V43*($T43-1)))^0.5),0) -> 0 | AA43: Encuesta
A44: 106 | B44: ESPECIALIZACIÓN EN BIOÉTICA - CHÍA | C44: FACULTAD DE MEDICINA | D44: 5 | E44: 5 | F44: =VLOOKUP(B44,'BDD Estudiantes Posgrado'!$A$1:$D$200,4,0) -> 5 | G44: =E44-F44 -> 0 | H44: =F44/D44 -> 1 | I44: =IFERROR((((1.96^2*0.5*0.5*($D44-F44))/(F44*($D44-1)))^0.5),"") -> 0 | J44: =IFERROR((((1.65^2*0.5*0.5*($D44-F44))/(F44*($D44-1)))^0.5),"") -> 0 | K44: Encuesta | L44: =VLOOKUP($B44,'BDD Prof. Planta'!$B$29:$G$162,6,0) -> 3 | M44: 3 | N44: =VLOOKUP($B44,'BDD Prof. Planta'!$B$29:$L$162,11,0) -> 2 | O44: =M44-N44 -> 1 | P44: =N44/L44 -> 0.66666667 | Q44: =IFERROR((((1.96^2*0.5*0.5*($L44-N44))/(N44*($L44-1)))^0.5),"") -> 0.49 | R44: =IFERROR((((1.65^2*0.5*0.5*($L44-N44))/(N44*($L44-1)))^0.5),"") -> 0.4125 | S44: Sondeo | Z44: =IFERROR((((1.65^2*0.5*0.5*($T44-V44))/(V44*($T44-1)))^0.5),"")
A45: 4 | B45: ESPECIALIZACIÓN EN ELECTROFISIOLOGÍA CARDIOVASCULAR | C45: FACULTAD DE MEDICINA | D45: 3 | E45: 3 | F45: =VLOOKUP(B45,'BDD Estudiantes Posgrado'!$A$1:$D$200,4,0) -> 1 | G45: =E45-F45 -> 2 | H45: =F45/D45 -> 0.33333333 | I45: =IFERROR((((1.96^2*0.5*0.5*($D45-F45))/(F45*($D45-1)))^0.5),"") -> 0.98 | J45: =IFERROR((((1.65^2*0.5*0.5*($D45-F45))/(F45*($D45-1)))^0.5),"") -> 0.825 | K45: Sondeo | Q45: =IFERROR((((1.96^2*0.5*0.5*($L45-N45))/(N45*($L45-1)))^0.5),"") | R45: =IFERROR((((1.65^2*0.5*0.5*($L45-N45))/(N45*($L45-1)))^0.5),"") | T45: =VLOOKUP($B45,'BDD Prof. Catedra'!B:G,6,0) -> 1 | U45: 1 | V45: =VLOOKUP($B45,'BDD Prof. Catedra'!$B:$J,9,0) -> 0 | W45: =U45-V45 -> 1 | X45: =V45/T45 -> 0 | Y45: =IFERROR((((1.96^2*0.5*0.5*($T45-V45))/(V45*($T45-1)))^0.5),"") | Z45: =IFERROR((((1.65^2*0.5*0.5*($T45-V45))/(V45*($T45-1)))^0.5),"")
A46: 5 | B46: ESPECIALIZACIÓN EN FARMACOLOGÍA CLÍNICA | C46: FACULTAD DE MEDICINA | D46: 12 | E46: 12 | F46: =VLOOKUP(B46,'BDD Estudiantes Posgrado'!$A$1:$D$200,4,0) -> 10 | G46: =E46-F46 -> 2 | H46: =F46/D46 -> 0.83333333 | I46: =IFERROR((((1.96^2*0.5*0.5*($D46-F46))/(F46*($D46-1)))^0.5),"") -> 0.13214317 | J46: =IFERROR((((1.65^2*0.5*0.5*($D46-F46))/(F46*($D46-1)))^0.5),"") -> 0.11124298 | K46: Encuesta | L46: =VLOOKUP($B46,'BDD Prof. Planta'!$B$29:$G$162,6,0) -> 3 | M46: 3 | N46: =VLOOKUP($B46,'BDD Prof. Planta'!$B$29:$L$162,11,0) -> 2 | O46: =M46-N46 -> 1 | P46: =N46/L46 -> 0.66666667 | Q46: =IFERROR((((1.96^2*0.5*0.5*($L46-N46))/(N46*($L46-1)))^0.5),"") -> 0.49 | R46: =IFERROR((((1.65^2*0.5*0.5*($L46-N46))/(N46*($L46-1)))^0.5),"") -> 0.4125 | S46: Sondeo | T46: =VLOOKUP($B46,'BDD Prof. Catedra'!B:G,6,0) -> 4 | U46: 4 | V46: =VLOOKUP($B46,'BDD Prof. Catedra'!$B:$J,9,0) -> 2 | W46: =U46-V46 -> 2 | X46: =V46/T46 -> 0.5 | Y46: =IFERROR((((1.96^2*0.5*0.5*($T46-V46))/(V46*($T46-1)))^0.5),"") -> 0.56580326 | Z46: =IFERROR((((1.65^2*0.5*0.5*($T46-V46))/(V46*($T46-1)))^0.5),"") -> 0.47631397 | AA46: Sondeo
A47: 6 | B47: ESPECIALIZACIÓN EN GINECOLOGÍA Y OBSTETRICIA | C47: FACULTAD DE MEDICINA | D47: 14 | E47: 14 | F47: =VLOOKUP(B47,'BDD Estudiantes Posgrado'!$A$1:$D$200,4,0) -> 10 | G47: =E47-F47 -> 4 | H47: =F47/D47 -> 0.71428571 | I47: =IFERROR((((1.96^2*0.5*0.5*($D47-F47))/(F47*($D47-1)))^0.5),"") -> 0.17190337 | J47: =IFERROR((((1.65^2*0.5*0.5*($D47-F47))/(F47*($D47-1)))^0.5),"") -> 0.14471457 | K47: Sondeo | L47: =VLOOKUP($B47,'BDD Prof. Planta'!$B$29:$G$162,6,0) -> 1 | M47: 1 | N47: =VLOOKUP($B47,'BDD Prof. Planta'!$B$29:$L$162,11,0) -> 1 | O47: =M47-N47 -> 0 | P47: =N47/L47 -> 1 | Q47: 0 | R47: =IFERROR((((1.65^2*0.5*0.5*($L47-N47))/(N47*($L47-1)))^0.5),0) -> 0 | S47: Encuesta | Y47: =IFERROR((((1.96^2*0.5*0.5*($T47-V47))/(V47*($T47-1)))^0.5),"") | Z47: =IFERROR((((1.65^2*0.5*0.5*($T47-V47))/(V47*($T47-1)))^0.5),"")
A48: 17 | B48: ESPECIALIZACIÓN EN GASTROENTEROLOGÍA | C48: FACULTAD DE MEDICINA | D48: 4 | E48: 4 | F48: =VLOOKUP(B48,'BDD Estudiantes Posgrado'!$A$1:$D$200,4,0) -> 3 | G48: =E48-F48 -> 1 | H48: =F48/D48 -> 0.75 | I48: =IFERROR((((1.96^2*0.5*0.5*($D48-F48))/(F48*($D48-1)))^0.5),"") -> 0.32666667 | J48: =IFERROR((((1.65^2*0.5*0.5*($D48-F48))/(F48*($D48-1)))^0.5),"") -> 0.275 | K48: Sondeo | Q48: =IFERROR((((1.96^2*0.5*0.5*($L48-N48))/(N48*($L48-1)))^0.5),"") | R48: =IFERROR((((1.65^2*0.5*0.5*($L48-N48))/(N48*($L48-1)))^0.5),"") | T48: =VLOOKUP($B48,'BDD Prof. Catedra'!B:G,6,0) -> 1 | U48: 1 | V48: =VLOOKUP($B48,'BDD Prof. Catedra'!$B:$J,9,0) -> 0 | W48: =U48-V48 -> 1 | X48: =V48/T48 -> 0 | Y48: =IFERROR((((1.96^2*0.5*0.5*($T48-V48))/(V48*($T48-1)))^0.5),"") | Z48: =IFERROR((((1.65^2*0.5*0.5*($T48-V48))/(V48*($T48-1)))^0.5),"")
A49: 7 | B49: ESPECIALIZACIÓN EN MEDICINA CRÍTICA | C49: FACULTAD DE MEDICINA | D49: 33 | E49: 30 | F49: =VLOOKUP(B49,'BDD Estudiantes Posgrado'!$A$1:$D$200,4,0) -> 10 | G49: =E49-F49 -> 20 | H49: =F49/D49 -> 0.3030303 | I49: =IFERROR((((1.96^2*0.5*0.5*($D49-F49))/(F49*($D49-1)))^0.5),"") -> 0.26273323 | J49: =IFERROR((((1.65^2*0.5*0.5*($D49-F49))/(F49*($D49-1)))^0.5),"") -> 0.22117848 | K49: Sondeo | Q49: =IFERROR((((1.96^2*0.5*0.5*($L49-N49))/(N49*($L49-1)))^0.5),"") | R49: =IFERROR((((1.65^2*0.5*0.5*($L49-N49))/(N49*($L49-1)))^0.5),"") | T49: =VLOOKUP($B49,'BDD Prof. Catedra'!B:G,6,0) -> 1 | U49: 1 | V49: =VLOOKUP($B49,'BDD Prof. Catedra'!$B:$J,9,0) -> 0 | W49: =U49-V49 -> 1 | X49: =V49/T49 -> 0 | Y49: =IFERROR((((1.96^2*0.5*0.5*($T49-V49))/(V49*($T49-1)))^0.5),"") | Z49: =IFERROR((((1.65^2*0.5*0.5*($T49-V49))/(V49*($T49-1)))^0.5),"")
A50: 18 | B50: ESPECIALIZACIÓN EN MEDICINA DEL DOLOR Y CUIDADOS PALIATIVOS | C50: FACULTAD DE MEDICINA | D50: 19 | E50: 18 | F50: =VLOOKUP(B50,'BDD Estudiantes Posgrado'!$A$1:$D$200,4,0) -> 13 | G50: =E50-F50 -> 5 | H50: =F50/D50 -> 0.68421053 | I50: =IFERROR((((1.96^2*0.5*0.5*($D50-F50))/(F50*($D50-1)))^0.5),"") -> 0.15692559 | J50: =IFERROR((((1.65^2*0.5*0.5*($D50-F50))/(F50*($D50-1)))^0.5),"") -> 0.13210573 | K50: Sondeo | L50: =VLOOKUP($B50,'BDD Prof. Planta'!$B$29:$G$162,6,0) -> 2 | M50: 2 | N50: =VLOOKUP($B50,'BDD Prof. Planta'!$B$29:$L$162,11,0) -> 2 | O50: =M50-N50 -> 0 | P50: =N50/L50 -> 1 | Q50: =IFERROR((((1.96^2*0.5*0.5*($L50-N50))/(N50*($L50-1)))^0.5),"") -> 0 | R50: =IFERROR((((1.65^2*0.5*0.5*($L50-N50))/(N50*($L50-1)))^0.5),"") -> 0 | S50: Encuesta | T50: =VLOOKUP($B50,'BDD Prof. Catedra'!B:G,6,0) -> 1 | U50: 1 | V50: =VLOOKUP($B50,'BDD Prof. Catedra'!$B:$J,9,0) -> 1 | W50: =U50-V50 -> 0 | X50: =V50/T50 -> 1 | Y50: 0 | Z50: =IFERROR((((1.65^2*0.5*0.5*($T50-V50))/(V50*($T50-1)))^0.5),0) -> 0 | AA50: Encuesta
A51: 8 | B51: ESPECIALIZACIÓN EN MEDICINA FAMILIAR Y COMUNITARIA | C51: FACULTAD DE MEDICINA | D51: 31 | E51: 29 | F51: =VLOOKUP(B51,'BDD Estudiantes Posgrado'!$A$1:$D$200,4,0) -> 20 | G51: =E51-F51 -> 9 | H51: =F51/D51 -> 0.64516129 | I51: =IFERROR((((1.96^2*0.5*0.5*($D51-F51))/(F51*($D51-1)))^0.5),"") -> 0.13269263 | J51: =IFERROR((((1.65^2*0.5*0.5*($D51-F51))/(F51*($D51-1)))^0.5),"") -> 0.11170553 | K51: Sondeo | L51: =VLOOKUP($B51,'BDD Prof. Planta'!$B$29:$G$162,6,0) -> 4 | M51: 4 | N51: =VLOOKUP($B51,'BDD Prof. Planta'!$B$29:$L$162,11,0) -> 4 | O51: =M51-N51 -> 0 | P51: =N51/L51 -> 1 | Q51: =IFERROR((((1.96^2*0.5*0.5*($L51-N51))/(N51*($L51-1)))^0.5),"") -> 0 | R51: =IFERROR((((1.65^2*0.5*0.5*($L51-N51))/(N51*($L51-1)))^0.5),"") -> 0 | S51: Encuesta | T51: =VLOOKUP($B51,'BDD Prof. Catedra'!B:G,6,0) -> 10 | U51: 10 | V51: =VLOOKUP($B51,'BDD Prof. Catedra'!$B:$J,9,0) -> 3 | W51: =U51-V51 -> 7 | X51: =V51/T51 -> 0.3 | Y51: =IFERROR((((1.96^2*0.5*0.5*($T51-V51))/(V51*($T51-1)))^0.5),"") -> 0.49899158 | Z51: =IFERROR((((1.65^2*0.5*0.5*($T51-V51))/(V51*($T51-1)))^0.5),"") -> 0.42006944 | AA51: Sondeo
A52: 9 | B52: ESPECIALIZACIÓN EN MEDICINA FÍSICA Y REHABILITACIÓN | C52: FACULTAD DE MEDICINA | D52: 12 | E52: 12 | F52: =VLOOKUP(B52,'BDD Estudiantes Posgrado'!$A$1:$D$200,4,0) -> 12 | G52: =E52-F52 -> 0 | H52: =F52/D52 -> 1 | I52: =IFERROR((((1.96^2*0.5*0.5*($D52-F52))/(F52*($D52-1)))^0.5),"") -> 0 | J52: =IFERROR((((1.65^2*0.5*0.5*($D52-F52))/(F52*($D52-1)))^0.5),"") -> 0 | K52: Encuesta | Q52: =IFERROR((((1.96^2*0.5*0.5*($L52-N52))/(N52*($L52-1)))^0.5),"") | R52: =IFERROR((((1.65^2*0.5*0.5*($L52-N52))/(N52*($L52-1)))^0.5),"") | T52: =VLOOKUP($B52,'BDD Prof. Catedra'!B:G,6,0) -> 1 | U52: 1 | V52: =VLOOKUP($B52,'BDD Prof. Catedra'!$B:$J,9,0) -> 1 | W52: =U52-V52 -> 0 | X52: =V52/T52 -> 1 | Y52: 0 | Z52: =IFERROR((((1.65^2*0.5*0.5*($T52-V52))/(V52*($T52-1)))^0.5),0) -> 0 | AA52: Encuesta
A53: 10 | B53: ESPECIALIZACIÓN EN MEDICINA INTERNA | C53: FACULTAD DE MEDICINA | D53: 35 | E53: 32 | F53: =VLOOKUP(B53,'BDD Estudiantes Posgrado'!$A$1:$D$200,4,0) -> 17 | G53: =E53-F53 -> 15 | H53: =F53/D53 -> 0.48571429 | I53: =IFERROR((((1.96^2*0.5*0.5*($D53-F53))/(F53*($D53-1)))^0.5),"") -> 0.17294118 | J53: =IFERROR((((1.65^2*0.5*0.5*($D53-F53))/(F53*($D53-1)))^0.5),"") -> 0.14558824 | K53: Sondeo | L53: =VLOOKUP($B53,'BDD Prof. Planta'!$B$29:$G$162,6,0) -> 2 | M53: 2 | N53: =VLOOKUP($B53,'BDD Prof. Planta'!$B$29:$L$162,11,0) -> 2 | O53: =M53-N53 -> 0 | P53: =N53/L53 -> 1 | Q53: =IFERROR((((1.96^2*0.5*0.5*($L53-N53))/(N53*($L53-1)))^0.5),"") -> 0 | R53: =IFERROR((((1.65^2*0.5*0.5*($L53-N53))/(N53*($L53-1)))^0.5),"") -> 0 | S53: Encuesta | Y53: =IFERROR((((1.96^2*0.5*0.5*($T53-V53))/(V53*($T53-1)))^0.5),"") | Z53: =IFERROR((((1.65^2*0.5*0.5*($T53-V53))/(V53*($T53-1)))^0.5),"")
A54: 11 | B54: ESPECIALIZACIÓN EN NEUMOLOGÍA | C54: FACULTAD DE MEDICINA | D54: 8 | E54: 8 | F54: =VLOOKUP(B54,'BDD Estudiantes Posgrado'!$A$1:$D$200,4,0) -> 8 | G54: =E54-F54 -> 0 | H54: =F54/D54 -> 1 | I54: =IFERROR((((1.96^2*0.5*0.5*($D54-F54))/(F54*($D54-1)))^0.5),"") -> 0 | J54: =IFERROR((((1.65^2*0.5*0.5*($D54-F54))/(F54*($D54-1)))^0.5),"") -> 0 | K54: Encuesta | L54: =VLOOKUP($B54,'BDD Prof. Planta'!$B$29:$G$162,6,0) -> 1 | M54: 1 | N54: =VLOOKUP($B54,'BDD Prof. Planta'!$B$29:$L$162,11,0) -> 1 | O54: =M54-N54 -> 0 | P54: =N54/L54 -> 1 | Q54: 0 | R54: =IFERROR((((1.65^2*0.5*0.5*($L54-N54))/(N54*($L54-1)))^0.5),0) -> 0 | S54: Encuesta | T54: =VLOOKUP($B54,'BDD Prof. Catedra'!B:G,6,0) -> 2 | U54: 2 | V54: =VLOOKUP($B54,'BDD Prof. Catedra'!$B:$J,9,0) -> 2 | W54: =U54-V54 -> 0 | X54: =V54/T54 -> 1 | Y54: =IFERROR((((1.96^2*0.5*0.5*($T54-V54))/(V54*($T54-1)))^0.5),"") -> 0 | Z54: =IFERROR((((1.65^2*0.5*0.5*($T54-V54))/(V54*($T54-1)))^0.5),"") -> 0 | AA54: Encuesta
A55: 19 | B55: ESPECIALIZACIÓN EN NEUMOLOGÍA PEDIÁTRICA | C55: FACULTAD DE MEDICINA | D55: 6 | E55: 6 | F55: =VLOOKUP(B55,'BDD Estudiantes Posgrado'!$A$1:$D$200,4,0) -> 3 | G55: =E55-F55 -> 3 | H55: =F55/D55 -> 0.5 | I55: =IFERROR((((1.96^2*0.5*0.5*($D55-F55))/(F55*($D55-1)))^0.5),"") -> 0.43826932 | J55: =IFERROR((((1.65^2*0.5*0.5*($D55-F55))/(F55*($D55-1)))^0.5),"") -> 0.36895122 | K55: Sondeo | Q55: =IFERROR((((1.96^2*0.5*0.5*($L55-N55))/(N55*($L55-1)))^0.5),"") | R55: =IFERROR((((1.65^2*0.5*0.5*($L55-N55))/(N55*($L55-1)))^0.5),"") | T55: =VLOOKUP($B55,'BDD Prof. Catedra'!B:G,6,0) -> 1 | U55: 1 | V55: =VLOOKUP($B55,'BDD Prof. Catedra'!$B:$J,9,0) -> 0 | W55: =U55-V55 -> 1 | X55: =V55/T55 -> 0 | Y55: =IFERROR((((1.96^2*0.5*0.5*($T55-V55))/(V55*($T55-1)))^0.5),"") | Z55: =IFERROR((((1.65^2*0.5*0.5*($T55-V55))/(V55*($T55-1)))^0.5),"")
A56: 12 | B56: ESPECIALIZACIÓN EN NEUROLOGÍA | C56: FACULTAD DE MEDICINA | D56: 21 | E56: 20 | F56: =VLOOKUP(B56,'BDD Estudiantes Posgrado'!$A$1:$D$200,4,0) -> 15 | G56: =E56-F56 -> 5 | H56: =F56/D56 -> 0.71428571 | I56: =IFERROR((((1.96^2*0.5*0.5*($D56-F56))/(F56*($D56-1)))^0.5),"") -> 0.13859293 | J56: =IFERROR((((1.65^2*0.5*0.5*($D56-F56))/(F56*($D56-1)))^0.5),"") -> 0.11667262 | K56: Sondeo | Q56: =IFERROR((((1.96^2*0.5*0.5*($L56-N56))/(N56*($L56-1)))^0.5),"") | R56: =IFERROR((((1.65^2*0.5*0.5*($L56-N56))/(N56*($L56-1)))^0.5),"") | T56: =VLOOKUP($B56,'BDD Prof. Catedra'!B:G,6,0) -> 2 | U56: 2 | V56: =VLOOKUP($B56,'BDD Prof. Catedra'!$B:$J,9,0) -> 0 | W56: =U56-V56 -> 2 | X56: =V56/T56 -> 0 | Y56: =IFERROR((((1.96^2*0.5*0.5*($T56-V56))/(V56*($T56-1)))^0.5),"") | Z56: =IFERROR((((1.65^2*0.5*0.5*($T56-V56))/(V56*($T56-1)))^0.5),"")
A57: 13 | B57: ESPECIALIZACIÓN EN OFTALMOLOGÍA | C57: FACULTAD DE MEDICINA | D57: 6 | E57: 6 | F57: =VLOOKUP(B57,'BDD Estudiantes Posgrado'!$A$1:$D$200,4,0) -> 6 | G57: =E57-F57 -> 0 | H57: =F57/D57 -> 1 | I57: =IFERROR((((1.96^2*0.5*0.5*($D57-F57))/(F57*($D57-1)))^0.5),"") -> 0 | J57: =IFERROR((((1.65^2*0.5*0.5*($D57-F57))/(F57*($D57-1)))^0.5),"") -> 0 | K57: Encuesta | Q57: =IFERROR((((1.96^2*0.5*0.5*($L57-N57))/(N57*($L57-1)))^0.5),"") | R57: =IFERROR((((1.65^2*0.5*0.5*($L57-N57))/(N57*($L57-1)))^0.5),"") | T57: =VLOOKUP($B57,'BDD Prof. Catedra'!B:G,6,0) -> 1 | U57: 1 | V57: =VLOOKUP($B57,'BDD Prof. Catedra'!$B:$J,9,0) -> 0 | W57: =U57-V57 -> 1 | X57: =V57/T57 -> 0 | Y57: =IFERROR((((1.96^2*0.5*0.5*($T57-V57))/(V57*($T57-1)))^0.5),"") | Z57: =IFERROR((((1.65^2*0.5*0.5*($T57-V57))/(V57*($T57-1)))^0.5),"")
A58: 14 | B58: ESPECIALIZACIÓN EN PEDIATRÍA | C58: FACULTAD DE MEDICINA | D58: 17 | E58: 16 | F58: =VLOOKUP(B58,'BDD Estudiantes Posgrado'!$A$1:$D$200,4,0) -> 16 | G58: =E58-F58 -> 0 | H58: =F58/D58 -> 0.94117647 | I58: =IFERROR((((1.96^2*0.5*0.5*($D58-F58))/(F58*($D58-1)))^0.5),"") -> 0.06125 | J58: =IFERROR((((1.65^2*0.5*0.5*($D58-F58))/(F58*($D58-1)))^0.5),"") -> 0.0515625 | K58: Encuesta | L58: =VLOOKUP($B58,'BDD Prof. Planta'!$B$29:$G$162,6,0) -> 3 | M58: 3 | N58: =VLOOKUP($B58,'BDD Prof. Planta'!$B$29:$L$162,11,0) -> 2 | O58: =M58-N58 -> 1 | P58: =N58/L58 -> 0.66666667 | Q58: =IFERROR((((1.96^2*0.5*0.5*($L58-N58))/(N58*($L58-1)))^0.5),"") -> 0.49 | R58: =IFERROR((((1.65^2*0.5*0.5*($L58-N58))/(N58*($L58-1)))^0.5),"") -> 0.4125 | S58: Sondeo | T58: =VLOOKUP($B58,'BDD Prof. Catedra'!B:G,6,0) -> 2 | U58: 2 | V58: =VLOOKUP($B58,'BDD Prof. Catedra'!$B:$J,9,0) -> 1 | W58: =U58-V58 -> 1 | X58: =V58/T58 -> 0.5 | Y58: =IFERROR((((1.96^2*0.5*0.5*($T58-V58))/(V58*($T58-1)))^0.5),"") -> 0.98 | Z58: =IFERROR((((1.65^2*0.5*0.5*($T58-V58))/(V58*($T58-1)))^0.5),"") -> 0.825 | AA58: Sondeo
A59: 15 | B59: ESPECIALIZACIÓN EN RADIOLOGÍA E IMÁGENES DIAGNÓSTICAS | C59: FACULTAD DE MEDICINA | D59: 14 | E59: 14 | F59: =VLOOKUP(B59,'BDD Estudiantes Posgrado'!$A$1:$D$200,4,0) -> 4 | G59: =E59-F59 -> 10 | H59: =F59/D59 -> 0.28571429 | I59: =IFERROR((((1.96^2*0.5*0.5*($D59-F59))/(F59*($D59-1)))^0.5),"") -> 0.42975843 | J59: =IFERROR((((1.65^2*0.5*0.5*($D59-F59))/(F59*($D59-1)))^0.5),"") -> 0.36178643 | K59: Sondeo | Q59: =IFERROR((((1.96^2*0.5*0.5*($L59-N59))/(N59*($L59-1)))^0.5),"") | R59: =IFERROR((((1.65^2*0.5*0.5*($L59-N59))/(N59*($L59-1)))^0.5),"") | T59: =VLOOKUP($B59,'BDD Prof. Catedra'!B:G,6,0) -> 1 | U59: 1 | V59: =VLOOKUP($B59,'BDD Prof. Catedra'!$B:$J,9,0) -> 0 | W59: =U59-V59 -> 1 | X59: =V59/T59 -> 0 | Y59: =IFERROR((((1.96^2*0.5*0.5*($T59-V59))/(V59*($T59-1)))^0.5),"") | Z59: =IFERROR((((1.65^2*0.5*0.5*($T59-V59))/(V59*($T59-1)))^0.5),"")
A60: 16 | B60: ESPECIALIZACIÓN EN REUMATOLOGÍA | C60: FACULTAD DE MEDICINA | D60: 4 | E60: 4 | F60: =VLOOKUP(B60,'BDD Estudiantes Posgrado'!$A$1:$D$200,4,0) -> 1 | G60: =E60-F60 -> 3 | H60: =F60/D60 -> 0.25 | I60: =IFERROR((((1.96^2*0.5*0.5*($D60-F60))/(F60*($D60-1)))^0.5),"") -> 0.98 | J60: =IFERROR((((1.65^2*0.5*0.5*($D60-F60))/(F60*($D60-1)))^0.5),"") -> 0.825 | K60: Sondeo | L60: =VLOOKUP($B60,'BDD Prof. Planta'!$B$29:$G$162,6,0) -> 2 | M60: 2 | N60: =VLOOKUP($B60,'BDD Prof. Planta'!$B$29:$L$162,11,0) -> 2 | O60: =M60-N60 -> 0 | P60: =N60/L60 -> 1 | Q60: =IFERROR((((1.96^2*0.5*0.5*($L60-N60))/(N60*($L60-1)))^0.5),"") -> 0 | R60: =IFERROR((((1.65^2*0.5*0.5*($L60-N60))/(N60*($L60-1)))^0.5),"") -> 0 | S60: Encuesta | Y60: =IFERROR((((1.96^2*0.5*0.5*($T60-V60))/(V60*($T60-1)))^0.5),"") | Z60: =IFERROR((((1.65^2*0.5*0.5*($T60-V60))/(V60*($T60-1)))^0.5),"")
A61: 97 | B61: ESPECIALIZACIÓN EN CONTRATACIÓN ESTATAL | C61: FACULTAD DE DERECHO Y CIENCIAS POLÍTICAS | D61: 39 | E61: 20 | F61: =VLOOKUP(B61,'BDD Estudiantes Posgrado'!$A$1:$D$200,4,0) -> 5 | G61: =E61-F61 -> 15 | H61: =F61/D61 -> 0.12820513 | I61: =IFERROR((((1.96^2*0.5*0.5*($D61-F61))/(F61*($D61-1)))^0.5),"") -> 0.41456128 | J61: =IFERROR((((1.65^2*0.5*0.5*($D61-F61))/(F61*($D61-1)))^0.5),"") -> 0.34899291 | K61: Sondeo | L61: =VLOOKUP($B61,'BDD Prof. Planta'!$B$29:$G$162,6,0) -> 2 | M61: 2 | N61: =VLOOKUP($B61,'BDD Prof. Planta'!$B$29:$L$162,11,0) -> 1 | O61: =M61-N61 -> 1 | P61: =N61/L61 -> 0.5 | Q61: =IFERROR((((1.96^2*0.5*0.5*($L61-N61))/(N61*($L61-1)))^0.5),"") -> 0.98 | R61: =IFERROR((((1.65^2*0.5*0.5*($L61-N61))/(N61*($L61-1)))^0.5),"") -> 0.825 | S61: Sondeo | T61: =VLOOKUP($B61,'BDD Prof. Catedra'!B:G,6,0) -> 8 | U61: 8 | V61: =VLOOKUP($B61,'BDD Prof. Catedra'!$B:$J,9,0) -> 3 | W61: =U61-V61 -> 5 | X61: =V61/T61 -> 0.375 | Y61: =IFERROR((((1.96^2*0.5*0.5*($T61-V61))/(V61*($T61-1)))^0.5),"") -> 0.47819104 | Z61: =IFERROR((((1.65^2*0.5*0.5*($T61-V61))/(V61*($T61-1)))^0.5),"") -> 0.40255878 | AA61: Sondeo
A62: 98 | B62: ESPECIALIZACIÓN EN DERECHO COMERCIAL | C62: FACULTAD DE DERECHO Y CIENCIAS POLÍTICAS | D62: 19 | E62: 19 | F62: =VLOOKUP(B62,'BDD Estudiantes Posgrado'!$A$1:$D$200,4,0) -> 3 | G62: =E62-F62 -> 16 | H62: =F62/D62 -> 0.15789474 | I62: =IFERROR((((1.96^2*0.5*0.5*($D62-F62))/(F62*($D62-1)))^0.5),"") -> 0.53344443 | J62: =IFERROR((((1.65^2*0.5*0.5*($D62-F62))/(F62*($D62-1)))^0.5),"") -> 0.44907312 | K62: Sondeo | Q62: =IFERROR((((1.96^2*0.5*0.5*($L62-N62))/(N62*($L62-1)))^0.5),"") | R62: =IFERROR((((1.65^2*0.5*0.5*($L62-N62))/(N62*($L62-1)))^0.5),"") | T62: =VLOOKUP($B62,'BDD Prof. Catedra'!B:G,6,0) -> 2 | U62: 2 | V62: =VLOOKUP($B62,'BDD Prof. Catedra'!$B:$J,9,0) -> 0 | W62: =U62-V62 -> 2 | X62: =V62/T62 -> 0 | Y62: =IFERROR((((1.96^2*0.5*0.5*($T62-V62))/(V62*($T62-1)))^0.5),"") | Z62: =IFERROR((((1.65^2*0.5*0.5*($T62-V62))/(V62*($T62-1)))^0.5),"")
A63: 99 | B63: ESPECIALIZACIÓN EN DERECHO TRIBUTARIO | C63: FACULTAD DE DERECHO Y CIENCIAS POLÍTICAS | D63: 25 | E63: 12 | F63: =VLOOKUP(B63,'BDD Estudiantes Posgrado'!$A$1:$D$200,4,0) -> 2 | G63: =E63-F63 -> 10 | H63: =F63/D63 -> 0.08 | I63: =IFERROR((((1.96^2*0.5*0.5*($D63-F63))/(F63*($D63-1)))^0.5),"") -> 0.67837428 | J63: =IFERROR((((1.65^2*0.5*0.5*($D63-F63))/(F63*($D63-1)))^0.5),"") -> 0.57108039 | K63: Sondeo | Q63: =IFERROR((((1.96^2*0.5*0.5*($L63-N63))/(N63*($L63-1)))^0.5),"") | R63: =IFERROR((((1.65^2*0.5*0.5*($L63-N63))/(N63*($L63-1)))^0.5),"") | T63: =VLOOKUP($B63,'BDD Prof. Catedra'!B:G,6,0) -> 16 | U63: 15 | V63: =VLOOKUP($B63,'BDD Prof. Catedra'!$B:$J,9,0) -> 7 | W63: =U63-V63 -> 8 | X63: =V63/T63 -> 0.4375 | Y63: =IFERROR((((1.96^2*0.5*0.5*($T63-V63))/(V63*($T63-1)))^0.5),"") -> 0.28691462 | Z63: =IFERROR((((1.65^2*0.5*0.5*($T63-V63))/(V63*($T63-1)))^0.5),"") -> 0.24153527 | AA63: Sondeo
A64: 100 | B64: ESPECIALIZACIÓN EN DERECHO Y EMPRESA | C64: FACULTAD DE DERECHO Y CIENCIAS POLÍTICAS | D64: 15 | E64: 15 | F64: =VLOOKUP(B64,'BDD Estudiantes Posgrado'!$A$1:$D$200,4,0) -> 1 | G64: =E64-F64 -> 14 | H64: =F64/D64 -> 0.066666667 | I64: =IFERROR((((1.96^2*0.5*0.5*($D64-F64))/(F64*($D64-1)))^0.5),"") -> 0.98 | J64: =IFERROR((((1.65^2*0.5*0.5*($D64-F64))/(F64*($D64-1)))^0.5),"") -> 0.825 | K64: Sondeo | L64: =VLOOKUP($B64,'BDD Prof. Planta'!$B$29:$G$162,6,0) -> 1 | M64: 1 | N64: =VLOOKUP($B64,'BDD Prof. Planta'!$B$29:$L$162,11,0) -> 0 | O64: =M64-N64 -> 1 | P64: =N64/L64 -> 0 | Q64: =IFERROR((((1.96^2*0.5*0.5*($L64-N64))/(N64*($L64-1)))^0.5),"") | R64: =IFERROR((((1.65^2*0.5*0.5*($L64-N64))/(N64*($L64-1)))^0.5),"") | T64: =VLOOKUP($B64,'BDD Prof. Catedra'!B:G,6,0) -> 5 | U64: 5 | V64: =VLOOKUP($B64,'BDD Prof. Catedra'!$B:$J,9,0) -> 3 | W64: =U64-V64 -> 2 | X64: =V64/T64 -> 0.6 | Y64: =IFERROR((((1.96^2*0.5*0.5*($T64-V64))/(V64*($T64-1)))^0.5),"") -> 0.40008332 | Z64: =IFERROR((((1.65^2*0.5*0.5*($T64-V64))/(V64*($T64-1)))^0.5),"") -> 0.33680484 | AA64: Sondeo
A65: 101 | B65: ESPECIALIZACIÓN EN RESPONSABILIDAD CIVIL Y DEL ESTADO | C65: FACULTAD DE DERECHO Y CIENCIAS POLÍTICAS | D65: 9 | E65: 9 | F65: =VLOOKUP(B65,'BDD Estudiantes Posgrado'!$A$1:$D$200,4,0) -> 3 | G65: =E65-F65 -> 6 | H65: =F65/D65 -> 0.33333333 | I65: =IFERROR((((1.96^2*0.5*0.5*($D65-F65))/(F65*($D65-1)))^0.5),"") -> 0.49 | J65: =IFERROR((((1.65^2*0.5*0.5*($D65-F65))/(F65*($D65-1)))^0.5),"") -> 0.4125 | K65: Sondeo | L65: =VLOOKUP($B65,'BDD Prof. Planta'!$B$29:$G$162,6,0) -> 1 | M65: 1 | N65: =VLOOKUP($B65,'BDD Prof. Planta'!$B$29:$L$162,11,0) -> 0 | O65: =M65-N65 -> 1 | P65: =N65/L65 -> 0 | Q65: =IFERROR((((1.96^2*0.5*0.5*($L65-N65))/(N65*($L65-1)))^0.5),"") | R65: =IFERROR((((1.65^2*0.5*0.5*($L65-N65))/(N65*($L65-1)))^0.5),"") | T65: =VLOOKUP($B65,'BDD Prof. Catedra'!B:G,6,0) -> 7 | U65: 7 | V65: =VLOOKUP($B65,'BDD Prof. Catedra'!$B:$J,9,0) -> 3 | W65: =U65-V65 -> 4 | X65: =V65/T65 -> 0.42857143 | Y65: =IFERROR((((1.96^2*0.5*0.5*($T65-V65))/(V65*($T65-1)))^0.5),"") -> 0.46197643 | Z65: =IFERROR((((1.65^2*0.5*0.5*($T65-V65))/(V65*($T65-1)))^0.5),"") -> 0.38890873 | AA65: Sondeo
A66: 102 | B66: ESPECIALIZACIÓN EN SEGUROS Y SEGURIDAD SOCIAL | C66: FACULTAD DE DERECHO Y CIENCIAS POLÍTICAS | D66: 34 | E66: 18 | F66: =VLOOKUP(B66,'BDD Estudiantes Posgrado'!$A$1:$D$200,4,0) -> 13 | G66: =E66-F66 -> 5 | H66: =F66/D66 -> 0.38235294 | I66: =IFERROR((((1.96^2*0.5*0.5*($D66-F66))/(F66*($D66-1)))^0.5),"") -> 0.21682386 | J66: =IFERROR((((1.65^2*0.5*0.5*($D66-F66))/(F66*($D66-1)))^0.5),"") -> 0.18253029 | K66: Sondeo | Q66: =IFERROR((((1.96^2*0.5*0.5*($L66-N66))/(N66*($L66-1)))^0.5),"") | R66: =IFERROR((((1.65^2*0.5*0.5*($L66-N66))/(N66*($L66-1)))^0.5),"") | T66: =VLOOKUP($B66,'BDD Prof. Catedra'!B:G,6,0) -> 19 | U66: 18 | V66: =VLOOKUP($B66,'BDD Prof. Catedra'!$B:$J,9,0) -> 4 | W66: =U66-V66 -> 14 | X66: =V66/T66 -> 0.21052632 | Y66: =IFERROR((((1.96^2*0.5*0.5*($T66-V66))/(V66*($T66-1)))^0.5),"") -> 0.44730676 | Z66: =IFERROR((((1.65^2*0.5*0.5*($T66-V66))/(V66*($T66-1)))^0.5),"") -> 0.37655926 | AA66: Sondeo
A67: 96 | B67: ESPECIALIZACIÓN EN GERENCIA DE LA COMUNICACIÓN ORGANIZACIONAL | C67: FACULTAD DE COMUNICACIÓN | D67: 14 | E67: 14 | F67: =VLOOKUP(B67,'BDD Estudiantes Posgrado'!$A$1:$D$200,4,0) -> 13 | G67: =E67-F67 -> 1 | H67: =F67/D67 -> 0.92857143 | I67: =IFERROR((((1.96^2*0.5*0.5*($D67-F67))/(F67*($D67-1)))^0.5),"") -> 0.075384615 | J67: =IFERROR((((1.65^2*0.5*0.5*($D67-F67))/(F67*($D67-1)))^0.5),"") -> 0.063461538 | K67: Encuesta | Q67: =IFERROR((((1.96^2*0.5*0.5*($L67-N67))/(N67*($L67-1)))^0.5),"") | R67: =IFERROR((((1.65^2*0.5*0.5*($L67-N67))/(N67*($L67-1)))^0.5),"") | T67: =VLOOKUP($B67,'BDD Prof. Catedra'!B:G,6,0) -> 3 | U67: 3 | V67: =VLOOKUP($B67,'BDD Prof. Catedra'!$B:$J,9,0) -> 1 | W67: =U67-V67 -> 2 | X67: =V67/T67 -> 0.33333333 | Y67: =IFERROR((((1.96^2*0.5*0.5*($T67-V67))/(V67*($T67-1)))^0.5),"") -> 0.98 | Z67: =IFERROR((((1.65^2*0.5*0.5*($T67-V67))/(V67*($T67-1)))^0.5),"") -> 0.825 | AA67: Sondeo
A68: 103 | B68: ESPECIALIZACIÓN EN GERENCIA EDUCATIVA | C68: FACULTAD DE EDUCACIÓN | D68: 7 | E68: 7 | F68: =VLOOKUP(B68,'BDD Estudiantes Posgrado'!$A$1:$D$200,4,0) -> 1 | G68: =E68-F68 -> 6 | H68: =F68/D68 -> 0.14285714 | I68: =IFERROR((((1.96^2*0.5*0.5*($D68-F68))/(F68*($D68-1)))^0.5),"") -> 0.98 | J68: =IFERROR((((1.65^2*0.5*0.5*($D68-F68))/(F68*($D68-1)))^0.5),"") -> 0.825 | K68: Sondeo | L68: =VLOOKUP($B68,'BDD Prof. Planta'!$B$29:$G$162,6,0) -> 2 | M68: 2 | N68: =VLOOKUP($B68,'BDD Prof. Planta'!$B$29:$L$162,11,0) -> 1 | O68: =M68-N68 -> 1 | P68: =N68/L68 -> 0.5 | Q68: =IFERROR((((1.96^2*0.5*0.5*($L68-N68))/(N68*($L68-1)))^0.5),"") -> 0.98 | R68: =IFERROR((((1.65^2*0.5*0.5*($L68-N68))/(N68*($L68-1)))^0.5),"") -> 0.825 | S68: Sondeo | T68: =VLOOKUP($B68,'BDD Prof. Catedra'!B:G,6,0) -> 2 | U68: 2 | V68: =VLOOKUP($B68,'BDD Prof. Catedra'!$B:$J,9,0) -> 0 | W68: =U68-V68 -> 2 | X68: =V68/T68 -> 0 | Y68: =IFERROR((((1.96^2*0.5*0.5*($T68-V68))/(V68*($T68-1)))^0.5),"") | Z68: =IFERROR((((1.65^2*0.5*0.5*($T68-V68))/(V68*($T68-1)))^0.5),"")
A69: 202 | B69: ESPECIALIZACIÓN EN EMPRENDIMIENTO Y NEGOCIOS DIGITALES- CHÍA | C69: INSTITUTO FORUM | D69: 16 | E69: 15 | F69: =VLOOKUP(B69,'BDD Estudiantes Posgrado'!$A$1:$D$200,4,0) -> 14 | G69: =E69-F69 -> 1 | H69: =F69/D69 -> 0.875 | I69: =IFERROR((((1.96^2*0.5*0.5*($D69-F69))/(F69*($D69-1)))^0.5),"") -> 0.095638207 | J69: =IFERROR((((1.65^2*0.5*0.5*($D69-F69))/(F69*($D69-1)))^0.5),"") -> 0.080511756 | K69: Encuesta | Q69: =IFERROR((((1.96^2*0.5*0.5*($L69-N69))/(N69*($L69-1)))^0.5),"") | R69: =IFERROR((((1.65^2*0.5*0.5*($L69-N69))/(N69*($L69-1)))^0.5),"") | T69: =VLOOKUP($B69,'BDD Prof. Catedra'!B:G,6,0) -> 5 | U69: 5 | V69: =VLOOKUP($B69,'BDD Prof. Catedra'!$B:$J,9,0) -> 5 | W69: =U69-V69 -> 0 | X69: =V69/T69 -> 1 | Y69: =IFERROR((((1.96^2*0.5*0.5*($T69-V69))/(V69*($T69-1)))^0.5),"") -> 0 | Z69: =IFERROR((((1.65^2*0.5*0.5*($T69-V69))/(V69*($T69-1)))^0.5),"") -> 0 | AA69: Encuesta
A70: 117 | B70: ESPECIALIZACIÓN EN FINANZAS CORPORATIVAS CHÍA | C70: INSTITUTO FORUM | D70: 28 | E70: 27 | F70: =VLOOKUP(B70,'BDD Estudiantes Posgrado'!$A$1:$D$200,4,0) -> 27 | G70: =E70-F70 -> 0 | H70: =F70/D70 -> 0.96428571 | I70: =IFERROR((((1.96^2*0.5*0.5*($D70-F70))/(F70*($D70-1)))^0.5),"") -> 0.036296296 | J70: =IFERROR((((1.65^2*0.5*0.5*($D70-F70))/(F70*($D70-1)))^0.5),"") -> 0.030555556 | K70: Encuesta | L70: =VLOOKUP($B70,'BDD Prof. Planta'!$B$29:$G$162,6,0) -> 1 | M70: 1 | N70: =VLOOKUP($B70,'BDD Prof. Planta'!$B$29:$L$162,11,0) -> 1 | O70: =M70-N70 -> 0 | P70: =N70/L70 -> 1 | Q70: 0 | R70: =IFERROR((((1.65^2*0.5*0.5*($L70-N70))/(N70*($L70-1)))^0.5),0) -> 0 | S70: Encuesta | T70: =VLOOKUP($B70,'BDD Prof. Catedra'!B:G,6,0) -> 6 | U70: 6 | V70: =VLOOKUP($B70,'BDD Prof. Catedra'!$B:$J,9,0) -> 6 | W70: =U70-V70 -> 0 | X70: =V70/T70 -> 1 | Y70: =IFERROR((((1.96^2*0.5*0.5*($T70-V70))/(V70*($T70-1)))^0.5),"") -> 0 | Z70: =IFERROR((((1.65^2*0.5*0.5*($T70-V70))/(V70*($T70-1)))^0.5),"") -> 0 | AA70: Encuesta
A71: 111 | B71: ESPECIALIZACIÓN EN GERENCIA COMERCIAL CHÍA | C71: INSTITUTO FORUM | D71: 74 | E71: 62 | F71: =VLOOKUP(B71,'BDD Estudiantes Posgrado'!$A$1:$D$200,4,0) -> 62 | G71: =E71-F71 -> 0 | H71: =F71/D71 -> 0.83783784 | I71: =IFERROR((((1.96^2*0.5*0.5*($D71-F71))/(F71*($D71-1)))^0.5),"") -> 0.050461415 | J71: =IFERROR((((1.65^2*0.5*0.5*($D71-F71))/(F71*($D71-1)))^0.5),"") -> 0.042480273 | K71: Encuesta | L71: =VLOOKUP($B71,'BDD Prof. Planta'!$B$29:$G$162,6,0) -> 1 | M71: 1 | N71: =VLOOKUP($B71,'BDD Prof. Planta'!$B$29:$L$162,11,0) -> 1 | O71: =M71-N71 -> 0 | P71: =N71/L71 -> 1 | Q71: =IFERROR((((1.96^2*0.5*0.5*($L71-N71))/(N71*($L71-1)))^0.5),0) -> 0 | R71: =IFERROR((((1.65^2*0.5*0.5*($L71-N71))/(N71*($L71-1)))^0.5),0) -> 0 | S71: Encuesta | T71: =VLOOKUP($B71,'BDD Prof. Catedra'!B:G,6,0) -> 4 | U71: 4 | V71: =VLOOKUP($B71,'BDD Prof. Catedra'!$B:$J,9,0) -> 4 | W71: =U71-V71 -> 0 | X71: =V71/T71 -> 1 | Y71: =IFERROR((((1.96^2*0.5*0.5*($T71-V71))/(V71*($T71-1)))^0.5),"") -> 0 | Z71: =IFERROR((((1.65^2*0.5*0.5*($T71-V71))/(V71*($T71-1)))^0.5),"") -> 0 | AA71: Encuesta
A72: 112 | B72: ESPECIALIZACIÓN EN GERENCIA DE PRODUCCIÓN Y OPERACIONES CHÍA | C72: INSTITUTO FORUM | D72: 26 | E72: 26 | F72: =VLOOKUP(B72,'BDD Estudiantes Posgrado'!$A$1:$D$200,4,0) -> 26 | G72: =E72-F72 -> 0 | H72: =F72/D72 -> 1 | I72: =IFERROR((((1.96^2*0.5*0.5*($D72-F72))/(F72*($D72-1)))^0.5),"") -> 0 | J72: =IFERROR((((1.65^2*0.5*0.5*($D72-F72))/(F72*($D72-1)))^0.5),"") -> 0 | K72: Encuesta | L72: =VLOOKUP($B72,'BDD Prof. Planta'!$B$29:$G$162,6,0) -> 1 | M72: 1 | N72: =VLOOKUP($B72,'BDD Prof. Planta'!$B$29:$L$162,11,0) -> 1 | O72: =M72-N72 -> 0 | P72: =N72/L72 -> 1 | Q72: =IFERROR((((1.96^2*0.5*0.5*($L72-N72))/(N72*($L72-1)))^0.5),0) -> 0 | R72: =IFERROR((((1.65^2*0.5*0.5*($L72-N72))/(N72*($L72-1)))^0.5),0) -> 0 | S72: Encuesta | T72: =VLOOKUP($B72,'BDD Prof. Catedra'!B:G,6,0) -> 2 | U72: 2 | V72: =VLOOKUP($B72,'BDD Prof. Catedra'!$B:$J,9,0) -> 1 | W72: =U72-V72 -> 1 | X72: =V72/T72 -> 0.5 | Y72: =IFERROR((((1.96^2*0.5*0.5*($T72-V72))/(V72*($T72-1)))^0.5),"") -> 0.98 | Z72: =IFERROR((((1.65^2*0.5*0.5*($T72-V72))/(V72*($T72-1)))^0.5),"") -> 0.825 | AA72: Sondeo
A73: 119 | B73: ESPECIALIZACIÓN EN GERENCIA DE PROYECTOS CON ENFOQUE EN HABILIDADES DIRECTIVAS CHÍA | C73: INSTITUTO FORUM | D73: 48 | E73: 45 | F73: =VLOOKUP(B73,'BDD Estudiantes Posgrado'!$A$1:$D$200,4,0) -> 45 | G73: =E73-F73 -> 0 | H73: =F73/D73 -> 0.9375 | I73: =IFERROR((((1.96^2*0.5*0.5*($D73-F73))/(F73*($D73-1)))^0.5),"") -> 0.036908935 | J73: =IFERROR((((1.65^2*0.5*0.5*($D73-F73))/(F73*($D73-1)))^0.5),"") -> 0.031071298 | K73: Encuesta | L73: 1 | M73: 1 | N73: =VLOOKUP($B73,'BDD Prof. Planta'!$B$29:$L$162,11,0) -> 1 | O73: =M73-N73 -> 0 | P73: =N73/L73 -> 1 | Q73: =IFERROR((((1.96^2*0.5*0.5*($L73-N73))/(N73*($L73-1)))^0.5),0) -> 0 | R73: =IFERROR((((1.65^2*0.5*0.5*($L73-N73))/(N73*($L73-1)))^0.5),0) -> 0 | S73: Encuesta | T73: =VLOOKUP($B73,'BDD Prof. Catedra'!B:G,6,0) -> 3 | U73: 3 | V73: =VLOOKUP($B73,'BDD Prof. Catedra'!$B:$J,9,0) -> 2 | W73: =U73-V73 -> 1 | X73: =V73/T73 -> 0.66666667 | Y73: =IFERROR((((1.96^2*0.5*0.5*($T73-V73))/(V73*($T73-1)))^0.5),"") -> 0.49 | Z73: =IFERROR((((1.65^2*0.5*0.5*($T73-V73))/(V73*($T73-1)))^0.5),"") -> 0.4125 | AA73: Sondeo
A74: 120 | B74: ESPECIALIZACIÓN EN GERENCIA DE RIESGOS - CHÍA | C74: INSTITUTO FORUM | D74: 28 | E74: 28 | F74: =VLOOKUP(B74,'BDD Estudiantes Posgrado'!$A$1:$D$200,4,0) -> 28 | G74: =E74-F74 -> 0 | H74: =F74/D74 -> 1 | I74: =IFERROR((((1.96^2*0.5*0.5*($D74-F74))/(F74*($D74-1)))^0.5),"") -> 0 | J74: =IFERROR((((1.65^2*0.5*0.5*($D74-F74))/(F74*($D74-1)))^0.5),"") -> 0 | K74: Encuesta | Q74: =IFERROR((((1.96^2*0.5*0.5*($L74-N74))/(N74*($L74-1)))^0.5),"") | R74: =IFERROR((((1.65^2*0.5*0.5*($L74-N74))/(N74*($L74-1)))^0.5),"") | T74: =VLOOKUP($B74,'BDD Prof. Catedra'!B:G,6,0) -> 5 | U74: 5 | V74: =VLOOKUP($B74,'BDD Prof. Catedra'!$B:$J,9,0) -> 5 | W74: =U74-V74 -> 0 | X74: =V74/T74 -> 1 | Y74: =IFERROR((((1.96^2*0.5*0.5*($T74-V74))/(V74*($T74-1)))^0.5),"") -> 0 | Z74: =IFERROR((((1.65^2*0.5*0.5*($T74-V74))/(V74*($T74-1)))^0.5),"") -> 0 | AA74: Encuesta
A75: 118 | B75: ESPECIALIZACIÓN EN GERENCIA DEL SERVICIO CHÍA | C75: INSTITUTO FORUM | D75: 22 | E75: 21 | F75: =VLOOKUP(B75,'BDD Estudiantes Posgrado'!$A$1:$D$200,4,0) -> 18 | G75: =E75-F75 -> 3 | H75: =F75/D75 -> 0.81818182 | I75: =IFERROR((((1.96^2*0.5*0.5*($D75-F75))/(F75*($D75-1)))^0.5),"") -> 0.10081152 | J75: =IFERROR((((1.65^2*0.5*0.5*($D75-F75))/(F75*($D75-1)))^0.5),"") -> 0.084866842 | K75: Encuesta | Q75: =IFERROR((((1.96^2*0.5*0.5*($L75-N75))/(N75*($L75-1)))^0.5),"") | R75: =IFERROR((((1.65^2*0.5*0.5*($L75-N75))/(N75*($L75-1)))^0.5),"") | T75: =VLOOKUP($B75,'BDD Prof. Catedra'!B:G,6,0) -> 14 | U75: 14 | V75: =VLOOKUP($B75,'BDD Prof. Catedra'!$B:$J,9,0) -> 10 | W75: =U75-V75 -> 4 | X75: =V75/T75 -> 0.71428571 | Y75: =IFERROR((((1.96^2*0.5*0.5*($T75-V75))/(V75*($T75-1)))^0.5),"") -> 0.17190337 | Z75: =IFERROR((((1.65^2*0.5*0.5*($T75-V75))/(V75*($T75-1)))^0.5),"") -> 0.14471457 | AA75: Sondeo
A76: 114 | B76: ESPECIALIZACIÓN EN GERENCIA ESTRATÉGICA CHÍA | C76: INSTITUTO FORUM | D76: 101 | E76: 96 | F76: =VLOOKUP(B76,'BDD Estudiantes Posgrado'!$A$1:$D$200,4,0) -> 96 | G76: =E76-F76 -> 0 | H76: =F76/D76 -> 0.95049505 | I76: =IFERROR((((1.96^2*0.5*0.5*($D76-F76))/(F76*($D76-1)))^0.5),"") -> 0.022365338 | J76: =IFERROR((((1.65^2*0.5*0.5*($D76-F76))/(F76*($D76-1)))^0.5),"") -> 0.018827963 | K76: Encuesta | L76: =VLOOKUP($B76,'BDD Prof. Planta'!$B$29:$G$162,6,0) -> 2 | M76: 2 | N76: =VLOOKUP($B76,'BDD Prof. Planta'!$B$29:$L$162,11,0) -> 2 | O76: =M76-N76 -> 0 | P76: =N76/L76 -> 1 | Q76: 0 | R76: =IFERROR((((1.65^2*0.5*0.5*($L76-N76))/(N76*($L76-1)))^0.5),"") -> 0 | S76: Encuesta | T76: =VLOOKUP($B76,'BDD Prof. Catedra'!B:G,6,0) -> 8 | U76: 8 | V76: =VLOOKUP($B76,'BDD Prof. Catedra'!$B:$J,9,0) -> 8 | W76: =U76-V76 -> 0 | X76: =V76/T76 -> 1 | Y76: =IFERROR((((1.96^2*0.5*0.5*($T76-V76))/(V76*($T76-1)))^0.5),"") -> 0 | Z76: =IFERROR((((1.65^2*0.5*0.5*($T76-V76))/(V76*($T76-1)))^0.5),"") -> 0 | AA76: Encuesta
A77: 113 | B77: ESPECIALIZACIÓN EN GERENCIA ESTRATÉGICA DE MARCA CHÍA | C77: INSTITUTO FORUM | D77: 35 | E77: 33 | F77: =VLOOKUP(B77,'BDD Estudiantes Posgrado'!$A$1:$D$200,4,0) -> 33 | G77: =E77-F77 -> 0 | H77: =F77/D77 -> 0.94285714 | I77: =IFERROR((((1.96^2*0.5*0.5*($D77-F77))/(F77*($D77-1)))^0.5),"") -> 0.041375632 | J77: =IFERROR((((1.65^2*0.5*0.5*($D77-F77))/(F77*($D77-1)))^0.5),"") -> 0.034831527 | K77: Encuesta | L77: =VLOOKUP($B77,'BDD Prof. Planta'!$B$29:$G$162,6,0) -> 2 | M77: 2 | N77: =VLOOKUP($B77,'BDD Prof. Planta'!$B$29:$L$162,11,0) -> 2 | O77: =M77-N77 -> 0 | P77: =N77/L77 -> 1 | Q77: =IFERROR((((1.96^2*0.5*0.5*($L77-N77))/(N77*($L77-1)))^0.5),"") -> 0 | R77: =IFERROR((((1.65^2*0.5*0.5*($L77-N77))/(N77*($L77-1)))^0.5),"") -> 0 | S77: Encuesta | T77: =VLOOKUP($B77,'BDD Prof. Catedra'!B:G,6,0) -> 4 | U77: 3 | V77: =VLOOKUP($B77,'BDD Prof. Catedra'!$B:$J,9,0) -> 3 | W77: =U77-V77 -> 0 | X77: =V77/T77 -> 0.75 | Y77: =IFERROR((((1.96^2*0.5*0.5*($T77-V77))/(V77*($T77-1)))^0.5),"") -> 0.32666667 | Z77: =IFERROR((((1.65^2*0.5*0.5*($T77-V77))/(V77*($T77-1)))^0.5),"") -> 0.275 | AA77: Sondeo
A78: 110 | B78: ESPECIALIZACIÓN EN GERENCIA FINANCIERA INTERNACIONAL CHÍA | C78: INSTITUTO FORUM | D78: 30 | E78: 27 | F78: =VLOOKUP(B78,'BDD Estudiantes Posgrado'!$A$1:$D$200,4,0) -> 27 | G78: =E78-F78 -> 0 | H78: =F78/D78 -> 0.9 | I78: =IFERROR((((1.96^2*0.5*0.5*($D78-F78))/(F78*($D78-1)))^0.5),"") -> 0.060660477 | J78: =IFERROR((((1.65^2*0.5*0.5*($D78-F78))/(F78*($D78-1)))^0.5),"") -> 0.051066218 | K78: Encuesta | L78: =VLOOKUP($B78,'BDD Prof. Planta'!$B$29:$G$162,6,0) -> 1 | M78: 1 | N78: =VLOOKUP($B78,'BDD Prof. Planta'!$B$29:$L$162,11,0) -> 1 | O78: =M78-N78 -> 0 | P78: =N78/L78 -> 1 | Q78: 0 | R78: =IFERROR((((1.65^2*0.5*0.5*($L78-N78))/(N78*($L78-1)))^0.5),0) -> 0 | S78: Encuesta | T78: =VLOOKUP($B78,'BDD Prof. Catedra'!B:G,6,0) -> 3 | U78: 3 | V78: =VLOOKUP($B78,'BDD Prof. Catedra'!$B:$J,9,0) -> 2 | W78: =U78-V78 -> 1 | X78: =V78/T78 -> 0.66666667 | Y78: =IFERROR((((1.96^2*0.5*0.5*($T78-V78))/(V78*($T78-1)))^0.5),"") -> 0.49 | Z78: =IFERROR((((1.65^2*0.5*0.5*($T78-V78))/(V78*($T78-1)))^0.5),"") -> 0.4125 | AA78: Sondeo
A79: 115 | B79: ESPECIALIZACIÓN EN GERENCIA LOGÍSTICA CHÍA | C79: INSTITUTO FORUM | D79: 45 | E79: 40 | F79: =VLOOKUP(B79,'BDD Estudiantes Posgrado'!$A$1:$D$200,4,0) -> 33 | G79: =E79-F79 -> 7 | H79: =F79/D79 -> 0.73333333 | I79: =IFERROR((((1.96^2*0.5*0.5*($D79-F79))/(F79*($D79-1)))^0.5),"") -> 0.089090909 | J79: =IFERROR((((1.65^2*0.5*0.5*($D79-F79))/(F79*($D79-1)))^0.5),"") -> 0.075 | K79: Sondeo | L79: =VLOOKUP($B79,'BDD Prof. Planta'!$B$29:$G$162,6,0) -> 3 | M79: 3 | N79: =VLOOKUP($B79,'BDD Prof. Planta'!$B$29:$L$162,11,0) -> 2 | O79: =M79-N79 -> 1 | P79: =N79/L79 -> 0.66666667 | Q79: =IFERROR((((1.96^2*0.5*0.5*($L79-N79))/(N79*($L79-1)))^0.5),"") -> 0.49 | R79: =IFERROR((((1.65^2*0.5*0.5*($L79-N79))/(N79*($L79-1)))^0.5),"") -> 0.4125 | S79: Sondeo | T79: =VLOOKUP($B79,'BDD Prof. Catedra'!B:G,6,0) -> 2 | U79: 2 | V79: =VLOOKUP($B79,'BDD Prof. Catedra'!$B:$J,9,0) -> 0 | W79: =U79-V79 -> 2 | X79: =V79/T79 -> 0 | Y79: =IFERROR((((1.96^2*0.5*0.5*($T79-V79))/(V79*($T79-1)))^0.5),"") | Z79: =IFERROR((((1.65^2*0.5*0.5*($T79-V79))/(V79*($T79-1)))^0.5),"")
A80: 141 | B80: ESPECIALIZACIÓN EN GESTIÓN PARA EL DESARROLLO HUMANO EN LA ORGANIZACIÓN CHÍA | C80: INSTITUTO FORUM | D80: 33 | E80: 30 | F80: =VLOOKUP(B80,'BDD Estudiantes Posgrado'!$A$1:$D$200,4,0) -> 16 | G80: =E80-F80 -> 14 | H80: =F80/D80 -> 0.48484848 | I80: =IFERROR((((1.96^2*0.5*0.5*($D80-F80))/(F80*($D80-1)))^0.5),"") -> 0.1785729 | J80: =IFERROR((((1.65^2*0.5*0.5*($D80-F80))/(F80*($D80-1)))^0.5),"") -> 0.15032923 | K80: Sondeo | L80: =VLOOKUP($B80,'BDD Prof. Planta'!$B$29:$G$162,6,0) -> 1 | M80: 1 | N80: =VLOOKUP($B80,'BDD Prof. Planta'!$B$29:$L$162,11,0) -> 1 | O80: =M80-N80 -> 0 | P80: =N80/L80 -> 1 | Q80: 0 | R80: =IFERROR((((1.65^2*0.5*0.5*($L80-N80))/(N80*($L80-1)))^0.5),0) -> 0 | S80: Encuesta | T80: =VLOOKUP($B80,'BDD Prof. Catedra'!B:G,6,0) -> 6 | U80: 6 | V80: =VLOOKUP($B80,'BDD Prof. Catedra'!$B:$J,9,0) -> 2 | W80: =U80-V80 -> 4 | X80: =V80/T80 -> 0.33333333 | Y80: =IFERROR((((1.96^2*0.5*0.5*($T80-V80))/(V80*($T80-1)))^0.5),"") -> 0.61980642 | Z80: =IFERROR((((1.65^2*0.5*0.5*($T80-V80))/(V80*($T80-1)))^0.5),"") -> 0.52177581 | AA80: Sondeo
A81: 203 | B81: ESPECIALIZACIÓN EN LIDERAZGO Y COACHING- CHÍA | C81: INSTITUTO FORUM | D81: 27 | E81: 25 | F81: =VLOOKUP(B81,'BDD Estudiantes Posgrado'!$A$1:$D$200,4,0) -> 10 | G81: =E81-F81 -> 15 | H81: =F81/D81 -> 0.37037037 | I81: =IFERROR((((1.96^2*0.5*0.5*($D81-F81))/(F81*($D81-1)))^0.5),"") -> 0.25059007 | J81: =IFERROR((((1.65^2*0.5*0.5*($D81-F81))/(F81*($D81-1)))^0.5),"") -> 0.21095593 | K81: Sondeo | L81: =VLOOKUP($B81,'BDD Prof. Planta'!$B$29:$G$162,6,0) -> 1 | M81: 1 | N81: =VLOOKUP($B81,'BDD Prof. Planta'!$B$29:$L$162,11,0) -> 1 | O81: =M81-N81 -> 0 | P81: =N81/L81 -> 1 | Q81: 0 | R81: =IFERROR((((1.65^2*0.5*0.5*($L81-N81))/(N81*($L81-1)))^0.5),0) -> 0 | S81: Encuesta | T81: =VLOOKUP($B81,'BDD Prof. Catedra'!B:G,6,0) -> 2 | U81: 2 | V81: =VLOOKUP($B81,'BDD Prof. Catedra'!$B:$J,9,0) -> 1 | W81: =U81-V81 -> 1 | X81: =V81/T81 -> 0.5 | Y81: =IFERROR((((1.96^2*0.5*0.5*($T81-V81))/(V81*($T81-1)))^0.5),"") -> 0.98 | Z81: =IFERROR((((1.65^2*0.5*0.5*($T81-V81))/(V81*($T81-1)))^0.5),"") -> 0.825 | AA81: Sondeo
A82: 107 | B82: ESPECIALIZACIÓN EN PSICOLOGÍA CLÍNICA DE LA NIÑEZ Y LA ADOLESCENCIA | C82: FACULTAD DE PSICOLOGÍA | D82: 16 | E82: 15 | F82: =VLOOKUP(B82,'BDD Estudiantes Posgrado'!$A$1:$D$200,4,0) -> 14 | G82: =E82-F82 -> 1 | H82: =F82/D82 -> 0.875 | I82: =IFERROR((((1.96^2*0.5*0.5*($D82-F82))/(F82*($D82-1)))^0.5),"") -> 0.095638207 | J82: =IFERROR((((1.65^2*0.5*0.5*($D82-F82))/(F82*($D82-1)))^0.5),"") -> 0.080511756 | K82: Encuesta | L82: =VLOOKUP($B82,'BDD Prof. Planta'!$B$29:$G$162,6,0) -> 3 | M82: 3 | N82: =VLOOKUP($B82,'BDD Prof. Planta'!$B$29:$L$162,11,0) -> 3 | O82: =M82-N82 -> 0 | P82: =N82/L82 -> 1 | Q82: =IFERROR((((1.96^2*0.5*0.5*($L82-N82))/(N82*($L82-1)))^0.5),"") -> 0 | R82: =IFERROR((((1.65^2*0.5*0.5*($L82-N82))/(N82*($L82-1)))^0.5),"") -> 0 | S82: Encuesta | T82: =VLOOKUP($B82,'BDD Prof. Catedra'!B:G,6,0) -> 9 | U82: 9 | V82: =VLOOKUP($B82,'BDD Prof. Catedra'!$B:$J,9,0) -> 9 | W82: =U82-V82 -> 0 | X82: =V82/T82 -> 1 | Y82: =IFERROR((((1.96^2*0.5*0.5*($T82-V82))/(V82*($T82-1)))^0.5),"") -> 0 | Z82: =IFERROR((((1.65^2*0.5*0.5*($T82-V82))/(V82*($T82-1)))^0.5),"") -> 0 | AA82: Encuesta
A83: 108 | B83: ESPECIALIZACIÓN EN PSICOLOGÍA EDUCATIVA | C83: FACULTAD DE PSICOLOGÍA | D83: 16 | E83: 16 | F83: =VLOOKUP(B83,'BDD Estudiantes Posgrado'!$A$1:$D$200,4,0) -> 16 | G83: =E83-F83 -> 0 | H83: =F83/D83 -> 1 | I83: =IFERROR((((1.96^2*0.5*0.5*($D83-F83))/(F83*($D83-1)))^0.5),"") -> 0 | J83: =IFERROR((((1.65^2*0.5*0.5*($D83-F83))/(F83*($D83-1)))^0.5),"") -> 0 | K83: Encuesta | L83: =VLOOKUP($B83,'BDD Prof. Planta'!$B$29:$G$162,6,0) -> 2 | M83: 2 | N83: =VLOOKUP($B83,'BDD Prof. Planta'!$B$29:$L$162,11,0) -> 2 | O83: =M83-N83 -> 0 | P83: =N83/L83 -> 1 | Q83: =IFERROR((((1.96^2*0.5*0.5*($L83-N83))/(N83*($L83-1)))^0.5),"") -> 0 | R83: =IFERROR((((1.65^2*0.5*0.5*($L83-N83))/(N83*($L83-1)))^0.5),"") -> 0 | S83: Encuesta | T83: =VLOOKUP($B83,'BDD Prof. Catedra'!B:G,6,0) -> 3 | U83: 3 | V83: =VLOOKUP($B83,'BDD Prof. Catedra'!$B:$J,9,0) -> 3 | W83: =U83-V83 -> 0 | X83: =V83/T83 -> 1 | Y83: =IFERROR((((1.96^2*0.5*0.5*($T83-V83))/(V83*($T83-1)))^0.5),"") -> 0 | Z83: =IFERROR((((1.65^2*0.5*0.5*($T83-V83))/(V83*($T83-1)))^0.5),"") -> 0 | AA83: Encuesta
A84: 104 | B84: ESPECIALIZACIÓN EN ENFERMERÍA EN CUIDADO CRÍTICO | C84: FACULTAD DE ENFERMERÍA Y REHABILITACIÓN | D84: 38 | E84: 35 | F84: =VLOOKUP(B84,'BDD Estudiantes Posgrado'!$A$1:$D$200,4,0) -> 10 | G84: =E84-F84 -> 25 | H84: =F84/D84 -> 0.26315789 | I84: =IFERROR((((1.96^2*0.5*0.5*($D84-F84))/(F84*($D84-1)))^0.5),"") -> 0.26959028 | J84: =IFERROR((((1.65^2*0.5*0.5*($D84-F84))/(F84*($D84-1)))^0.5),"") -> 0.226951 | K84: Sondeo | L84: =VLOOKUP($B84,'BDD Prof. Planta'!$B$29:$G$162,6,0) -> 10 | M84: 10 | N84: =VLOOKUP($B84,'BDD Prof. Planta'!$B$29:$L$162,11,0) -> 9 | O84: =M84-N84 -> 1 | P84: =N84/L84 -> 0.9 | Q84: =IFERROR((((1.96^2*0.5*0.5*($L84-N84))/(N84*($L84-1)))^0.5),"") -> 0.10888889 | R84: =IFERROR((((1.65^2*0.5*0.5*($L84-N84))/(N84*($L84-1)))^0.5),"") -> 0.091666667 | S84: Encuesta | T84: =VLOOKUP($B84,'BDD Prof. Catedra'!B:G,6,0) -> 6 | U84: 6 | V84: =VLOOKUP($B84,'BDD Prof. Catedra'!$B:$J,9,0) -> 5 | W84: =U84-V84 -> 1 | X84: =V84/T84 -> 0.83333333 | Y84: =IFERROR((((1.96^2*0.5*0.5*($T84-V84))/(V84*($T84-1)))^0.5),"") -> 0.196 | Z84: =IFERROR((((1.65^2*0.5*0.5*($T84-V84))/(V84*($T84-1)))^0.5),"") -> 0.165 | AA84: Encuesta
A85: 105 | B85: ESPECIALIZACIÓN EN TERAPIA MANUAL ORTOPÉDICA | C85: FACULTAD DE ENFERMERÍA Y REHABILITACIÓN | D85: 12 | E85: 12 | F85: =VLOOKUP(B85,'BDD Estudiantes Posgrado'!$A$1:$D$200,4,0) -> 12 | G85: =E85-F85 -> 0 | H85: =F85/D85 -> 1 | I85: =IFERROR((((1.96^2*0.5*0.5*($D85-F85))/(F85*($D85-1)))^0.5),"") -> 0 | J85: =IFERROR((((1.65^2*0.5*0.5*($D85-F85))/(F85*($D85-1)))^0.5),"") -> 0 | K85: Encuesta | L85: =VLOOKUP($B85,'BDD Prof. Planta'!$B$29:$G$162,6,0) -> 5 | M85: 5 | N85: =VLOOKUP($B85,'BDD Prof. Planta'!$B$29:$L$162,11,0) -> 5 | O85: =M85-N85 -> 0 | P85: =N85/L85 -> 1 | Q85: =IFERROR((((1.96^2*0.5*0.5*($L85-N85))/(N85*($L85-1)))^0.5),"") -> 0 | R85: =IFERROR((((1.65^2*0.5*0.5*($L85-N85))/(N85*($L85-1)))^0.5),"") -> 0 | S85: Encuesta | T85: =VLOOKUP($B85,'BDD Prof. Catedra'!B:G,6,0) -> 3 | U85: 3 | V85: =VLOOKUP($B85,'BDD Prof. Catedra'!$B:$J,9,0) -> 3 | W85: =U85-V85 -> 0 | X85: =V85/T85 -> 1 | Y85: =IFERROR((((1.96^2*0.5*0.5*($T85-V85))/(V85*($T85-1)))^0.5),"") -> 0 | Z85: =IFERROR((((1.65^2*0.5*0.5*($T85-V85))/(V85*($T85-1)))^0.5),"") -> 0 | AA85: Encuesta
A86: 208 | B86: ESPECIALIZACIÓN EN GERENCIA DE PROYECTOS CON ENFOQUE EN HABILIDADES DIRECTIVAS - BOGOTÁ | C86: INSTITUTO FORUM | D86: 23 | E86: 22 | F86: =VLOOKUP(B86,'BDD Estudiantes Posgrado'!$A$1:$D$200,4,0) -> 22 | G86: =E86-F86 -> 0 | H86: =F86/D86 -> 0.95652174 | I86: =IFERROR((((1.96^2*0.5*0.5*($D86-F86))/(F86*($D86-1)))^0.5),"") -> 0.044545455 | J86: =IFERROR((((1.65^2*0.5*0.5*($D86-F86))/(F86*($D86-1)))^0.5),"") -> 0.0375 | K86: Encuesta | Q86: =IFERROR((((1.96^2*0.5*0.5*($L86-N86))/(N86*($L86-1)))^0.5),"") | R86: =IFERROR((((1.65^2*0.5*0.5*($L86-N86))/(N86*($L86-1)))^0.5),"") | T86: =VLOOKUP($B86,'BDD Prof. Catedra'!B:G,6,0) -> 4 | U86: 4 | V86: =VLOOKUP($B86,'BDD Prof. Catedra'!$B:$J,9,0) -> 3 | W86: =U86-V86 -> 1 | X86: =V86/T86 -> 0.75 | Y86: =IFERROR((((1.96^2*0.5*0.5*($T86-V86))/(V86*($T86-1)))^0.5),"") -> 0.32666667 | Z86: =IFERROR((((1.65^2*0.5*0.5*($T86-V86))/(V86*($T86-1)))^0.5),"") -> 0.275 | AA86: Sondeo
A87: 145 | B87: ESPECIALIZACIÓN EN GERENCIA COMERCIAL - BOGOTÁ | C87: INSTITUTO FORUM | D87: 21 | E87: 20 | F87: =VLOOKUP(B87,'BDD Estudiantes Posgrado'!$A$1:$D$200,4,0) -> 17 | G87: =E87-F87 -> 3 | H87: =F87/D87 -> 0.80952381 | I87: =IFERROR((((1.96^2*0.5*0.5*($D87-F87))/(F87*($D87-1)))^0.5),"") -> 0.10629592 | J87: =IFERROR((((1.65^2*0.5*0.5*($D87-F87))/(F87*($D87-1)))^0.5),"") -> 0.089483814 | K87: Encuesta | Q87: =IFERROR((((1.96^2*0.5*0.5*($L87-N87))/(N87*($L87-1)))^0.5),"") | R87: =IFERROR((((1.65^2*0.5*0.5*($L87-N87))/(N87*($L87-1)))^0.5),"") | T87: =VLOOKUP($B87,'BDD Prof. Catedra'!B:G,6,0) -> 3 | U87: 3 | V87: =VLOOKUP($B87,'BDD Prof. Catedra'!$B:$J,9,0) -> 2 | W87: =U87-V87 -> 1 | X87: =V87/T87 -> 0.66666667 | Y87: =IFERROR((((1.96^2*0.5*0.5*($T87-V87))/(V87*($T87-1)))^0.5),"") -> 0.49 | Z87: =IFERROR((((1.65^2*0.5*0.5*($T87-V87))/(V87*($T87-1)))^0.5),"") -> 0.4125 | AA87: Sondeo
A88: 143 | B88: ESPECIALIZACIÓN EN GERENCIA LOGÍSTICA - BOGOTÁ | C88: INSTITUTO FORUM | D88: 17 | E88: 17 | F88: =VLOOKUP(B88,'BDD Estudiantes Posgrado'!$A$1:$D$200,4,0) -> 17 | G88: =E88-F88 -> 0 | H88: =F88/D88 -> 1 | I88: =IFERROR((((1.96^2*0.5*0.5*($D88-F88))/(F88*($D88-1)))^0.5),"") -> 0 | J88: =IFERROR((((1.65^2*0.5*0.5*($D88-F88))/(F88*($D88-1)))^0.5),"") -> 0 | K88: Encuesta | Q88: =IFERROR((((1.96^2*0.5*0.5*($L88-N88))/(N88*($L88-1)))^0.5),"") | R88: =IFERROR((((1.65^2*0.5*0.5*($L88-N88))/(N88*($L88-1)))^0.5),"") | T88: =VLOOKUP($B88,'BDD Prof. Catedra'!B:G,6,0) -> 3 | U88: 3 | V88: =VLOOKUP($B88,'BDD Prof. Catedra'!$B:$J,9,0) -> 2 | W88: =U88-V88 -> 1 | X88: =V88/T88 -> 0.66666667 | Y88: =IFERROR((((1.96^2*0.5*0.5*($T88-V88))/(V88*($T88-1)))^0.5),"") -> 0.49 | Z88: =IFERROR((((1.65^2*0.5*0.5*($T88-V88))/(V88*($T88-1)))^0.5),"") -> 0.4125 | AA88: Sondeo
A89: 204 | B89: ESPECIALIZACIÓN EN GERENCIA FINANCIERA INTERNACIONAL -BOGOTÁ | C89: INSTITUTO FORUM | D89: 17 | E89: 17 | F89: =VLOOKUP(B89,'BDD Estudiantes Posgrado'!$A$1:$D$200,4,0) -> 17 | G89: =E89-F89 -> 0 | H89: =F89/D89 -> 1 | I89: =IFERROR((((1.96^2*0.5*0.5*($D89-F89))/(F89*($D89-1)))^0.5),"") -> 0 | J89: =IFERROR((((1.65^2*0.5*0.5*($D89-F89))/(F89*($D89-1)))^0.5),"") -> 0 | K89: Encuesta | Q89: =IFERROR((((1.96^2*0.5*0.5*($L89-N89))/(N89*($L89-1)))^0.5),"") | R89: =IFERROR((((1.65^2*0.5*0.5*($L89-N89))/(N89*($L89-1)))^0.5),"") | T89: =VLOOKUP($B89,'BDD Prof. Catedra'!B:G,6,0) -> 4 | U89: 4 | V89: =VLOOKUP($B89,'BDD Prof. Catedra'!$B:$J,9,0) -> 3 | W89: =U89-V89 -> 1 | X89: =V89/T89 -> 0.75 | Y89: =IFERROR((((1.96^2*0.5*0.5*($T89-V89))/(V89*($T89-1)))^0.5),"") -> 0.32666667 | Z89: =IFERROR((((1.65^2*0.5*0.5*($T89-V89))/(V89*($T89-1)))^0.5),"") -> 0.275 | AA89: Sondeo
A90: 140 | B90: ESPECIALIZACIÓN EN GERENCIA ESTRATÉGICA - BOGOTÁ | C90: INSTITUTO FORUM | D90: 35 | E90: 32 | F90: =VLOOKUP(B90,'BDD Estudiantes Posgrado'!$A$1:$D$200,4,0) -> 32 | G90: =E90-F90 -> 0 | H90: =F90/D90 -> 0.91428571 | I90: =IFERROR((((1.96^2*0.5*0.5*($D90-F90))/(F90*($D90-1)))^0.5),"") -> 0.051460293 | J90: =IFERROR((((1.65^2*0.5*0.5*($D90-F90))/(F90*($D90-1)))^0.5),"") -> 0.043321165 | K90: Encuesta | L90: 2 | M90: 2 | N90: =VLOOKUP($B90,'BDD Prof. Planta'!$B$29:$L$201,11,0) -> 2 | O90: =M90-N90 -> 0 | P90: =N90/L90 -> 1 | Q90: 0 | R90: =IFERROR((((1.65^2*0.5*0.5*($L90-N90))/(N90*($L90-1)))^0.5),"") -> 0 | S90: Encuesta | T90: 5 | U90: 5 | V90: =VLOOKUP($B90,'BDD Prof. Catedra'!$B:$J,9,0) -> 5 | W90: =U90-V90 -> 0 | X90: =V90/T90 -> 1 | Y90: =IFERROR((((1.96^2*0.5*0.5*($T90-V90))/(V90*($T90-1)))^0.5),"") -> 0 | Z90: =IFERROR((((1.65^2*0.5*0.5*($T90-V90))/(V90*($T90-1)))^0.5),"") -> 0 | AA90: Encuesta
A91: 209 | B91: ESPECIALIZACIÓN EN GESTIÓN PARA EL DESARROLLO HUMANO EN LA ORGANIZACIÓN - BOGOTÁ | C91: INSTITUTO FORUM | D91: 9 | E91: 9 | F91: =VLOOKUP(B91,'BDD Estudiantes Posgrado'!$A$1:$D$200,4,0) -> 7 | G91: =E91-F91 -> 2 | H91: =F91/D91 -> 0.77777778 | I91: =IFERROR((((1.96^2*0.5*0.5*($D91-F91))/(F91*($D91-1)))^0.5),"") -> 0.18520259 | J91: =IFERROR((((1.65^2*0.5*0.5*($D91-F91))/(F91*($D91-1)))^0.5),"") -> 0.15591035 | K91: Sondeo | L91: =VLOOKUP($B91,'BDD Prof. Planta'!$B$29:$G$162,6,0) -> 1 | M91: 1 | N91: =VLOOKUP($B91,'BDD Prof. Planta'!$B$29:$L$162,11,0) -> 1 | O91: =M91-N91 -> 0 | P91: =N91/L91 -> 1 | Q91: 0 | R91: =IFERROR((((1.65^2*0.5*0.5*($L91-N91))/(N91*($L91-1)))^0.5),0) -> 0 | S91: Encuesta | T91: =VLOOKUP($B91,'BDD Prof. Catedra'!B:G,6,0) -> 2 | U91: 2 | V91: =VLOOKUP($B91,'BDD Prof. Catedra'!$B:$J,9,0) -> 0 | W91: =U91-V91 -> 2 | X91: =V91/T91 -> 0 | Y91: =IFERROR((((1.96^2*0.5*0.5*($T91-V91))/(V91*($T91-1)))^0.5),"") | Z91: =IFERROR((((1.65^2*0.5*0.5*($T91-V91))/(V91*($T91-1)))^0.5),"")
A92: 123 | B92: ESPECIALIZACIÓN EN PEDAGOGÍA E INVESTIGACIÓN EN EL AULA - VIRTUAL | C92: FACULTAD DE EDUCACIÓN | D92: 10 | E92: 10 | F92: =VLOOKUP(B92,'BDD Estudiantes Posgrado'!$A$1:$D$200,4,0) -> 10 | G92: =E92-F92 -> 0 | H92: =F92/D92 -> 1 | I92: =IFERROR((((1.96^2*0.5*0.5*($D92-F92))/(F92*($D92-1)))^0.5),"") -> 0 | J92: =IFERROR((((1.65^2*0.5*0.5*($D92-F92))/(F92*($D92-1)))^0.5),"") -> 0 | K92: Encuesta | L92: =VLOOKUP($B92,'BDD Prof. Planta'!$B$29:$G$162,6,0) -> 1 | M92: 1 | N92: =VLOOKUP($B92,'BDD Prof. Planta'!$B$29:$L$162,11,0) -> 0 | O92: =M92-N92 -> 1 | P92: =N92/L92 -> 0 | Q92: =IFERROR((((1.96^2*0.5*0.5*($L92-N92))/(N92*($L92-1)))^0.5),"") | R92: =IFERROR((((1.65^2*0.5*0.5*($L92-N92))/(N92*($L92-1)))^0.5),"") | T92: =VLOOKUP($B92,'BDD Prof. Catedra'!B:G,6,0) -> 3 | U92: 3 | V92: =VLOOKUP($B92,'BDD Prof. Catedra'!$B:$J,9,0) -> 3 | W92: =U92-V92 -> 0 | X92: =V92/T92 -> 1 | Y92: =IFERROR((((1.96^2*0.5*0.5*($T92-V92))/(V92*($T92-1)))^0.5),"") -> 0 | Z92: =IFERROR((((1.65^2*0.5*0.5*($T92-V92))/(V92*($T92-1)))^0.5),"") -> 0 | AA92: Encuesta
A93: 125 | B93: ESPECIALIZACIÓN EN GESTIÓN PARA EL DESARROLLO HUMANO EN LA ORGANIZACIÓN - VIRTUAL | C93: INSTITUTO FORUM | D93: 21 | E93: 20 | F93: =VLOOKUP(B93,'BDD Estudiantes Posgrado'!$A$1:$D$200,4,0) -> 1 | G93: =E93-F93 -> 19 | H93: =F93/D93 -> 0.047619048 | I93: =IFERROR((((1.96^2*0.5*0.5*($D93-F93))/(F93*($D93-1)))^0.5),"") -> 0.98 | J93: =IFERROR((((1.65^2*0.5*0.5*($D93-F93))/(F93*($D93-1)))^0.5),"") -> 0.825 | K93: Sondeo | R93: =IFERROR((((1.65^2*0.5*0.5*($L93-N93))/(N93*($L93-1)))^0.5),"") | T93: =VLOOKUP($B93,'BDD Prof. Catedra'!B:G,6,0) -> 2 | U93: 2 | V93: =VLOOKUP($B93,'BDD Prof. Catedra'!$B:$J,9,0) -> 2 | W93: =U93-V93 -> 0 | X93: =V93/T93 -> 1 | Y93: =IFERROR((((1.96^2*0.5*0.5*($T93-V93))/(V93*($T93-1)))^0.5),"") -> 0 | Z93: =IFERROR((((1.65^2*0.5*0.5*($T93-V93))/(V93*($T93-1)))^0.5),"") -> 0 | AA93: Encuesta
A94: 124 | B94: ESPECIALIZACIÓN EN GERENCIA ESTRATÉGICA - VIRTUAL | C94: INSTITUTO FORUM | D94: 49 | E94: 45 | F94: =VLOOKUP(B94,'BDD Estudiantes Posgrado'!$A$1:$D$200,4,0) -> 45 | G94: =E94-F94 -> 0 | H94: =F94/D94 -> 0.91836735 | I94: =IFERROR((((1.96^2*0.5*0.5*($D94-F94))/(F94*($D94-1)))^0.5),"") -> 0.042172485 | J94: =IFERROR((((1.65^2*0.5*0.5*($D94-F94))/(F94*($D94-1)))^0.5),"") -> 0.035502347 | K94: Encuesta | L94: =VLOOKUP($B94,'BDD Prof. Planta'!$B$29:$G$162,6,0) -> 2 | M94: 2 | N94: =VLOOKUP($B94,'BDD Prof. Planta'!$B$29:$L$162,11,0) -> 2 | O94: =M94-N94 -> 0 | P94: =N94/L94 -> 1 | Q94: 0 | R94: =IFERROR((((1.65^2*0.5*0.5*($L94-N94))/(N94*($L94-1)))^0.5),"") -> 0 | S94: Encuesta | T94: =VLOOKUP($B94,'BDD Prof. Catedra'!B:G,6,0) -> 6 | U94: 6 | V94: =VLOOKUP($B94,'BDD Prof. Catedra'!$B:$J,9,0) -> 6 | W94: =U94-V94 -> 0 | X94: =V94/T94 -> 1 | Y94: =IFERROR((((1.96^2*0.5*0.5*($T94-V94))/(V94*($T94-1)))^0.5),"") -> 0 | Z94: =IFERROR((((1.65^2*0.5*0.5*($T94-V94))/(V94*($T94-1)))^0.5),"") -> 0 | AA94: Encuesta
A95: 126 | B95: ESPECIALIZACIÓN EN GERENCIA COMERCIAL VIRTUAL | C95: INSTITUTO FORUM | D95: 44 | E95: 40 | F95: =VLOOKUP(B95,'BDD Estudiantes Posgrado'!$A$1:$D$200,4,0) -> 24 | G95: =E95-F95 -> 16 | H95: =F95/D95 -> 0.54545455 | I95: =IFERROR((((1.96^2*0.5*0.5*($D95-F95))/(F95*($D95-1)))^0.5),"") -> 0.13642728 | J95: =IFERROR((((1.65^2*0.5*0.5*($D95-F95))/(F95*($D95-1)))^0.5),"") -> 0.1148495 | K95: Sondeo | L95: =VLOOKUP($B95,'BDD Prof. Planta'!$B$29:$G$162,6,0) -> 1 | M95: 1 | N95: =VLOOKUP($B95,'BDD Prof. Planta'!$B$29:$L$162,11,0) -> 0 | O95: =M95-N95 -> 1 | P95: =N95/L95 -> 0 | Q95: =IFERROR((((1.96^2*0.5*0.5*($L95-N95))/(N95*($L95-1)))^0.5),"") | R95: =IFERROR((((1.65^2*0.5*0.5*($L95-N95))/(N95*($L95-1)))^0.5),"") | T95: =VLOOKUP($B95,'BDD Prof. Catedra'!B:G,6,0) -> 2 | U95: 2 | V95: =VLOOKUP($B95,'BDD Prof. Catedra'!$B:$J,9,0) -> 1 | W95: =U95-V95 -> 1 | X95: =V95/T95 -> 0.5 | Y95: =IFERROR((((1.96^2*0.5*0.5*($T95-V95))/(V95*($T95-1)))^0.5),"") -> 0.98 | Z95: =IFERROR((((1.65^2*0.5*0.5*($T95-V95))/(V95*($T95-1)))^0.5),"") -> 0.825 | AA95: Sondeo
A96: 128 | B96: ESPECIALIZACIÓN EN GERENCIA COMERCIAL IBAGUÉ | C96: INSTITUTO FORUM | Q96: =IFERROR((((1.96^2*0.5*0.5*($L96-N96))/(N96*($L96-1)))^0.5),"") | R96: =IFERROR((((1.65^2*0.5*0.5*($L96-N96))/(N96*($L96-1)))^0.5),"") | T96: =VLOOKUP($B96,'BDD Prof. Catedra'!B:G,6,0) -> 3 | U96: 3 | V96: =VLOOKUP($B96,'BDD Prof. Catedra'!$B:$J,9,0) -> 0 | W96: =U96-V96 -> 3 | X96: =V96/T96 -> 0 | Y96: =IFERROR((((1.96^2*0.5*0.5*($T96-V96))/(V96*($T96-1)))^0.5),"") | Z96: =IFERROR((((1.65^2*0.5*0.5*($T96-V96))/(V96*($T96-1)))^0.5),"")
A97: 129 | B97: ESPECIALIZACIÓN EN GERENCIA COMERCIAL MEDELLÍN | C97: INSTITUTO FORUM | D97: 22 | E97: 21 | F97: =VLOOKUP(B97,'BDD Estudiantes Posgrado'!$A$1:$D$200,4,0) -> 11 | G97: =E97-F97 -> 10 | H97: =F97/D97 -> 0.5 | I97: =IFERROR((((1.96^2*0.5*0.5*($D97-F97))/(F97*($D97-1)))^0.5),"") -> 0.21385353 | J97: =IFERROR((((1.65^2*0.5*0.5*($D97-F97))/(F97*($D97-1)))^0.5),"") -> 0.18002976 | K97: Sondeo | Q97: =IFERROR((((1.96^2*0.5*0.5*($L97-N97))/(N97*($L97-1)))^0.5),"") | R97: =IFERROR((((1.65^2*0.5*0.5*($L97-N97))/(N97*($L97-1)))^0.5),"") | T97: =VLOOKUP($B97,'BDD Prof. Catedra'!B:G,6,0) -> 3 | U97: 3 | V97: =VLOOKUP($B97,'BDD Prof. Catedra'!$B:$J,9,0) -> 3 | W97: =U97-V97 -> 0 | X97: =V97/T97 -> 1 | Y97: =IFERROR((((1.96^2*0.5*0.5*($T97-V97))/(V97*($T97-1)))^0.5),"") -> 0 | Z97: =IFERROR((((1.65^2*0.5*0.5*($T97-V97))/(V97*($T97-1)))^0.5),"") -> 0 | AA97: Encuesta
A98: 138 | B98: ESPECIALIZACIÓN EN GERENCIA COMERCIAL BARRANQUILLA | C98: INSTITUTO FORUM | D98: 12 | E98: 12 | F98: =VLOOKUP(B98,'BDD Estudiantes Posgrado'!$A$1:$D$200,4,0) -> 12 | G98: =E98-F98 -> 0 | H98: =F98/D98 -> 1 | I98: =IFERROR((((1.96^2*0.5*0.5*($D98-F98))/(F98*($D98-1)))^0.5),"") -> 0 | J98: =IFERROR((((1.65^2*0.5*0.5*($D98-F98))/(F98*($D98-1)))^0.5),"") -> 0 | K98: Encuesta | Q98: =IFERROR((((1.96^2*0.5*0.5*($L98-N98))/(N98*($L98-1)))^0.5),"") | R98: =IFERROR((((1.65^2*0.5*0.5*($L98-N98))/(N98*($L98-1)))^0.5),"") | T98: =VLOOKUP($B98,'BDD Prof. Catedra'!B:G,6,0) -> 3 | U98: 3 | V98: =VLOOKUP($B98,'BDD Prof. Catedra'!$B:$J,9,0) -> 3 | W98: =U98-V98 -> 0 | X98: =V98/T98 -> 1 | Y98: =IFERROR((((1.96^2*0.5*0.5*($T98-V98))/(V98*($T98-1)))^0.5),"") -> 0 | Z98: =IFERROR((((1.65^2*0.5*0.5*($T98-V98))/(V98*($T98-1)))^0.5),"") -> 0 | AA98: Encuesta
A99: 127 | B99: ESPECIALIZACIÓN EN GERENCIA COMERCIAL BUCARAMANGA | C99: INSTITUTO FORUM | D99: 41 | E99: 39 | F99: =VLOOKUP(B99,'BDD Estudiantes Posgrado'!$A$1:$D$200,4,0) -> 39 | G99: =E99-F99 -> 0 | H99: =F99/D99 -> 0.95121951 | I99: =IFERROR((((1.96^2*0.5*0.5*($D99-F99))/(F99*($D99-1)))^0.5),"") -> 0.035089629 | J99: =IFERROR((((1.65^2*0.5*0.5*($D99-F99))/(F99*($D99-1)))^0.5),"") -> 0.029539739 | K99: Encuesta | L99: =VLOOKUP($B99,'BDD Prof. Planta'!$B$29:$G$162,6,0) -> 2 | M99: 2 | N99: =VLOOKUP($B99,'BDD Prof. Planta'!$B$29:$L$162,11,0) -> 2 | O99: =M99-N99 -> 0 | P99: =N99/L99 -> 1 | Q99: =IFERROR((((1.96^2*0.5*0.5*($L99-N99))/(N99*($L99-1)))^0.5),"") -> 0 | R99: =IFERROR((((1.65^2*0.5*0.5*($L99-N99))/(N99*($L99-1)))^0.5),"") -> 0 | S99: Encuesta | T99: =VLOOKUP($B99,'BDD Prof. Catedra'!B:G,6,0) -> 3 | U99: 3 | V99: =VLOOKUP($B99,'BDD Prof. Catedra'!$B:$J,9,0) -> 3 | W99: =U99-V99 -> 0 | X99: =V99/T99 -> 1 | Y99: =IFERROR((((1.96^2*0.5*0.5*($T99-V99))/(V99*($T99-1)))^0.5),"") -> 0 | Z99: =IFERROR((((1.65^2*0.5*0.5*($T99-V99))/(V99*($T99-1)))^0.5),"") -> 0 | AA99: Encuesta
A100: 139 | B100: ESPECIALIZACIÓN EN GERENCIA ESTRATÉGICA BARRANQUILLA | C100: INSTITUTO FORUM | D100: 12 | E100: 12 | F100: =VLOOKUP(B100,'BDD Estudiantes Posgrado'!$A$1:$D$200,4,0) -> 12 | G100: =E100-F100 -> 0 | H100: =F100/D100 -> 1 | I100: =IFERROR((((1.96^2*0.5*0.5*($D100-F100))/(F100*($D100-1)))^0.5),"") -> 0 | J100: =IFERROR((((1.65^2*0.5*0.5*($D100-F100))/(F100*($D100-1)))^0.5),"") -> 0 | K100: Encuesta | L100: =VLOOKUP($B100,'BDD Prof. Planta'!$B$29:$G$162,6,0) -> 2 | M100: 2 | N100: =VLOOKUP($B100,'BDD Prof. Planta'!$B$29:$L$162,11,0) -> 2 | O100: =M100-N100 -> 0 | P100: =N100/L100 -> 1 | Q100: 0 | R100: =IFERROR((((1.65^2*0.5*0.5*($L100-N100))/(N100*($L100-1)))^0.5),"") -> 0 | S100: Encuesta | T100: =VLOOKUP($B100,'BDD Prof. Catedra'!B:G,6,0) -> 6 | U100: 6 | V100: =VLOOKUP($B100,'BDD Prof. Catedra'!$B:$J,9,0) -> 6 | W100: =U100-V100 -> 0 | X100: =V100/T100 -> 1 | Y100: =IFERROR((((1.96^2*0.5*0.5*($T100-V100))/(V100*($T100-1)))^0.5),"") -> 0 | Z100: =IFERROR((((1.65^2*0.5*0.5*($T100-V100))/(V100*($T100-1)))^0.5),"") -> 0 | AA100: Encuesta
...

Sheet Tabla dinamica Reporte Profesor
A1: ESTATUS | B1: Replicado
A3: Cuenta de PROGRAMA | B3: Etiquetas de columna
A4: Etiquetas de fila | B4: Cátedra | C4: Planta | D4: Total general | F4: Etiquetas de fila | G4: Cátedra | H4: Planta | L4: Cuenta de ESTATUS | M4: Etiquetas de columna
A5: Ciencias Políticas | B5: 1 | D5: 1 | F5: Ciencias Políticas | G5: 1 | I5: =VLOOKUP(F5,'BDD Prof. Planta'!$A$2:$M$177,13,0) -> 8 | L5: Etiquetas de fila | M5: Cátedra | N5: Planta | O5: Total general
A6: Comunicación Audiovisual y Multimedios | B6: 1 | C6: 2 | D6: 3 | F6: Comunicación Audiovisual y Multimedios | G6: 1 | H6: 2 | I6: =VLOOKUP(F6,'BDD Prof. Planta'!$A$2:$M$177,13,0) -> 16 | L6: Completa | M6: 681 | N6: 542 | O6: 1223
A7: Comunicación Corporativa | B7: 2 | C7: 4 | D7: 6 | F7: Comunicación Corporativa | G7: 2 | H7: 4 | I7: =VLOOKUP(F7,'BDD Prof. Planta'!$A$2:$M$177,13,0) -> 14 | L7: Incompleta | M7: 279 | N7: 90 | O7: 369
A8: Comunicación Social y Periodismo | B8: 3 | C8: 3 | D8: 6 | F8: Comunicación Social y Periodismo | G8: 3 | H8: 3 | I8: =VLOOKUP(F8,'BDD Prof. Planta'!$A$2:$M$177,13,0) -> 14 | L8: No diligenciada | M8: 1 | O8: 1
A9: Derecho | C9: 1 | D9: 1 | F9: Derecho | H9: 1 | I9: =VLOOKUP(F9,'BDD Prof. Planta'!$A$2:$M$177,13,0) -> 26 | L9: Replicado | M9: 60 | N9: 38 | O9: 98
A10: ESPECIALIZACIÓN EN GERENCIA COMERCIAL BARRANQUILLA | B10: 1 | D10: 1 | F10: ESPECIALIZACIÓN EN FINANZAS CORPORATIVAS CHÍA | G10: 1 | I10: =VLOOKUP(F10,'BDD Prof. Planta'!$A$2:$M$177,13,0) -> 1 | L10: Total general | M10: 1021 | N10: 670 | O10: 1691
A11: ESPECIALIZACIÓN EN GERENCIA DEL SERVICIO CHÍA | B11: 3 | D11: 3 | F11: ESPECIALIZACIÓN EN GERENCIA COMERCIAL BARRANQUILLA | G11: 1 | I11: =VLOOKUP(F11,'BDD Prof. Planta'!$A$2:$M$177,13,0) -> 0
A12: ESPECIALIZACIÓN EN GERENCIA ESTRATÉGICA - BOGOTÁ | B12: 5 | C12: 2 | D12: 7 | F12: ESPECIALIZACIÓN EN GERENCIA DE PROYECTOS CON ENFOQUE EN HABILIDADES DIRECTIVAS CHÍA | G12: 1 | I12: =VLOOKUP(F12,'BDD Prof. Planta'!$A$2:$M$177,13,0) -> 1
A13: ESPECIALIZACIÓN EN GERENCIA ESTRATÉGICA - VIRTUAL | B13: 5 | C13: 2 | D13: 7 | F13: ESPECIALIZACIÓN EN GERENCIA DEL SERVICIO CHÍA | G13: 3 | I13: =VLOOKUP(F13,'BDD Prof. Planta'!$A$2:$M$177,13,0) -> 0
A14: ESPECIALIZACIÓN EN GERENCIA ESTRATÉGICA BARRANQUILLA | B14: 4 | C14: 1 | D14: 5 | F14: ESPECIALIZACIÓN EN GERENCIA ESTRATÉGICA - BOGOTÁ | G14: 5 | H14: 2 | I14: =VLOOKUP(F14,'BDD Prof. Planta'!$A$2:$M$177,13,0) -> 2
A15: ESPECIALIZACIÓN EN GERENCIA ESTRATÉGICA BUCARAMANGA | B15: 5 | C15: 2 | D15: 7 | F15: ESPECIALIZACIÓN EN GERENCIA ESTRATÉGICA - VIRTUAL | G15: 5 | H15: 2 | I15: =VLOOKUP(F15,'BDD Prof. Planta'!$A$2:$M$177,13,0) -> 2
A16: ESPECIALIZACIÓN EN GERENCIA ESTRATÉGICA CHÍA | B16: 4 | C16: 2 | D16: 6 | F16: ESPECIALIZACIÓN EN GERENCIA ESTRATÉGICA BARRANQUILLA | G16: 4 | H16: 1 | I16: =VLOOKUP(F16,'BDD Prof. Planta'!$A$2:$M$177,13,0) -> 2
A17: ESPECIALIZACIÓN EN GERENCIA ESTRATÉGICA DE MARCA CHÍA | B17: 1 | D17: 1 | F17: ESPECIALIZACIÓN EN GERENCIA ESTRATÉGICA BUCARAMANGA | G17: 5 | H17: 2 | I17: =VLOOKUP(F17,'BDD Prof. Planta'!$A$2:$M$177,13,0) -> 2
A18: ESPECIALIZACIÓN EN GERENCIA ESTRATÉGICA IBAGUÉ | B18: 3 | C18: 2 | D18: 5 | F18: ESPECIALIZACIÓN EN GERENCIA ESTRATÉGICA CHÍA | G18: 4 | H18: 2 | I18: =VLOOKUP(F18,'BDD Prof. Planta'!$A$2:$M$177,13,0) -> 2
A19: ESPECIALIZACIÓN EN GERENCIA ESTRATÉGICA MEDELLÍN | B19: 5 | C19: 1 | D19: 6 | F19: ESPECIALIZACIÓN EN GERENCIA ESTRATÉGICA IBAGUÉ | G19: 3 | H19: 2 | I19: =VLOOKUP(F19,'BDD Prof. Planta'!$A$2:$M$177,13,0) -> 2
A20: ESPECIALIZACIÓN EN GERENCIA ESTRATÉGICA VILLAVICENCIO | B20: 4 | C20: 2 | D20: 6 | F20: ESPECIALIZACIÓN EN GERENCIA ESTRATÉGICA MEDELLÍN | G20: 5 | H20: 1 | I20: =VLOOKUP(F20,'BDD Prof. Planta'!$A$2:$M$177,13,0) -> 2
A21: ESPECIALIZACIÓN EN GERENCIA LOGÍSTICA - BOGOTÁ | B21: 1 | D21: 1 | F21: ESPECIALIZACIÓN EN GERENCIA ESTRATÉGICA VILLAVICENCIO | G21: 4 | H21: 2 | I21: =VLOOKUP(F21,'BDD Prof. Planta'!$A$2:$M$177,13,0) -> 2
A22: ESPECIALIZACIÓN EN GERENCIA LOGÍSTICA CHÍA | C22: 2 | D22: 2 | F22: ESPECIALIZACIÓN EN GERENCIA FINANCIERA INTERNACIONAL CHÍA | G22: 2 | I22: =VLOOKUP(F22,'BDD Prof. Planta'!$A$2:$M$177,13,0) -> 1
A23: ESPECIALIZACIÓN EN GESTIÓN PARA EL DESARROLLO HUMANO EN LA ORGANIZACIÓN - VIRTUAL | B23: 2 | D23: 2 | F23: ESPECIALIZACIÓN EN GERENCIA LOGÍSTICA - BOGOTÁ | G23: 1 | I23: =VLOOKUP(F23,'BDD Prof. Planta'!$A$2:$M$177,13,0) -> 0
A24: ESPECIALIZACIÓN EN GESTIÓN PARA EL DESARROLLO HUMANO EN LA ORGANIZACIÓN CHÍA | C24: 1 | D24: 1 | F24: ESPECIALIZACIÓN EN GERENCIA LOGÍSTICA CHÍA | H24: 2 | I24: =VLOOKUP(F24,'BDD Prof. Planta'!$A$2:$M$177,13,0) -> 2
A25: ESPECIALIZACIÓN EN PSICOLOGÍA EDUCATIVA | C25: 1 | D25: 1 | F25: ESPECIALIZACIÓN EN GESTIÓN PARA EL DESARROLLO HUMANO EN LA ORGANIZACIÓN - VIRTUAL | G25: 2
A26: ESPECIALIZACIÓN EN SEGUROS Y SEGURIDAD SOCIAL | B26: 1 | D26: 1 | F26: ESPECIALIZACIÓN EN GESTIÓN PARA EL DESARROLLO HUMANO EN LA ORGANIZACIÓN CHÍA | H26: 1 | I26: =VLOOKUP(F26,'BDD Prof. Planta'!$A$2:$M$177,13,0) -> 1
A27: Licenciatura en Ciencias Naturales | B27: 2 | D27: 2 | F27: ESPECIALIZACIÓN EN PEDAGOGÍA E INVESTIGACIÓN EN EL AULA - VIRTUAL | G27: 1 | I27: =VLOOKUP(F27,'BDD Prof. Planta'!$A$2:$M$177,13,0) -> 0
A28: Licenciatura en Educación Infantil | C28: 1 | D28: 1 | F28: ESPECIALIZACIÓN EN PSICOLOGÍA EDUCATIVA | H28: 1 | I28: =VLOOKUP(F28,'BDD Prof. Planta'!$A$2:$M$177,13,0) -> 2
A29: MAESTRÍA EN ANALÍTICA APLICADA | B29: 1 | D29: 1 | F29: ESPECIALIZACIÓN EN SEGUROS Y SEGURIDAD SOCIAL | G29: 1 | I29: =VLOOKUP(F29,'BDD Prof. Planta'!$A$2:$M$177,13,0) -> 0
A30: MAESTRÍA EN DESARROLLO INFANTIL | B30: 1 | D30: 1 | F30: Licenciatura en Ciencias Naturales | G30: 2 | I30: =VLOOKUP(F30,'BDD Prof. Planta'!$A$2:$M$177,13,0) -> 7
A31: MAESTRÍA EN DIRECCIÓN Y GESTIÓN DE INSTITUCIONES EDUCATIVAS | B31: 1 | D31: 1 | F31: Licenciatura en Educación Infantil | H31: 1 | I31: =VLOOKUP(F31,'BDD Prof. Planta'!$A$2:$M$177,13,0) -> 8
A32: MAESTRÍA EN DISEÑO Y GESTIÓN DE PROCESOS | B32: 1 | D32: 1 | F32: MAESTRÍA EN ANALÍTICA APLICADA | G32: 2 | I32: =VLOOKUP(F32,'BDD Prof. Planta'!$A$2:$M$177,13,0) -> 7
A33: MAESTRÍA EN ENFERMERÍA PRESENCIAL | C33: 1 | D33: 1 | F33: MAESTRÍA EN DESARROLLO INFANTIL | G33: 1 | I33: =VLOOKUP(F33,'BDD Prof. Planta'!$A$2:$M$177,13,0) -> 1
A34: MAESTRÍA EN ENFERMERÍA VIRTUAL | C34: 2 | D34: 2 | F34: MAESTRÍA EN DIRECCIÓN Y GESTIÓN DE INSTITUCIONES EDUCATIVAS | G34: 1 | I34: =VLOOKUP(F34,'BDD Prof. Planta'!$A$2:$M$177,13,0) -> 1
A35: MAESTRÍA EN FISIOTERAPIA - VIRTUAL | C35: 1 | D35: 1 | F35: MAESTRÍA EN DISEÑO Y GESTIÓN DE PROCESOS | G35: 1 | I35: =VLOOKUP(F35,'BDD Prof. Planta'!$A$2:$M$177,13,0) -> 20
A36: MAESTRÍA EN GERENCIA INTERNACIONAL | B36: 1 | D36: 1 | F36: MAESTRÍA EN ENFERMERÍA PRESENCIAL | H36: 1 | I36: =VLOOKUP(F36,'BDD Prof. Planta'!$A$2:$M$177,13,0) -> 7
A37: MAESTRÍA EN GERENCIA Y DESARROLLO DE PERSONAS | B37: 1 | C37: 2 | D37: 3 | F37: MAESTRÍA EN ENFERMERÍA VIRTUAL | H37: 2 | I37: =VLOOKUP(F37,'BDD Prof. Planta'!$A$2:$M$177,13,0) -> 7
A38: MAESTRÍA EN INNOVACIÓN EDUCATIVA MEDIADA POR TIC - VIRTUAL | B38: 1 | D38: 1 | F38: MAESTRÍA EN FISIOTERAPIA - VIRTUAL | H38: 1 | I38: =VLOOKUP(F38,'BDD Prof. Planta'!$A$2:$M$177,13,0) -> 9
A39: MAESTRÍA EN PEDAGOGÍA - NEIVA | B39: 1 | D39: 1 | F39: MAESTRÍA EN GERENCIA DE LA INNOVACIÓN | G39: 1 | I39: =VLOOKUP(F39,'BDD Prof. Planta'!$A$2:$M$177,13,0) -> 4
A40: MAESTRÍA EN PSICOLOGÍA | C40: 1 | D40: 1 | F40: MAESTRÍA EN GERENCIA INTERNACIONAL | G40: 1 | I40: =VLOOKUP(F40,'BDD Prof. Planta'!$A$2:$M$177,13,0) -> 2
A41: MAESTRÍA EN PSICOLOGÍA CLÍNICA DE LA NIÑEZ Y LA ADOLESCENCIA | C41: 1 | D41: 1 | F41: MAESTRÍA EN GERENCIA Y DESARROLLO DE PERSONAS | G41: 3 | H41: 2 | I41: =VLOOKUP(F41,'BDD Prof. Planta'!$A$2:$M$177,13,0) -> 4
A42: Total general | B42: 61 | C42: 37 | D42: 98 | F42: MAESTRÍA EN INNOVACIÓN EDUCATIVA MEDIADA POR TIC - VIRTUAL | G42: 1 | H42: 1 | I42: =VLOOKUP(F42,'BDD Prof. Planta'!$A$2:$M$177,13,0) -> 4
F43: MAESTRÍA EN PEDAGOGÍA - NEIVA | G43: 2 | I43: =VLOOKUP(F43,'BDD Prof. Planta'!$A$2:$M$177,13,0) -> 0
F44: MAESTRÍA EN PSICOLOGÍA | H44: 1 | I44: =VLOOKUP(F44,'BDD Prof. Planta'!$A$2:$M$177,13,0) -> 8
F45: MAESTRÍA EN PSICOLOGÍA CLÍNICA DE LA NIÑEZ Y LA ADOLESCENCIA | H45: 1 | I45: =VLOOKUP(F45,'BDD Prof. Planta'!$A$2:$M$177,13,0) -> 3
F46: Total general | G46: 70 | H46: 38
A51: ESTATUS | B51: Completa
A53: Cuenta de PROGRAMA | B53: Etiquetas de columna
A54: Etiquetas de fila | B54: Cátedra | C54: Planta | D54: Total general | F54: Etiquetas de fila | G54: Cátedra | H54: Planta | I54: Hoja BDD Prof. Catedra
A55: ADMINISTRACIÓN Y ORGANIZACIONES | B55: 13 | C55: 8 | D55: 21 | F55: ADMINISTRACIÓN Y ORGANIZACIONES | G55: 13 | H55: 8 | I55: =VLOOKUP(F55,'BDD Prof. Catedra'!$A$2:$C$176,3,0) -> 13 | J55: =I55-G55 -> 0
A56: ARTES CULINARIAS Y CIENCIAS DE LA ALIMENTACIÓN | B56: 13 | C56: 7 | D56: 20 | F56: ARTES CULINARIAS Y CIENCIAS DE LA ALIMENTACIÓN | G56: 13 | H56: 7 | I56: =VLOOKUP(F56,'BDD Prof. Catedra'!$A$2:$C$176,3,0) -> 13 | J56: =I56-G56 -> 0
A57: Centro de tecnologias parta la academia | B57: 5 | C57: 2 | D57: 7 | F57: Centro de tecnologias parta la academia | G57: 5 | H57: 2 | I57: =VLOOKUP(F57,'BDD Prof. Catedra'!$A$2:$C$176,3,0) -> #N/A | J57: =I57-G57 -> #N/A
A58: Ciencia de Datos | B58: 4 | C58: 1 | D58: 5 | F58: Ciencia de Datos | G58: 4 | H58: 1 | I58: =VLOOKUP(F58,'BDD Prof. Catedra'!$A$2:$C$176,3,0) -> 4 | J58: =I58-G58 -> 0
A59: Ciencias Políticas | B59: 7 | C59: 8 | D59: 15 | F59: Ciencias Políticas | G59: 7 | H59: 8 | I59: =VLOOKUP(F59,'BDD Prof. Catedra'!$A$2:$C$176,3,0) -> 7 | J59: =I59-G59 -> 0
A60: Comunicación Audiovisual y Multimedios | B60: 35 | C60: 14 | D60: 49 | F60: Comunicación Audiovisual y Multimedios | G60: 35 | H60: 14 | I60: =VLOOKUP(F60,'BDD Prof. Catedra'!$A$2:$C$176,3,0) -> 35 | J60: =I60-G60 -> 0
A61: Comunicación Corporativa | B61: 19 | C61: 10 | D61: 29 | F61: Comunicación Corporativa | G61: 19 | H61: 10 | I61: =VLOOKUP(F61,'BDD Prof. Catedra'!$A$2:$C$176,3,0) -> 19 | J61: =I61-G61 -> 0
A62: Comunicación Social y Periodismo | B62: 25 | C62: 11 | D62: 36 | F62: Comunicación Social y Periodismo | G62: 25 | H62: 11 | I62: =VLOOKUP(F62,'BDD Prof. Catedra'!$A$2:$C$176,3,0) -> 25 | J62: =I62-G62 -> 0
A63: Core curriculum persona y cultura | B63: 8 | C63: 11 | D63: 19 | F63: Core curriculum persona y cultura | G63: 8 | H63: 11 | I63: =VLOOKUP(F63,'BDD Prof. Catedra'!$A$2:$C$176,3,0) -> 8 | J63: =I63-G63 -> 0
A64: Departamento de lenguas y culturas extranjeras | B64: 22 | C64: 20 | D64: 42 | F64: Departamento de lenguas y culturas extranjeras | G64: 22 | H64: 20 | I64: =VLOOKUP(F64,'BDD Prof. Catedra'!$A$2:$C$176,3,0) -> #N/A | J64: =I64-G64 -> #N/A
A65: Derecho | B65: 24 | C65: 25 | D65: 49 | F65: Derecho | G65: 24 | H65: 25 | I65: =VLOOKUP(F65,'BDD Prof. Catedra'!$A$2:$C$176,3,0) -> 24 | J65: =I65-G65 -> 0
A66: DOCTORADO EN ADMINISTRACIÓN DE ORGANIZACIONES | C66: 8 | D66: 8 | F66: DOCTORADO EN ADMINISTRACIÓN DE ORGANIZACIONES | H66: 8 | J66: =I66-G66 -> 0
A67: DOCTORADO EN BIOCIENCIAS | B67: 1 | C67: 6 | D67: 7 | F67: DOCTORADO EN BIOCIENCIAS | G67: 1 | H67: 6 | I67: =VLOOKUP(F67,'BDD Prof. Catedra'!$A$2:$C$176,3,0) -> 1 | J67: =I67-G67 -> 0
A68: DOCTORADO EN COMUNICACIÓN | C68: 4 | D68: 4 | F68: DOCTORADO EN COMUNICACIÓN | H68: 4 | I68: =VLOOKUP(F68,'BDD Prof. Catedra'!$A$2:$C$176,3,0) -> 0 | J68: =I68-G68 -> 0
A69: DOCTORADO EN DERECHO | C69: 3 | D69: 3 | F69: DOCTORADO EN DERECHO | H69: 3 | I69: =VLOOKUP(F69,'BDD Prof. Catedra'!$A$2:$C$176,3,0) -> 0 | J69: =I69-G69 -> 0
A70: DOCTORADO EN EDUCACIÓN | C70: 5 | D70: 5 | F70: DOCTORADO EN EDUCACIÓN | H70: 5 | I70: =VLOOKUP(F70,'BDD Prof. Catedra'!$A$2:$C$176,3,0) -> 0 | J70: =I70-G70 -> 0
A71: DOCTORADO EN ENFERMERÍA | B71: 2 | C71: 4 | D71: 6 | F71: DOCTORADO EN ENFERMERÍA | G71: 2 | H71: 4 | I71: =VLOOKUP(F71,'BDD Prof. Catedra'!$A$2:$C$176,3,0) -> 2 | J71: =I71-G71 -> 0
A72: DOCTORADO EN INGENIERÍA | C72: 5 | D72: 5 | F72: DOCTORADO EN INGENIERÍA | H72: 5 | I72: =VLOOKUP(F72,'BDD Prof. Catedra'!$A$2:$C$176,3,0) -> 0 | J72: =I72-G72 -> 0
A73: DOCTORADO EN INNOVACIÓN EDUCATIVA CON USO DE TIC | B73: 2 | C73: 4 | D73: 6 | F73: DOCTORADO EN INNOVACIÓN EDUCATIVA CON USO DE TIC | G73: 2 | H73: 4 | I73: =VLOOKUP(F73,'BDD Prof. Catedra'!$A$2:$C$176,3,0) -> 2 | J73: =I73-G73 -> 0
A74: DOCTORADO EN LOGÍSTICA Y GESTIÓN DE CADENA DE SUMINISTRO | C74: 2 | D74: 2 | F74: DOCTORADO EN LOGÍSTICA Y GESTIÓN DE CADENA DE SUMINISTRO | H74: 2 | J74: =I74-G74 -> 0
A75: DOCTORADO EN PSICOLOGÍA | B75: 1 | C75: 5 | D75: 6 | F75: DOCTORADO EN PSICOLOGÍA | G75: 1 | H75: 5 | I75: =VLOOKUP(F75,'BDD Prof. Catedra'!$A$2:$C$176,3,0) -> 1 | J75: =I75-G75 -> 0
A76: ECONOMÍA | B76: 10 | C76: 7 | D76: 17 | F76: ECONOMÍA | G76: 10 | H76: 7 | I76: =VLOOKUP(F76,'BDD Prof. Catedra'!$A$2:$C$176,3,0) -> 10 | J76: =I76-G76 -> 0
A77: Enfermería | B77: 5 | C77: 14 | D77: 19 | F77: Enfermería | G77: 5 | H77: 14 | I77: =VLOOKUP(F77,'BDD Prof. Catedra'!$A$2:$C$176,3,0) -> 5 | J77: =I77-G77 -> 0
A78: ESPECIALIZACIÓN EN ANESTESIOLOGÍA Y MEDICINA PERIOPERATORIA | C78: 1 | D78: 1 | F78: ESPECIALIZACIÓN EN ANESTESIOLOGÍA Y MEDICINA PERIOPERATORIA | H78: 1 | I78: =VLOOKUP(F78,'BDD Prof. Catedra'!$A$2:$C$176,3,0) -> 0 | J78: =I78-G78 -> 0
A79: ESPECIALIZACIÓN EN CIRUGÍA GENERAL | B79: 2 | C79: 3 | D79: 5 | F79: ESPECIALIZACIÓN EN CIRUGÍA GENERAL | G79: 2 | H79: 3 | I79: =VLOOKUP(F79,'BDD Prof. Catedra'!$A$2:$C$176,3,0) -> 2 | J79: =I79-G79 -> 0
A80: ESPECIALIZACIÓN EN CONTRATACIÓN ESTATAL | B80: 3 | C80: 1 | D80: 4 | F80: ESPECIALIZACIÓN EN CONTRATACIÓN ESTATAL | G80: 3 | H80: 1 | I80: =VLOOKUP(F80,'BDD Prof. Catedra'!$A$2:$C$176,3,0) -> 3 | J80: =I80-G80 -> 0
A81: ESPECIALIZACIÓN EN CONTRATACIÓN ESTATAL - IBAGUÉ | B81: 2 | D81: 2 | F81: ESPECIALIZACIÓN EN CONTRATACIÓN ESTATAL - IBAGUÉ | G81: 2 | I81: =VLOOKUP(F81,'BDD Prof. Catedra'!$A$2:$C$176,3,0) -> 2 | J81: =I81-G81 -> 0
A82: ESPECIALIZACIÓN EN CONTRATACIÓN ESTATAL - NEIVA | B82: 3 | D82: 3 | F82: ESPECIALIZACIÓN EN CONTRATACIÓN ESTATAL - NEIVA | G82: 3 | I82: =VLOOKUP(F82,'BDD Prof. Catedra'!$A$2:$C$176,3,0) -> 3 | J82: =I82-G82 -> 0
A83: ESPECIALIZACIÓN EN CUIDADO INTENSIVO PEDIÁTRICO | B83: 1 | C83: 1 | D83: 2 | F83: ESPECIALIZACIÓN EN CUIDADO INTENSIVO PEDIÁTRICO | G83: 1 | H83: 1 | I83: =VLOOKUP(F83,'BDD Prof. Catedra'!$A$2:$C$176,3,0) -> 1 | J83: =I83-G83 -> 0
A84: ESPECIALIZACIÓN EN DERECHO TRIBUTARIO | B84: 7 | D84: 7 | F84: ESPECIALIZACIÓN EN DERECHO TRIBUTARIO | G84: 7 | I84: =VLOOKUP(F84,'BDD Prof. Catedra'!$A$2:$C$176,3,0) -> 7 | J84: =I84-G84 -> 0
A85: ESPECIALIZACIÓN EN DERECHO Y EMPRESA | B85: 3 | D85: 3 | F85: ESPECIALIZACIÓN EN DERECHO Y EMPRESA | G85: 3 | I85: =VLOOKUP(F85,'BDD Prof. Catedra'!$A$2:$C$176,3,0) -> 3 | J85: =I85-G85 -> 0
A86: ESPECIALIZACIÓN EN EMPRENDIMIENTO Y NEGOCIOS DIGITALES- CHÍA | B86: 5 | D86: 5 | F86: ESPECIALIZACIÓN EN EMPRENDIMIENTO Y NEGOCIOS DIGITALES- CHÍA | G86: 3 | I86: =VLOOKUP(F86,'BDD Prof. Catedra'!$A$2:$C$176,3,0) -> 5 | J86: =I86-G86 -> 2
A87: ESPECIALIZACIÓN EN ENFERMERÍA EN CUIDADO CRÍTICO | B87: 5 | C87: 9 | D87: 14 | F87: ESPECIALIZACIÓN EN ENFERMERÍA EN CUIDADO CRÍTICO | G87: 5 | H87: 9 | I87: =VLOOKUP(F87,'BDD Prof. Catedra'!$A$2:$C$176,3,0) -> 5 | J87: =I87-G87 -> 0
A88: ESPECIALIZACIÓN EN FARMACOLOGÍA CLÍNICA | B88: 2 | C88: 2 | D88: 4 | F88: ESPECIALIZACIÓN EN FARMACOLOGÍA CLÍNICA | G88: 2 | H88: 2 | I88: =VLOOKUP(F88,'BDD Prof. Catedra'!$A$2:$C$176,3,0) -> 2 | J88: =I88-G88 -> 0
A89: ESPECIALIZACIÓN EN FINANZAS CORPORATIVAS CHÍA | B89: 6 | C89: 1 | D89: 7 | F89: ESPECIALIZACIÓN EN FINANZAS CORPORATIVAS CHÍA | G89: 4 | H89: 1 | I89: =VLOOKUP(F89,'BDD Prof. Catedra'!$A$2:$C$176,3,0) -> 6 | J89: =I89-G89 -> 2
A90: ESPECIALIZACIÓN EN GERENCIA COMERCIAL - BOGOTÁ | B90: 2 | D90: 2 | F90: ESPECIALIZACIÓN EN GERENCIA COMERCIAL - BOGOTÁ | G90: 1 | I90: =VLOOKUP(F90,'BDD Prof. Catedra'!$A$2:$C$176,3,0) -> 2 | J90: =I90-G90 -> 1
A91: ESPECIALIZACIÓN EN GERENCIA COMERCIAL BARRANQUILLA | B91: 2 | D91: 2 | F91: ESPECIALIZACIÓN EN GERENCIA COMERCIAL BARRANQUILLA | G91: 2 | I91: =VLOOKUP(F91,'BDD Prof. Catedra'!$A$2:$C$176,3,0) -> 2 | J91: =I91-G91 -> 0
A92: ESPECIALIZACIÓN EN GERENCIA COMERCIAL BUCARAMANGA | B92: 2 | C92: 2 | D92: 4 | F92: ESPECIALIZACIÓN EN GERENCIA COMERCIAL BUCARAMANGA | G92: 1 | H92: 1 | I92: =VLOOKUP(F92,'BDD Prof. Catedra'!$A$2:$C$176,3,0) -> 3 | J92: =I92-G92 -> 2
A93: ESPECIALIZACIÓN EN GERENCIA COMERCIAL CHÍA | B93: 3 | C93: 1 | D93: 4 | F93: ESPECIALIZACIÓN EN GERENCIA COMERCIAL CHÍA | G93: 2 | I93: =VLOOKUP(F93,'BDD Prof. Catedra'!$A$2:$C$176,3,0) -> 4 | J93: =I93-G93 -> 2
A94: ESPECIALIZACIÓN EN GERENCIA COMERCIAL MEDELLÍN | B94: 3 | D94: 3 | F94: ESPECIALIZACIÓN EN GERENCIA COMERCIAL MEDELLÍN | G94: 3 | I94: =VLOOKUP(F94,'BDD Prof. Catedra'!$A$2:$C$176,3,0) -> 3 | J94: =I94-G94 -> 0
A95: ESPECIALIZACIÓN EN GERENCIA COMERCIAL VIRTUAL | B95: 1 | D95: 1 | F95: ESPECIALIZACIÓN EN GERENCIA COMERCIAL VIRTUAL | G95: 1 | I95: =VLOOKUP(F95,'BDD Prof. Catedra'!$A$2:$C$176,3,0) -> 1 | J95: =I95-G95 -> 0
A96: ESPECIALIZACIÓN EN GERENCIA DE LA COMUNICACIÓN ORGANIZACIONAL | B96: 1 | D96: 1 | F96: ESPECIALIZACIÓN EN GERENCIA DE LA COMUNICACIÓN ORGANIZACIONAL | G96: 1 | I96: =VLOOKUP(F96,'BDD Prof. Catedra'!$A$2:$C$176,3,0) -> 1 | J96: =I96-G96 -> 0
A97: ESPECIALIZACIÓN EN GERENCIA DE PRODUCCIÓN Y OPERACIONES CHÍA | B97: 1 | C97: 1 | D97: 2 | F97: ESPECIALIZACIÓN EN GERENCIA DE PRODUCCIÓN Y OPERACIONES CHÍA | G97: 1 | H97: 1 | I97: =VLOOKUP(F97,'BDD Prof. Catedra'!$A$2:$C$176,3,0) -> 1 | J97: =I97-G97 -> 0
A98: ESPECIALIZACIÓN EN GERENCIA DE PROYECTOS CON ENFOQUE EN HABILIDADES DIRECTIVAS - BOGOTÁ | B98: 3 | D98: 3 | F98: ESPECIALIZACIÓN EN GERENCIA DE PROYECTOS CON ENFOQUE EN HABILIDADES DIRECTIVAS - BOGOTÁ | G98: 1 | I98: =VLOOKUP(F98,'BDD Prof. Catedra'!$A$2:$C$176,3,0) -> 3 | J98: =I98-G98 -> 2
A99: ESPECIALIZACIÓN EN GERENCIA DE PROYECTOS CON ENFOQUE EN HABILIDADES DIRECTIVAS CHÍA | B99: 2 | C99: 1 | D99: 3 | F99: ESPECIALIZACIÓN EN GERENCIA DE PROYECTOS CON ENFOQUE EN HABILIDADES DIRECTIVAS CHÍA | H99: 1 | I99: =VLOOKUP(F99,'BDD Prof. Catedra'!$A$2:$C$176,3,0) -> 2 | J99: =I99-G99 -> 2
A100: ESPECIALIZACIÓN EN GERENCIA DE RIESGOS - CHÍA | B100: 4 | D100: 4 | F100: ESPECIALIZACIÓN EN GERENCIA DE RIESGOS - CHÍA | G100: 3 | I100: =VLOOKUP(F100,'BDD Prof. Catedra'!$A$2:$C$176,3,0) -> 5 | J100: =I100-G100 -> 2
A101: ESPECIALIZACIÓN EN GERENCIA DEL SERVICIO CHÍA | B101: 7 | D101: 7 | F101: ESPECIALIZACIÓN EN GERENCIA DEL SERVICIO CHÍA | G101: 7 | I101: =VLOOKUP(F101,'BDD Prof. Catedra'!$A$2:$C$176,3,0) -> 7 | J101: =I101-G101 -> 0
A102: ESPECIALIZACIÓN EN GERENCIA EDUCATIVA | C102: 1 | D102: 1 | F102: ESPECIALIZACIÓN EN GERENCIA EDUCATIVA | H102: 1 | I102: =VLOOKUP(F102,'BDD Prof. Catedra'!$A$2:$C$176,3,0) -> 0 | J102: =I102-G102 -> 0
A103: ESPECIALIZACIÓN EN GERENCIA ESTRATÉGICA - VIRTUAL | B103: 1 | D103: 1 | F103: ESPECIALIZACIÓN EN GERENCIA ESTRATÉGICA - VIRTUAL | G103: 1 | I103: =VLOOKUP(F103,'BDD Prof. Catedra'!$A$2:$C$176,3,0) -> 1 | J103: =I103-G103 -> 0
A104: ESPECIALIZACIÓN EN GERENCIA ESTRATÉGICA BARRANQUILLA | B104: 2 | C104: 1 | D104: 3 | F104: ESPECIALIZACIÓN EN GERENCIA ESTRATÉGICA BARRANQUILLA | G104: 2 | H104: 1 | I104: =VLOOKUP(F104,'BDD Prof. Catedra'!$A$2:$C$176,3,0) -> 2 | J104: =I104-G104 -> 0
A105: ESPECIALIZACIÓN EN GERENCIA ESTRATÉGICA BUCARAMANGA | B105: 1 | D105: 1 | F105: ESPECIALIZACIÓN EN GERENCIA ESTRATÉGICA BUCARAMANGA | G105: 1 | I105: =VLOOKUP(F105,'BDD Prof. Catedra'!$A$2:$C$176,3,0) -> 1 | J105: =I105-G105 -> 0
A106: ESPECIALIZACIÓN EN GERENCIA ESTRATÉGICA CHÍA | B106: 4 | D106: 4 | F106: ESPECIALIZACIÓN EN GERENCIA ESTRATÉGICA CHÍA | G106: 4 | I106: =VLOOKUP(F106,'BDD Prof. Catedra'!$A$2:$C$176,3,0) -> 4 | J106: =I106-G106 -> 0
...

Sheet BDD Estudiantes Posgrado
A1: resumen | B1: Value | C1: Label | D1: Total
A2: ESPECIALIZACIÓN EN ANESTESIOLOGÍA Y MEDICINA PERIOPERATORIA | B2: 1 | C2: Especialización en Anestesiología y Medicina Perioperatoria | D2: 7
A3: ESPECIALIZACIÓN EN CIRUGÍA GENERAL | B3: 2 | C3: Especialización en Cirugía General | D3: 23
A4: ESPECIALIZACIÓN EN CUIDADO INTENSIVO PEDIÁTRICO | B4: 3 | C4: Especialización en Cuidado Intensivo Pediátrico | D4: 4
A5: ESPECIALIZACIÓN EN ELECTROFISIOLOGÍA CARDIOVASCULAR | B5: 4 | C5: Especialización en Electrofisiología Cardiovascular | D5: 1
A6: ESPECIALIZACIÓN EN FARMACOLOGÍA CLÍNICA | B6: 5 | C6: Especialización en Farmacología Clínica | D6: 10
A7: ESPECIALIZACIÓN EN GINECOLOGÍA Y OBSTETRICIA | B7: 6 | C7: Especialización en Ginecología y Obstetricia | D7: 10
A8: ESPECIALIZACIÓN EN MEDICINA CRÍTICA | B8: 7 | C8: Especialización en Medicina Crítica y Cuidado Intensivo | D8: 10
A9: ESPECIALIZACIÓN EN MEDICINA FAMILIAR Y COMUNITARIA | B9: 8 | C9: Especialización en Medicina Familiar y Comunitaria | D9: 20
A10: ESPECIALIZACIÓN EN MEDICINA FÍSICA Y REHABILITACIÓN | B10: 9 | C10: Especialización en Medicina Física y Rehabilitación | D10: 12
A11: ESPECIALIZACIÓN EN MEDICINA INTERNA | B11: 10 | C11: Especialización en Medicina Interna | D11: 17
A12: ESPECIALIZACIÓN EN NEUMOLOGÍA | B12: 11 | C12: Especialización en Neumología | D12: 8
A13: ESPECIALIZACIÓN EN NEUROLOGÍA | B13: 12 | C13: Especialización en Neurología | D13: 15
... A37: Ingeniería Civil | B37: 36 | C37: Ingeniería Civil | D37: 101
A38: Ingeniería de Bioproducción / Producción Agroindustrial | B38: 37 | C38: Ingeniería de Bioproducción / Ingeniería Agroindustrial | D38: =F147+F148 -> 35
A39: Ingeniería Industrial | B39: 38 | C39: Ingeniería Industrial | D39: 185
A40: Ingeniería Informática | B40: 39 | C40: Ingeniería Informática | D40: 209
A41: Ingeniería Mecánica | B41: 40 | C41: Ingeniería Mecánica | D41: 136
A42: Ingeniería Química | B42: 41 | C42: Ingeniería Química | D42: 139
A43: Medicina | B43: 42 | C43: Medicina | D43: 679
A44: Psicología | B44: 43 | C44: Psicología | D44: 205
A45: DOCTORADO EN ADMINISTRACIÓN DE ORGANIZACIONES | B45: 44 | C45: Doctorado en Administración de Organizaciones - Chía | D45: 9
A46: MAESTRÍA EN GERENCIA DE INVERSIÓN | B46: 45 | C46: Maestría en Gerencia de Inversión - Chía | D46: 23
A47: MAESTRÍA EN GERENCIA DE OPERACIONES | B47: 46 | C47: Maestría en Gerencia de Operaciones - Chía | D47: 23
A48: MAESTRÍA EN GERENCIA ESTRATÉGICA | B48: 47 | C48: Maestría en Gerencia Estratégica - Chía | D48: 46
A49: MAESTRÍA EN GERENCIA INTERNACIONAL | B49: 48 | C49: Maestría en Gerencia Internacional - Chía | D49: 4
A50: MAESTRÍA EN GERENCIA DE LA INNOVACIÓN | B50: 49 | C50: Maestría en Gerencia de la Innovación - Chía | D50: 33
... A62: MAESTRÍA EN EDUCACIÓN | B62: 61 | C62: Maestría en Educación - Chía | D62: 12
B63: 62 | C63: Maestría en Informática Educativa - Chía
A64: MAESTRÍA EN DIDÁCTICA DEL INGLÉS PARA EL APRENDIZAJE AUTODIRIGIDO | B64: 63 | C64: Maestría en Didáctica del Inglés con Énfasis en Ambientes de Aprendizaje Autónomo - Chía
A65: MAESTRÍA EN DIRECCIÓN Y GESTIÓN DE INSTITUCIONES EDUCATIVAS | B65: 64 | C65: Maestría en Dirección y Gestión de Instituciones Educativas - Chía | D65: 3
A66: MAESTRÍA EN PEDAGOGÍA | B66: 65 | C66: Maestría en Pedagogía - Chía | D66: 11
A67: DOCTORADO EN ENFERMERÍA | B67: 66 | C67: Doctorado en Enfermería - Chía | D67: 12
A68: MAESTRÍA EN ENFERMERÍA PRESENCIAL | B68: 67 | C68: Maestría en Enfermería - Chía | D68: 7
A69: MAESTRÍA EN LINGÜÍSTICA PANHISPÁNICA - VIRTUAL | B69: 68 | C69: Maestría en Lingüística Panhispánica - Chía | D69: 4
A70: MAESTRÍA EN TEOLOGÍA | B70: 69 | C70: Maestría en Teología - Chía | D70: 4
A71: DOCTORADO EN BIOCIENCIAS | B71: 70 | C71: Doctorado en Biociencias - Chía | D71: 7
A72: DOCTORADO EN LOGÍSTICA Y GESTIÓN DE CADENA DE SUMINISTRO | B72: 71 | C72: Doctorado en Logística y Gestión de Cadenas de Suministros - Chía | D72: 13
A73: DOCTORADO EN INGENIERÍA | B73: 72 | C73: Doctorado en Ingeniería - Chía | D73: 7
A74: MAESTRÍA EN DISEÑO Y GESTIÓN DE PROCESOS | B74: 73 | C74: Maestría en Diseño y Gestión de Procesos - Chía | D74: 16
A75: MAESTRÍA EN GERENCIA DE INGENIERÍA | B75: 74 | C75: Maestría en Gerencia de Ingeniería - Chía | D75: 4
A76: MAESTRÍA EN ANALÍTICA APLICADA | B76: 75 | C76: Maestría en Analítica Aplicada - Chía | D76: 32
A77: MAESTRÍA EN BIOÉTICA | B77: 76 | C77: Maestría en Bioética - Chía | D77: 5
A78: MAESTRÍA EN EPIDEMIOLOGÍA | B78: 77 | C78: Maestría en Epidemiología - Chía
A79: MAESTRÍA EN EDUCACIÓN MÉDICA | B79: 78 | C79: Maestría en Educación Médica - Chía | D79: 3
A80: MAESTRÍA EN SALUD PÚBLICA | B80: 79 | C80: Maestría en Salud Pública - Chía | D80: 1
A81: MAESTRÍA EN PSICOLOGÍA | B81: 80 | C81: Maestría en Psicología - Chía | D81: 13
A82: MAESTRÍA EN GERENCIA Y DESARROLLO DE PERSONAS | B82: 81 | C82: Maestría en Gerencia y Desarrollo de Personas - Chía | D82: 17
A83: MAESTRÍA EN PSICOLOGÍA DE LA SALUD Y LA DISCAPACIDAD | B83: 82 | C83: Maestría en Psicología de la Salud y la Discapacidad - Chía | D83: 10
A84: MAESTRÍA EN PROYECTOS EDUCATIVOS MEDIADOS POR TIC | B84: 83 | C84: Maestría en Proyectos Educativos Mediados por TIC - Virtual
A85: MAESTRÍA EN INNOVACIÓN EDUCATIVA MEDIADA POR TIC - VIRTUAL | B85: 84 | C85: Maestría en Innovación Educativa Mediada por TIC - Virtual | D85: 9
A86: MAESTRÍA EN PEDAGOGÍA E INVESTIGACIÓN EN AULA - VIRTUAL | B86: 85 | C86: Maestría en Pedagogía e Investigación en Aula - Virtual | D86: 50
A87: MAESTRÍA EN DIDÁCTICA DEL INGLÉS PARA EL APRENDIZAJE AUTODIRIGIDO - VIRTUAL | B87: 86 | C87: Maestría en Didáctica Del Inglés Para el Aprendizaje Autodirigido - Virtual | D87: 8
B88: 87 | C88: Maestría en Pedagogía - Riohacha
A89: MAESTRÍA EN DESARROLLO INFANTIL - RIOHACHA | B89: 88 | C89: Maestría en Desarrollo Infantil - Riohacha | D89: 8 | E89: Se le suma 1 del 158
A90: MAESTRÍA EN DIRECCIÓN Y GESTIÓN DE INSTITUCIONES EDUCATIVAS - RIOHACHA | B90: 89 | C90: Maestría en Dirección y Gestión de Instituciones Educativas - Riohacha | D90: 4
B91: 90 | C91: Maestría en Dirección y Gestión de Instituciones Educativas - Neiva
A92: MAESTRÍA EN PEDAGOGÍA - NEIVA | B92: 91 | C92: Maestría en Pedagogía - Neiva | D92: 4
B93: 92 | C93: Maestría en Pedagogía - Valledupar
B94: 93 | C94: Maestría en Dirección y Gestión de Instituciones Educativas - Valledupar
A95: MAESTRÍA EN ENFERMERÍA VIRTUAL | B95: 94 | C95: Maestría en Enfermería - Virtual | D95: 9
A96: MAESTRÍA EN ASESORÍA FAMILIAR Y GESTIÓN DE PROGRAMAS PARA LA FAMILIA | B96: 95 | C96: Maestría en Asesoría Familiar y Gestión de Programas para la Familia - Virtual | D96: 52
A97: ESPECIALIZACIÓN EN GERENCIA DE LA COMUNICACIÓN ORGANIZACIONAL | B97: 96 | C97: Especialización en Gerencia de la Comunicación Organizacional - Chía | D97: 13
A98: ESPECIALIZACIÓN EN CONTRATACIÓN ESTATAL | B98: 97 | C98: Especialización en Contratación Estatal - Chía | D98: 5
A99: ESPECIALIZACIÓN EN DERECHO COMERCIAL | B99: 98 | C99: Especialización en Derecho Comercial - Chía | D99: 3
A100: ESPECIALIZACIÓN EN DERECHO TRIBUTARIO | B100: 99 | C100: Especialización en Derecho Tributario - Chía | D100: 2
A101: ESPECIALIZACIÓN EN DERECHO Y EMPRESA | B101: 100 | C101: Especialización en Derecho y Empresa - Chía | D101: 1
A102: ESPECIALIZACIÓN EN RESPONSABILIDAD CIVIL Y DEL ESTADO | B102: 101 | C102: Especialización en Responsabilidad Civil y del Estado - Chía | D102: 3
A103: ESPECIALIZACIÓN EN SEGUROS Y SEGURIDAD SOCIAL | B103: 102 | C103: Especialización en Seguros y Seguridad Social - Chía | D103: 13
A104: ESPECIALIZACIÓN EN GERENCIA EDUCATIVA | B104: 103 | C104: Especialización en Gerencia Educativa - Chía | D104: 1
A105: ESPECIALIZACIÓN EN ENFERMERÍA EN CUIDADO CRÍTICO | B105: 104 | C105: Especialización en Enfermería en Cuidado Crítico - Chía | D105: 10
A106: ESPECIALIZACIÓN EN TERAPIA MANUAL ORTOPÉDICA | B106: 105 | C106: Especialización en Terapia Manual Ortopédica - Chía | D106: 12
... A109: ESPECIALIZACIÓN EN PSICOLOGÍA EDUCATIVA | B109: 108 | C109: Especialización en Psicología Educativa - Chía | D109: 16
B110: 109 | C110: Especialización en Desarrollo Personal y Familiar - Chía
A111: ESPECIALIZACIÓN EN GERENCIA FINANCIERA INTERNACIONAL CHÍA | B111: 110 | C111: Especialización en Gerencia Financiera Internacional - Chía. (Especialización en Finanzas y Negocios Internacionales) | D111: 27
A112: ESPECIALIZACIÓN EN GERENCIA COMERCIAL CHÍA | B112: 111 | C112: Especialización en Gerencia Comercial - Chía | D112: 62
A113: ESPECIALIZACIÓN EN GERENCIA DE PRODUCCIÓN Y OPERACIONES CHÍA | B113: 112 | C113: Especialización en Gerencia de Producción y Operaciones - Chía | D113: 26
A114: ESPECIALIZACIÓN EN GERENCIA ESTRATÉGICA DE MARCA CHÍA | B114: 113 | C114: Especialización en Gerencia Estratégica de Marca - Chía | D114: 33
A115: ESPECIALIZACIÓN EN GERENCIA ESTRATÉGICA CHÍA | B115: 114 | C115: Especialización en Gerencia Estratégica - Chía | D115: 96
A116: ESPECIALIZACIÓN EN GERENCIA LOGÍSTICA CHÍA | B116: 115 | C116: Especialización en Gerencia Logística - Chía | D116: 33
A117: ESPECIALIZACIÓN EN GESTIÓN PARA EL DESARROLLO HUMANO EN LA ORGANIZACIÓN CHÍA | B117: 116 | C117: Especialización en Gestión para el Desarrollo Humano en la Organización - Chía | D117: 16
A118: ESPECIALIZACIÓN EN FINANZAS CORPORATIVAS CHÍA | B118: 117 | C118: Especialización en Finanzas Corporativas - Chía | D118: 27
A119: ESPECIALIZACIÓN EN GERENCIA DEL SERVICIO CHÍA | B119: 118 | C119: Especialización en Gerencia del Servicio - Chía | D119: 18
A120: ESPECIALIZACIÓN EN GERENCIA DE PROYECTOS CON ENFOQUE EN HABILIDADES DIRECTIVAS CHÍA | B120: 119 | C120: Especialización en Gerencia de Proyectos con Enfoque en Habilidades Directivas - Chía | D120: 45
A121: ESPECIALIZACIÓN EN GERENCIA DE RIESGOS - CHÍA | B121: 120 | C121: Especialización en Gerencia de Riesgos - Chía | D121: 28
A122: ESPECIALIZACIÓN EN CONTRATACIÓN ESTATAL - IBAGUÉ | B122: 121 | C122: Especialización en Contratación Estatal Ibagué -Tolima
A123: ESPECIALIZACIÓN EN CONTRATACIÓN ESTATAL - NEIVA | B123: 122 | C123: Especialización en Contratación Estatal - Neiva | D123: 6
A124: ESPECIALIZACIÓN EN PEDAGOGÍA E INVESTIGACIÓN EN EL AULA - VIRTUAL | B124: 123 | C124: Especialización en Pedagogía e Investigación en el Aula - Virtual | D124: 10
A125: ESPECIALIZACIÓN EN GERENCIA ESTRATÉGICA - VIRTUAL | B125: 124 | C125: Especialización en Gerencia Estratégica - Virtual | D125: 45
A126: ESPECIALIZACIÓN EN GESTIÓN PARA EL DESARROLLO HUMANO EN LA ORGANIZACIÓN - VIRTUAL | B126: 125 | C126: Especialización en Gestión para el Desarrollo Humano en la Organización - Virtual | D126: 1
A127: ESPECIALIZACIÓN EN GERENCIA COMERCIAL VIRTUAL | B127: 126 | C127: Especialización en Gerencia Comercial - Virtual | D127: 24
A128: ESPECIALIZACIÓN EN GERENCIA COMERCIAL BUCARAMANGA | B128: 127 | C128: Especialización en Gerencia Comercial Bucaramanga - Santander | D128: 39
A129: ESPECIALIZACIÓN EN GERENCIA COMERCIAL IBAGUÉ | B129: 128 | C129: Especialización En Gerencia Comercial Ibagué - Tolima
A130: ESPECIALIZACIÓN EN GERENCIA COMERCIAL MEDELLÍN | B130: 129 | C130: Especialización en Gerencia Comercial Medellín - Antioquia | D130: 11
B131: 130 | C131: Especialización en Gerencia Comercial - Villavicencio
A132: ESPECIALIZACIÓN EN GERENCIA ESTRATÉGICA MEDELLÍN | B132: 131 | C132: Especialización en Gerencia Estratégica - Medellín | D132: 24
A133: ESPECIALIZACIÓN EN GERENCIA ESTRATÉGICA IBAGUÉ | B133: 132 | C133: Especialización En Gerencia Estratégica - Ibagué | D133: 17
A134: ESPECIALIZACIÓN EN GERENCIA ESTRATÉGICA VILLAVICENCIO | B134: 133 | C134: Especialización En Gerencia Estratégica - Villavicencio | D134: 19
A135: ESPECIALIZACIÓN EN GERENCIA ESTRATÉGICA BUCARAMANGA | B135: 134 | C135: Especialización en Gerencia Estratégica - Bucaramanga | D135: 41
A136: ESPECIALIZACIÓN EN GERENCIA LOGÍSTICA BUCARAMANGA | B136: 135 | C136: Especialización en Gerencia Logística. Bucaramanga | D136: 6
...

Sheet BDD Prof. Planta
B1: REALIZADO | C1: Count | D1: Suma | F1: UNIVERSO | I1: COD. UNIDAD | J1: UNIDAD | K1: Encuesta replicadas | L1: SUMA REALIZADO | M1: Universo BDD | N1: Diferencias
A2: =B2 -> ADMINISTRACIÓN Y ORGANIZACIONES | B2: ADMINISTRACIÓN Y ORGANIZACIONES | C2: 8 | F2: ADMINISTRACIï¿½N Y ORGANIZACIONES | G2: 8 | I2: 2 | J2: ESCUELA INTERNACIONAL DE CIENCIAS ECONÓMICAS Y ADMINISTRATIVAS | K2: 0 | L2: =K2+C2 -> 8 | M2: =IFERROR(VLOOKUP(A2,'Ajustes profesores'!$G$5:$I$151,3,0),0) -> 8 | N2: =G2-M2 -> 0 | R2: 0
A3: =B3 -> ARTES CULINARIAS Y CIENCIAS DE LA ALIMENTACIÓN | B3: ARTES CULINARIAS Y CIENCIAS DE LA ALIMENTACIÓN | C3: 7 | F3: ARTES CULINARIAS Y CIENCIAS DE LA ALIMENTACIï¿½N | G3: 7 | I3: 2 | J3: ESCUELA INTERNACIONAL DE CIENCIAS ECONÓMICAS Y ADMINISTRATIVAS | K3: 0 | L3: =K3+C3 -> 7 | M3: =IFERROR(VLOOKUP(A3,'Ajustes profesores'!$G$5:$I$151,3,0),0) -> 7 | N3: =G3-M3 -> 0 | R3: 0
A4: =B4 -> ECONOMÍA | B4: ECONOMÍA | C4: 7 | F4: ECONOMï¿½A | G4: 7 | I4: 2 | J4: ESCUELA INTERNACIONAL DE CIENCIAS ECONÓMICAS Y ADMINISTRATIVAS | K4: 0 | L4: =K4+C4 -> 7 | M4: =IFERROR(VLOOKUP(A4,'Ajustes profesores'!$G$5:$I$151,3,0),0) -> 7 | N4: =G4-M4 -> 0 | R4: 0
A5: =B5 -> FINANZAS | B5: FINANZAS | C5: 3 | F5: FINANZAS | G5: 3 | I5: 2 | J5: ESCUELA INTERNACIONAL DE CIENCIAS ECONÓMICAS Y ADMINISTRATIVAS | K5: 0 | L5: =K5+C5 -> 3 | M5: =IFERROR(VLOOKUP(A5,'Ajustes profesores'!$G$5:$I$151,3,0),0) -> 3 | N5: =G5-M5 -> 0 | R5: 0
A6: =B6 -> GESTIÓN DE OPERACIONES | B6: GESTIÓN DE OPERACIONES | C6: 2 | F6: GESTIï¿½N DE OPERACIONES | G6: 2 | I6: 2 | J6: ESCUELA INTERNACIONAL DE CIENCIAS ECONÓMICAS Y ADMINISTRATIVAS | K6: 0 | L6: =K6+C6 -> 2 | M6: =IFERROR(VLOOKUP(A6,'Ajustes profesores'!$G$5:$I$151,3,0),0) -> 2 | N6: =G6-M6 -> 0 | R6: 0
A7: =B7 -> INNOVACIÓN Y EMPRENDIMIENTO | B7: INNOVACIÓN Y EMPRENDIMIENTO | C7: 2 | F7: INNOVACIï¿½N Y EMPRENDIMIENTO | G7: 2 | I7: 2 | J7: ESCUELA INTERNACIONAL DE CIENCIAS ECONÓMICAS Y ADMINISTRATIVAS | K7: 0 | L7: =K7+C7 -> 2 | M7: =IFERROR(VLOOKUP(A7,'Ajustes profesores'!$G$5:$I$151,3,0),0) -> 2 | N7: =G7-M7 -> 0 | R7: 0
A8: =B8 -> MERCADEO | B8: MERCADEO | C8: 3 | F8: MERCADEO | G8: 3 | I8: 2 | J8: ESCUELA INTERNACIONAL DE CIENCIAS ECONÓMICAS Y ADMINISTRATIVAS | K8: 0 | L8: =K8+C8 -> 3 | M8: =IFERROR(VLOOKUP(A8,'Ajustes profesores'!$G$5:$I$151,3,0),0) -> 3 | N8: =G8-M8 -> 0 | R8: 0
A9: =B9 -> NEGOCIACIÓN Y COMERCIO INTERNACIONAL | B9: NEGOCIACIÓN Y COMERCIO INTERNACIONAL | C9: 4 | F9: NEGOCIACIï¿½N Y COMERCIO INTERNACIONAL | G9: 4 | I9: 2 | J9: ESCUELA INTERNACIONAL DE CIENCIAS ECONÓMICAS Y ADMINISTRATIVAS | K9: 0 | L9: =K9+C9 -> 4 | M9: =IFERROR(VLOOKUP(A9,'Ajustes profesores'!$G$5:$I$151,3,0),0) -> 4 | N9: =G9-M9 -> 0 | R9: 0
A10: =B10 -> SERVICIO, HOSPITALIDAD Y CALIDAD | B10: SERVICIO, HOSPITALIDAD Y CALIDAD | C10: 4 | D10: =SUM(C2:C10) -> 40 | F10: SERVICIO, HOSPITALIDAD Y CALIDAD | G10: 4 | H10: =SUM(G2:G10) -> 40 | I10: 2 | J10: ESCUELA INTERNACIONAL DE CIENCIAS ECONÓMICAS Y ADMINISTRATIVAS | K10: 0 | L10: =K10+C10 -> 4 | M10: =IFERROR(VLOOKUP(A10,'Ajustes profesores'!$G$5:$I$151,3,0),0) -> 4 | N10: =G10-M10 -> 0 | R10: 0
A11: Comunicación Audiovisual y Multimedios | B11: COMUNICACIÓN AUDIOVISUAL Y MULTIMEDIOS | C11: 14 | F11: COMUNICACIï¿½N AUDIOVISUAL Y MULTIMEDIOS | G11: 16 | I11: 3 | J11: FACULTAD DE COMUNICACIÓN | K11: 2 | L11: =K11+C11 -> 16 | M11: =IFERROR(VLOOKUP(A11,'Ajustes profesores'!$G$5:$I$151,3,0),0) -> 16 | N11: =G11-M11 -> 0 | R11: 2
A12: Comunicación Corporativa | B12: COMUNICACIÓN CORPORATIVA | C12: 10 | F12: COMUNICACIï¿½N CORPORATIVA | G12: 15 | I12: 3 | J12: FACULTAD DE COMUNICACIÓN | K12: 4 | L12: =K12+C12 -> 14 | M12: =IFERROR(VLOOKUP(A12,'Ajustes profesores'!$G$5:$I$151,3,0),0) -> 14 | N12: =G12-M12 -> 1 | R12: 4
A13: Comunicación Social y Periodismo | B13: COMUNICACIÓN SOCIAL Y PERIODISMO | C13: 11 | F13: COMUNICACIï¿½N SOCIAL Y PERIODISMO | G13: 14 | I13: 3 | J13: FACULTAD DE COMUNICACIÓN | K13: 3 | L13: =K13+C13 -> 14 | M13: =IFERROR(VLOOKUP(A13,'Ajustes profesores'!$G$5:$I$151,3,0),0) -> 14 | N13: =G13-M13 -> 0 | R13: 3
A14: Ciencias Políticas | B14: CIENCIAS POLÍTICAS | C14: 8 | F14: CIENCIAS POLï¿½TICAS | G14: 8 | I14: 4 | J14: FACULTAD DE DERECHO Y CIENCIAS POLÍTICAS | K14: 0 | L14: =K14+C14 -> 8 | M14: =IFERROR(VLOOKUP(A14,'Ajustes profesores'!$G$5:$I$151,3,0),0) -> 8 | N14: =G14-M14 -> 0 | R14: 0
A15: Derecho | B15: DERECHO | C15: 25 | F15: DERECHO | G15: 26 | I15: 4 | J15: FACULTAD DE DERECHO Y CIENCIAS POLÍTICAS | K15: 1 | L15: =K15+C15 -> 26 | M15: =IFERROR(VLOOKUP(A15,'Ajustes profesores'!$G$5:$I$151,3,0),0) -> 26 | N15: =G15-M15 -> 0 | R15: 1
A16: Licenciatura en Ciencias Naturales | B16: LICENCIATURA EN CIENCIAS NATURALES | C16: 7 | F16: LICENCIATURA EN CIENCIAS NATURALES | G16: 8 | I16: 5 | J16: FACULTAD DE EDUCACIÓN | K16: 0 | L16: =K16+C16 -> 7 | M16: =IFERROR(VLOOKUP(A16,'Ajustes profesores'!$G$5:$I$151,3,0),0) -> 7 | N16: =G16-M16 -> 1 | R16: 0
A17: Licenciatura en Educación Infantil | B17: LICENCIATURA EN EDUCACIÓN INFANTIL | C17: 7 | F17: LICENCIATURA EN EDUCACIï¿½N INFANTIL | G17: 9 | I17: 5 | J17: FACULTAD DE EDUCACIÓN | K17: 1 | L17: =K17+C17 -> 8 | M17: =IFERROR(VLOOKUP(A17,'Ajustes profesores'!$G$5:$I$151,3,0),0) -> 8 | N17: =G17-M17 -> 1 | R17: 1
A18: Enfermería | B18: ENFERMERÍA | C18: 14 | F18: ENFERMERï¿½A | G18: 14 | I18: 6 | J18: FACULTAD DE ENFERMERÍA Y REHABILITACIÓN | K18: 0 | L18: =K18+C18 -> 14 | M18: =IFERROR(VLOOKUP(A18,'Ajustes profesores'!$G$5:$I$151,3,0),0) -> 14 | N18: =G18-M18 -> 0 | R18: 0
A19: Fisioterapia | B19: FISIOTERAPIA | C19: 23 | F19: FISIOTERAPIA | G19: 23 | I19: 6 | J19: FACULTAD DE ENFERMERÍA Y REHABILITACIÓN | K19: 0 | L19: =K19+C19 -> 23 | M19: =IFERROR(VLOOKUP(A19,'Ajustes profesores'!$G$5:$I$151,3,0),0) -> 23 | N19: =G19-M19 -> 0 | R19: 0
A20: Filosofía | B20: FILOSOFÍA | C20: 5 | F20: FILOSOFï¿½A | G20: 5 | I20: 7 | J20: FACULTAD DE FILOSOFÍA Y CIENCIAS HUMANAS | K20: 0 | L20: =K20+C20 -> 5 | M20: =IFERROR(VLOOKUP(A20,'Ajustes profesores'!$G$5:$I$151,3,0),0) -> 5 | N20: =G20-M20 -> 0 | R20: 0
A21: Ingeniería Civil | B21: INGENIERÍA CIVIL | C21: 5 | F21: INGENIERï¿½A CIVIL | G21: 5 | I21: 8 | J21: FACULTAD DE INGENIERÍA | K21: 0 | L21: =K21+C21 -> 5 | M21: =IFERROR(VLOOKUP(A21,'Ajustes profesores'!$G$5:$I$151,3,0),0) -> 5 | N21: =G21-M21 -> 0 | R21: 0
B22: INGENIERÍA DE PRODUCCIÓN AGROINDUSTRIAL | G22: 0 | K22: 0 | L22: =K22+C22 -> 0 | M22: =IFERROR(VLOOKUP(A22,'Ajustes profesores'!$G$5:$I$151,3,0),0) -> 0 | N22: =G22-M22 -> 0 | R22: 0
A23: Ingeniería Industrial | B23: INGENIERÍA INDUSTRIAL | C23: 19 | F23: INGENIERï¿½A INDUSTRIAL | G23: 21 | I23: 8 | J23: FACULTAD DE INGENIERÍA | K23: 0 | L23: =K23+C23 -> 19 | M23: =IFERROR(VLOOKUP(A23,'Ajustes profesores'!$G$5:$I$151,3,0),0) -> 19 | N23: =G23-M23 -> 2 | R23: 0
A24: Ingeniería Informática | B24: INGENIERÍA INFORMÁTICA | C24: 7 | F24: INGENIERï¿½A INFORMï¿½TICA | G24: 7 | I24: 8 | J24: FACULTAD DE INGENIERÍA | K24: 0 | L24: =K24+C24 -> 7 | M24: =IFERROR(VLOOKUP(A24,'Ajustes profesores'!$G$5:$I$151,3,0),0) -> 7 | N24: =G24-M24 -> 0 | R24: 0
A25: Ingeniería Mecánica | B25: INGENIERÍA MECÁNICA | C25: 6 | F25: INGENIERï¿½A MECï¿½NICA | G25: 6 | I25: 8 | J25: FACULTAD DE INGENIERÍA | K25: 0 | L25: =K25+C25 -> 6 | M25: =IFERROR(VLOOKUP(A25,'Ajustes profesores'!$G$5:$I$151,3,0),0) -> 6 | N25: =G25-M25 -> 0 | R25: 0
A26: Ingeniería Química | B26: INGENIERÍA QUÍMICA | C26: 12 | F26: INGENIERï¿½A QUï¿½MICA | G26: 13 | I26: 8 | J26: FACULTAD DE INGENIERÍA | K26: 0 | L26: =K26+C26 -> 12 | M26: =IFERROR(VLOOKUP(A26,'Ajustes profesores'!$G$5:$I$151,3,0),0) -> 12 | N26: =G26-M26 -> 1 | R26: 0
A27: Medicina | B27: MEDICINA | C27: 48 | F27: MEDICINA | G27: 53 | I27: 1 | J27: FACULTAD DE MEDICINA | K27: 0 | L27: =K27+C27 -> 48 | M27: =IFERROR(VLOOKUP(A27,'Ajustes profesores'!$G$5:$I$151,3,0),0) -> 48 | N27: =G27-M27 -> 5 | R27: 0
A28: Psicología | B28: PSICOLOGÍA | C28: 16 | F28: PSICOLOGï¿½A | G28: 17 | I28: 9 | J28: FACULTAD DE PSICOLOGÍA | K28: 0 | L28: =K28+C28 -> 16 | M28: =IFERROR(VLOOKUP(A28,'Ajustes profesores'!$G$5:$I$151,3,0),0) -> 16 | N28: =G28-M28 -> 1 | R28: 0
A29: =B29 -> MAESTRÍA EN COMUNICACIÓN ESTRATÉGICA | B29: MAESTRÍA EN COMUNICACIÓN ESTRATÉGICA | C29: 2 | F29: MAESTRï¿½A EN COMUNICACIï¿½N ESTRï¿½TEGICA | G29: 5 | I29: 3 | J29: FACULTAD DE COMUNICACIÓN | K29: 0 | L29: =K29+C29 -> 2 | M29: =IFERROR(VLOOKUP(A29,'Ajustes profesores'!$G$5:$I$151,3,0),0) -> 2 | N29: =G29-M29 -> 3 | R29: 0
A30: =B30 -> MAESTRÍA EN PERIODISMO Y COMUNICACIÓN DIGITAL | B30: MAESTRÍA EN PERIODISMO Y COMUNICACIÓN DIGITAL | C30: 2 | F30: MAESTRï¿½A EN PERIODISMO Y COMUNICACIï¿½N DIGITAL | G30: 4 | I30: 3 | J30: FACULTAD DE COMUNICACIÓN | K30: 0 | L30: =K30+C30 -> 2 | M30: =IFERROR(VLOOKUP(A30,'Ajustes profesores'!$G$5:$I$151,3,0),0) -> 2 | N30: =G30-M30 -> 2 | R30: 0
A31: =B31 -> MAESTRÍA EN CONTRATACIÓN ESTATAL | B31: MAESTRÍA EN CONTRATACIÓN ESTATAL | C31: 2 | F31: MAESTRIA EN CONTRATACION ESTATAL | G31: 3 | I31: 4 | J31: FACULTAD DE DERECHO Y CIENCIAS POLÍTICAS | K31: 0 | L31: =K31+C31 -> 2 | M31: =IFERROR(VLOOKUP(A31,'Ajustes profesores'!$G$5:$I$151,3,0),0) -> 2 | N31: =G31-M31 -> 1 | R31: 0
A32: =B32 -> MAESTRÍA EN DERECHO CONSTITUCIONAL | B32: MAESTRÍA EN DERECHO CONSTITUCIONAL | C32: 1 | F32: MAESTRIA EN DERECHO CONSTITUCIONAL | G32: 2 | I32: 4 | J32: FACULTAD DE DERECHO Y CIENCIAS POLÍTICAS | K32: 0 | L32: =K32+C32 -> 1 | M32: =IFERROR(VLOOKUP(A32,'Ajustes profesores'!$G$5:$I$151,3,0),0) -> 1 | N32: =G32-M32 -> 1 | R32: 0
A33: =B33 -> MAESTRÍA EN DERECHO DE LA EMPRESA Y DE LOS NEGOCIOS | B33: MAESTRÍA EN DERECHO DE LA EMPRESA Y DE LOS NEGOCIOS | C33: 1 | F33: MAESTRIA EN DERECHO DE LA EMPRESA Y DE LOS NEGOCIOS | G33: 2 | I33: 4 | J33: FACULTAD DE DERECHO Y CIENCIAS POLÍTICAS | K33: 0 | L33: =K33+C33 -> 1 | M33: =IFERROR(VLOOKUP(A33,'Ajustes profesores'!$G$5:$I$151,3,0),0) -> 1 | N33: =G33-M33 -> 1 | R33: 0
A34: =B34 -> MAESTRÍA EN DERECHO INTERNACIONAL | B34: MAESTRÍA EN DERECHO INTERNACIONAL | C34: 5 | F34: MAESTRIA EN DERECHO INTERNACIONAL | G34: 6 | I34: 4 | J34: FACULTAD DE DERECHO Y CIENCIAS POLÍTICAS | K34: 0 | L34: =K34+C34 -> 5 | M34: =IFERROR(VLOOKUP(A34,'Ajustes profesores'!$G$5:$I$151,3,0),0) -> 5 | N34: =G34-M34 -> 1 | R34: 0
A35: =B35 -> MAESTRÍA EN DESARROLLO INFANTIL | B35: MAESTRÍA EN DESARROLLO INFANTIL | C35: 1 | F35: MAESTRï¿½A EN DESARROLLO INFANTIL - CHIA | G35: 1 | I35: 5 | J35: FACULTAD DE EDUCACIÓN | K35: 0 | L35: =K35+C35 -> 1 | M35: =IFERROR(VLOOKUP(A35,'Ajustes profesores'!$G$5:$I$151,3,0),0) -> 1 | N35: =G35-M35 -> 0 | R35: 0
A36: =B36 -> MAESTRÍA EN DIDÁCTICA DEL INGLÉS CON ÉNFASIS EN AMBIENTES DE APRENDIZAJE AUTÓNOMO | B36: MAESTRÍA EN DIDÁCTICA DEL INGLÉS CON ÉNFASIS EN AMBIENTES DE APRENDIZAJE AUTÓNOMO | G36: 0 | K36: 0 | L36: =K36+C36 -> 0 | M36: =IFERROR(VLOOKUP(A36,'Ajustes profesores'!$G$5:$I$151,3,0),0) -> 0 | N36: =G36-M36 -> 0 | R36: 0
A37: =B37 -> MAESTRÍA EN DIRECCIÓN Y GESTIÓN DE INSTITUCIONES EDUCATIVAS | B37: MAESTRÍA EN DIRECCIÓN Y GESTIÓN DE INSTITUCIONES EDUCATIVAS | C37: 1 | F37: MAESTRï¿½A EN DIRECCIï¿½N Y GESTIï¿½N DE INSTITUCIONES EDUCATIVAS | G37: 2 | I37: 5 | J37: FACULTAD DE EDUCACIÓN | K37: 0 | L37: =K37+C37 -> 1 | M37: =IFERROR(VLOOKUP(A37,'Ajustes profesores'!$G$5:$I$151,3,0),0) -> 1 | N37: =G37-M37 -> 1 | R37: 0
A38: =B38 -> MAESTRÍA EN EDUCACIÓN | B38: MAESTRÍA EN EDUCACIÓN | C38: 1 | F38: MAESTRï¿½A EN EDUCACIï¿½N | G38: 3 | I38: 5 | J38: FACULTAD DE EDUCACIÓN | K38: 0 | L38: =K38+C38 -> 1 | M38: =IFERROR(VLOOKUP(A38,'Ajustes profesores'!$G$5:$I$151,3,0),0) -> 1 | N38: =G38-M38 -> 2 | R38: 0
A39: =B39 -> MAESTRÍA EN PEDAGOGÍA | B39: MAESTRÍA EN PEDAGOGÍA | C39: 1 | F39: MAESTRï¿½A EN PEDAGOGï¿½A | G39: 2 | I39: 5 | J39: FACULTAD DE EDUCACIÓN | K39: 0 | L39: =K39+C39 -> 1 | M39: =IFERROR(VLOOKUP(A39,'Ajustes profesores'!$G$5:$I$151,3,0),0) -> 1 | N39: =G39-M39 -> 1 | R39: 0
A40: =B40 -> MAESTRÍA EN ENFERMERÍA PRESENCIAL | B40: MAESTRÍA EN ENFERMERÍA PRESENCIAL | C40: 6 | F40: MAESTRï¿½A EN ENFERMERï¿½A | G40: 8 | I40: 6 | J40: FACULTAD DE ENFERMERÍA Y REHABILITACIÓN | K40: 1 | L40: =K40+C40 -> 7 | M40: =IFERROR(VLOOKUP(A40,'Ajustes profesores'!$G$5:$I$151,3,0),0) -> 7 | N40: =G40-M40 -> 1 | R40: 1
A41: =B41 -> MAESTRÍA EN LINGÜÍSTICA PANHISPÁNICA - VIRTUAL | B41: MAESTRÍA EN LINGÜÍSTICA PANHISPÁNICA - VIRTUAL | C41: 2 | F41: MAESTRï¿½A EN LINGï¿½ï¿½STICA PANHISPï¿½NICA - CHï¿½A | G41: 2 | I41: 7 | J41: FACULTAD DE FILOSOFÍA Y CIENCIAS HUMANAS | K41: 0 | L41: =K41+C41 -> 2 | M41: =IFERROR(VLOOKUP(A41,'Ajustes profesores'!$G$5:$I$151,3,0),0) -> 2 | N41: =G41-M41 -> 0 | R41: 0
A42: =B42 -> MAESTRÍA EN TEOLOGÍA | B42: MAESTRÍA EN TEOLOGÍA | C42: 2 | F42: MAESTRï¿½A EN TEOLOGï¿½A - CHï¿½A | G42: 2 | I42: 7 | J42: FACULTAD DE FILOSOFÍA Y CIENCIAS HUMANAS | K42: 0 | L42: =K42+C42 -> 2 | M42: =IFERROR(VLOOKUP(A42,'Ajustes profesores'!$G$5:$I$151,3,0),0) -> 2 | N42: =G42-M42 -> 0 | R42: 0
A43: =B43 -> MAESTRÍA EN ANALÍTICA APLICADA | B43: MAESTRÍA EN ANALÍTICA APLICADA | C43: 7 | F43: MAESTRï¿½A EN ANALï¿½TICA APLICADA - CHï¿½A | G43: 7 | I43: 8 | J43: FACULTAD DE INGENIERÍA | K43: 0 | L43: =K43+C43 -> 7 | M43: =IFERROR(VLOOKUP(A43,'Ajustes profesores'!$G$5:$I$151,3,0),0) -> 7 | N43: =G43-M43 -> 0 | R43: 0
A44: =B44 -> MAESTRÍA EN DISEÑO Y GESTIÓN DE PROCESOS | B44: MAESTRÍA EN DISEÑO Y GESTIÓN DE PROCESOS | C44: 20 | F44: MAESTRï¿½A EN DISEï¿½O Y GESTIï¿½N DE PROCESOS - CHï¿½A | G44: 24 | I44: 8 | J44: FACULTAD DE INGENIERÍA | K44: 0 | L44: =K44+C44 -> 20 | M44: =IFERROR(VLOOKUP(A44,'Ajustes profesores'!$G$5:$I$151,3,0),0) -> 20 | N44: =G44-M44 -> 4 | R44: 0
A45: =B45 -> MAESTRÍA EN GERENCIA DE INGENIERÍA | B45: MAESTRÍA EN GERENCIA DE INGENIERÍA | C45: 3 | F45: MAESTRï¿½A EN GERENCIA DE INGENIERï¿½A - CHï¿½A | G45: 4 | I45: 8 | J45: FACULTAD DE INGENIERÍA | K45: 0 | L45: =K45+C45 -> 3 | M45: =IFERROR(VLOOKUP(A45,'Ajustes profesores'!$G$5:$I$151,3,0),0) -> 3 | N45: =G45-M45 -> 1 | R45: 0
A46: =B46 -> MAESTRÍA EN BIOÉTICA | B46: MAESTRÍA EN BIOÉTICA | C46: 2 | F46: MAESTRï¿½A EN BIOï¿½TICA | G46: 3 | I46: 1 | J46: FACULTAD DE MEDICINA | K46: 0 | L46: =K46+C46 -> 2 | M46: =IFERROR(VLOOKUP(A46,'Ajustes profesores'!$G$5:$I$151,3,0),0) -> 2 | N46: =G46-M46 -> 1 | R46: 0
A47: =B47 -> MAESTRÍA EN EDUCACIÓN MÉDICA | B47: MAESTRÍA EN EDUCACIÓN MÉDICA | C47: 1 | F47: MAESTRï¿½A EN EDUCACIï¿½N Mï¿½DICA | G47: 2 | I47: 1 | J47: FACULTAD DE MEDICINA | K47: 0 | L47: =K47+C47 -> 1 | M47: =IFERROR(VLOOKUP(A47,'Ajustes profesores'!$G$5:$I$151,3,0),0) -> 1 | N47: =G47-M47 -> 1 | R47: 0
A48: =B48 -> MAESTRÍA EN EPIDEMIOLOGÍA | B48: MAESTRÍA EN EPIDEMIOLOGÍA | C48: 2 | F48: MAESTRï¿½A EN EPIDEMIOLOGï¿½A | G48: 5 | I48: 1 | J48: FACULTAD DE MEDICINA | K48: 0 | L48: =K48+C48 -> 2 | M48: =IFERROR(VLOOKUP(A48,'Ajustes profesores'!$G$5:$I$151,3,0),0) -> 2 | N48: =G48-M48 -> 3 | R48: 0
... A55: =B55 -> MAESTRÍA EN GERENCIA INTERNACIONAL | B55: MAESTRÍA EN GERENCIA INTERNACIONAL | C55: 2 | F55: MAESTRï¿½A EN GERENCIA INTERNACIONAL | G55: 2 | I55: 2 | J55: ESCUELA INTERNACIONAL DE CIENCIAS ECONÓMICAS Y ADMINISTRATIVAS | K55: 0 | L55: =K55+C55 -> 2 | M55: =IFERROR(VLOOKUP(A55,'Ajustes profesores'!$G$5:$I$151,3,0),0) -> 2 | N55: =G55-M55 -> 0 | R55: 0
A56: =B56 -> MAESTRÍA EN DIDÁCTICA DEL INGLÉS PARA EL APRENDIZAJE AUTODIRIGIDO | B56: MAESTRÍA EN DIDÁCTICA DEL INGLÉS PARA EL APRENDIZAJE AUTODIRIGIDO | F56: MAESTRï¿½A EN DIDï¿½CTICA DEL INGLï¿½S PARA EL APRENDIZAJE AUTODIRIGIDO | G56: 0 | I56: 5 | J56: FACULTAD DE EDUCACIÓN | K56: 0 | L56: =K56+C56 -> 0 | M56: =IFERROR(VLOOKUP(A56,'Ajustes profesores'!$G$5:$I$151,3,0),0) -> 0 | N56: =G56-M56 -> 0 | R56: 0
A57: =B57 -> MAESTRÍA EN INNOVACIÓN EDUCATIVA MEDIADA POR TIC - VIRTUAL | B57: MAESTRÍA EN INNOVACIÓN EDUCATIVA MEDIADA POR TIC - VIRTUAL | C57: 4 | F57: MAESTRï¿½A EN INNOVACIï¿½N EDUCATIVA MEDIADA POR TIC | G57: 5 | I57: 5 | J57: FACULTAD DE EDUCACIÓN | K57: 0 | L57: =K57+C57 -> 4 | M57: =IFERROR(VLOOKUP(A57,'Ajustes profesores'!$G$5:$I$151,3,0),0) -> 4 | N57: =G57-M57 -> 1 | R57: 0
A58: =B58 -> MAESTRÍA EN PEDAGOGÍA E INVESTIGACIÓN EN EL AULA | B58: MAESTRÍA EN PEDAGOGÍA E INVESTIGACIÓN EN EL AULA | F58: MAESTRï¿½A EN PEDAGOGIA E INVESTIGACIï¿½N EN EL AULA | G58: 0 | I58: 5 | J58: FACULTAD DE EDUCACIÓN | K58: 0 | L58: =K58+C58 -> 0 | M58: =IFERROR(VLOOKUP(A58,'Ajustes profesores'!$G$5:$I$151,3,0),0) -> 0 | N58: =G58-M58 -> 0 | R58: 0
